Workbook

Sheet Question Bank
A1: Question ID | B1: Grade | C1: Part No. | D1: Part | E1: Part ID | F1: Section No. | G1: Section | H1: Section ID | I1: Topic ID | J1: Topic | K1: Question Sequence No. | L1: Learning Objective | M1: Question Type | N1: Question Category | O1: Difficulty | P1: Question Format | Q1: Visual Required | R1: Image Description | S1: Canva Prompt | T1: Bloom's Level | U1: Question | V1: Option A | W1: Option B | X1: Option C | Y1: Option D | Z1: Correct Option | AA1: Explanation | AB1: Future Ready Insight | AC1: Competency Assessed | AD1: Image File | AE1: Reviewer Comments | AF1: Reviewer Name | AG1: Review Date | AH1: Version
A2: 08_EM_OS_001 | B2: 8 | C2: 1 | D2: Entrepreneurship Mindset | E2: EM | F2: 1 | G2: Opportunity Spotting | H2: OS | I2: OS-T01 | J2: =Legacy_Backup!G2 -> Opportunity Spotting | K2: =TEXT(COUNTIF($E$2:E2,E2),"000") -> 001 | L2: =Legacy_Backup!H2 -> Identify useful opportunities from everyday problems | M2: =IFERROR(__xludf.DUMMYFUNCTION("IF(REGEXMATCH(UPPER(Legacy_Backup!I2),""KNOW""),""Know"",IF(REGEXMATCH(UPPER(Legacy_Backup!I2),""IMAGINE|INNOVATION""),""Imagine"",""Think""))"),"Think") -> Think | N2: =IFERROR(__xludf.DUMMYFUNCTION("IF(REGEXMATCH(UPPER(Legacy_Backup!J2),""FUTURE""),""Future-Oriented"",IF(REGEXMATCH(UPPER(Legacy_Backup!J2),""KNOWLEDGE""),""Knowledge-Based"",IF(REGEXMATCH(UPPER(Legacy_Backup!J2),""DECISION""),""Decision-Making"",""Situation-Based"")))"),"Situation-Based") -> Situation-Based | O2: =IF(UPPER(Legacy_Backup!K2)="HARD","Difficult",PROPER(Legacy_Backup!K2)) -> Easy | P2: =IF(UPPER(Legacy_Backup!O2)="YES","Visual","Text") -> Text | Q2: =PROPER(Legacy_Backup!O2) -> No | R2: =IF(UPPER(Legacy_Backup!O2)="YES",IF(Legacy_Backup!Y2<>"",Legacy_Backup!Y2,"Image required"),"NA") -> NA | S2: =IF(UPPER(Legacy_Backup!O2)="YES",IF(Legacy_Backup!Z2<>"",Legacy_Backup!Z2,"Prompt required"),"NA") -> NA | T2: =IF(Legacy_Backup!L2<>"",PROPER(Legacy_Backup!L2),"Apply") -> Apply | U2: =Legacy_Backup!P2 -> A school canteen has long queues and students often miss part of lunch. Which idea best turns this problem into an opportunity? | V2: =Legacy_Backup!Q2 -> Start a pre-order system for students | W2: =Legacy_Backup!R2 -> Sell more items only after lunch | X2: =Legacy_Backup!S2 -> Ask students to bring food every day | Y2: =Legacy_Backup!T2 -> Close one counter to reduce confusion | Z2: =Legacy_Backup!U2 -> A | AA2: =Legacy_Backup!W2 -> Start a pre-order system with fixed pickup slots is the best choice because it directly applies opportunity spotting to the situation and addresses the stated need with a practical, responsible action. | AB2: =Legacy_Backup!X2 -> Builds practical entrepreneurship for future study, work and responsible citizenship. | AC2: =Legacy_Backup!M2 -> Entrepreneurship | AD2: =IF(UPPER(Legacy_Backup!O2)="YES",A2&".png","NA") -> NA | AE2: =Legacy_Backup!AB2 | AH2: =IF(LEFT(Legacy_Backup!AC2,1)="v",Legacy_Backup!AC2,"v"&Legacy_Backup!AC2) -> v1.0
A3: 08_EM_CE_002 | B3: 8 | C3: 1 | D3: Entrepreneurship Mindset | E3: EM | F3: 6 | G3: Customer Understanding and Empathy | H3: CE | I3: CE-T01 | J3: =Legacy_Backup!G3 -> Customer Understanding | K3: =TEXT(COUNTIF($E$2:E3,E3),"000") -> 002 | L3: =Legacy_Backup!H3 -> Use customer feedback before designing a solution | M3: =IFERROR(__xludf.DUMMYFUNCTION("IF(REGEXMATCH(UPPER(Legacy_Backup!I3),""KNOW""),""Know"",IF(REGEXMATCH(UPPER(Legacy_Backup!I3),""IMAGINE|INNOVATION""),""Imagine"",""Think""))"),"Think") -> Think | N3: =IFERROR(__xludf.DUMMYFUNCTION("IF(REGEXMATCH(UPPER(Legacy_Backup!J3),""FUTURE""),""Future-Oriented"",IF(REGEXMATCH(UPPER(Legacy_Backup!J3),""KNOWLEDGE""),""Knowledge-Based"",IF(REGEXMATCH(UPPER(Legacy_Backup!J3),""DECISION""),""Decision-Making"",""Situation-Based"")))"),"Situation-Based") -> Situation-Based | O3: =IF(UPPER(Legacy_Backup!K3)="HARD","Difficult",PROPER(Legacy_Backup!K3)) -> Easy | P3: =IF(UPPER(Legacy_Backup!O3)="YES","Visual","Text") -> Text | Q3: =PROPER(Legacy_Backup!O3) -> No | R3: =IF(UPPER(Legacy_Backup!O3)="YES",IF(Legacy_Backup!Y3<>"",Legacy_Backup!Y3,"Image required"),"NA") -> NA | S3: =IF(UPPER(Legacy_Backup!O3)="YES",IF(Legacy_Backup!Z3<>"",Legacy_Backup!Z3,"Prompt required"),"NA") -> NA | T3: =IF(Legacy_Backup!L3<>"",PROPER(Legacy_Backup!L3),"Apply") -> Analyze | U3: =Legacy_Backup!P3 -> Riya wants to sell reusable water bottles at school. What should she do first? | V3: =Legacy_Backup!Q3 -> Order 200 bottles in her favourite colour | W3: =Legacy_Backup!R3 -> Ask students about their preferences /liking | X3: =Legacy_Backup!S3 -> Copy the most expensive bottle online | Y3: =Legacy_Backup!T3 -> Print posters before deciding the product | Z3: =Legacy_Backup!U3 -> B | AA3: =Legacy_Backup!W3 -> Ask students about size, price and features they prefer is the best choice because it directly applies customer understanding to the situation and addresses the stated need with a practical, responsible action. | AB3: =Legacy_Backup!X3 -> Builds practical entrepreneurship for future study, work and responsible citizenship. | AC3: =Legacy_Backup!M3 -> Entrepreneurship | AD3: =IF(UPPER(Legacy_Backup!O3)="YES",A3&".png","NA") -> NA | AE3: =Legacy_Backup!AB3 | AH3: =IF(LEFT(Legacy_Backup!AC3,1)="v",Legacy_Backup!AC3,"v"&Legacy_Backup!AC3) -> v1.0
A4: 08_EM_PR_003 | B4: 8 | C4: 1 | D4: Entrepreneurship Mindset | E4: EM | F4: 4 | G4: Planning and Resource Use | H4: PR | I4: PR-T01 | J4: =Legacy_Backup!G4 -> Planning and Resource Use | K4: =TEXT(COUNTIF($E$2:E4,E4),"000") -> 003 | L4: =Legacy_Backup!H4 -> Select a plan that uses limited resources wisely | M4: =IFERROR(__xludf.DUMMYFUNCTION("IF(REGEXMATCH(UPPER(Legacy_Backup!I4),""KNOW""),""Know"",IF(REGEXMATCH(UPPER(Legacy_Backup!I4),""IMAGINE|INNOVATION""),""Imagine"",""Think""))"),"Think") -> Think | N4: =IFERROR(__xludf.DUMMYFUNCTION("IF(REGEXMATCH(UPPER(Legacy_Backup!J4),""FUTURE""),""Future-Oriented"",IF(REGEXMATCH(UPPER(Legacy_Backup!J4),""KNOWLEDGE""),""Knowledge-Based"",IF(REGEXMATCH(UPPER(Legacy_Backup!J4),""DECISION""),""Decision-Making"",""Situation-Based"")))"),"Situation-Based") -> Situation-Based | O4: =IF(UPPER(Legacy_Backup!K4)="HARD","Difficult",PROPER(Legacy_Backup!K4)) -> Easy | P4: =IF(UPPER(Legacy_Backup!O4)="YES","Visual","Text") -> Visual | Q4: =PROPER(Legacy_Backup!O4) -> Yes | R4: =IF(UPPER(Legacy_Backup!O4)="YES",IF(Legacy_Backup!Y4<>"",Legacy_Backup!Y4,"Image required"),"NA") -> A clean Grade 8 educational table or chart illustrating: Four teams need the art room. The booking chart shows: Monday 2 teams, Tuesday 1, Wednesday 0, Thursday 3. Which day gives a new team the best chance to work without delay? | S4: =IF(UPPER(Legacy_Backup!O4)="YES",IF(Legacy_Backup!Z4<>"",Legacy_Backup!Z4,"Prompt required"),"NA") -> Create a clear, age-appropriate educational visual for Grade 8. Show only the information needed for this MCQ: Four teams need the art room. The booking chart shows: Monday 2 teams, Tuesday 1, Wednesday 0, Thursday 3. Which day gives a new team the best chance to work without delay? Use a light background, simple labels, high contrast, no answer clues, landscape 4:3. | T4: =IF(Legacy_Backup!L4<>"",PROPER(Legacy_Backup!L4),"Apply") -> Analyze | U4: =Legacy_Backup!P4 -> Four teams need the art room. Refer to the chart showing booking data. Which day gives a new team the best chance to work without delay? | V4: =Legacy_Backup!Q4 -> Monday | W4: =Legacy_Backup!R4 -> Tuesday | X4: =Legacy_Backup!S4 -> Wednesday | Y4: =Legacy_Backup!T4 -> Thursday | Z4: =Legacy_Backup!U4 -> C | AA4: =Legacy_Backup!W4 -> Wednesday is the best choice because it directly applies planning and resource use to the situation and addresses the stated need with a practical, responsible action. | AB4: =Legacy_Backup!X4 -> Builds practical entrepreneurship for future study, work and responsible citizenship. | AC4: =Legacy_Backup!M4 -> Entrepreneurship | AD4: =IF(UPPER(Legacy_Backup!O4)="YES",A4&".png","NA") -> 08_EM_PR_003.png | AE4: =Legacy_Backup!AB4 | AH4: =IF(LEFT(Legacy_Backup!AC4,1)="v",Legacy_Backup!AC4,"v"&Legacy_Backup!AC4) -> v1.0
A5: 08_EM_CE_004 | B5: 8 | C5: 1 | D5: Entrepreneurship Mindset | E5: EM | F5: 6 | G5: Customer Understanding and Empathy | H5: CE | I5: CE-T02 | J5: =Legacy_Backup!G5 -> Value Proposition | K5: =TEXT(COUNTIF($E$2:E5,E5),"000") -> 004 | L5: =Legacy_Backup!H5 -> Connect a product benefit to a customer need | M5: =IFERROR(__xludf.DUMMYFUNCTION("IF(REGEXMATCH(UPPER(Legacy_Backup!I5),""KNOW""),""Know"",IF(REGEXMATCH(UPPER(Legacy_Backup!I5),""IMAGINE|INNOVATION""),""Imagine"",""Think""))"),"Think") -> Think | N5: =IFERROR(__xludf.DUMMYFUNCTION("IF(REGEXMATCH(UPPER(Legacy_Backup!J5),""FUTURE""),""Future-Oriented"",IF(REGEXMATCH(UPPER(Legacy_Backup!J5),""KNOWLEDGE""),""Knowledge-Based"",IF(REGEXMATCH(UPPER(Legacy_Backup!J5),""DECISION""),""Decision-Making"",""Situation-Based"")))"),"Situation-Based") -> Situation-Based | O5: =IF(UPPER(Legacy_Backup!K5)="HARD","Difficult",PROPER(Legacy_Backup!K5)) -> Easy | P5: =IF(UPPER(Legacy_Backup!O5)="YES","Visual","Text") -> Visual | Q5: =PROPER(Legacy_Backup!O5) -> Yes | R5: =IF(UPPER(Legacy_Backup!O5)="YES",IF(Legacy_Backup!Y5<>"",Legacy_Backup!Y5,"Image required"),"NA") -> A clean Grade 8 educational real-life scene illustrating: An image shows two lunch boxes: Box P is stylish but leaks; Box Q is simple, leak-proof and easy to clean. Which is the stronger value proposition for students? | S5: =IF(UPPER(Legacy_Backup!O5)="YES",IF(Legacy_Backup!Z5<>"",Legacy_Backup!Z5,"Prompt required"),"NA") -> Create a clear, age-appropriate educational visual for Grade 8. Show only the information needed for this MCQ: An image shows two lunch boxes: Box P is stylish but leaks; Box Q is simple, leak-proof and easy to clean. Which is the stronger value proposition for students? Use a light background, simple labels, high contrast, no answer clues, landscape 4:3. | T5: =IF(Legacy_Backup!L5<>"",PROPER(Legacy_Backup!L5),"Apply") -> Analyze | U5: =Legacy_Backup!P5 -> An image shows two lunch boxes: Box P & Box Q . Which is the stronger value proposition for students to use? | V5: =Legacy_Backup!Q5 -> Box P, because style is always most important | W5: =Legacy_Backup!R5 -> Box P, because cleaning does not matter | X5: =Legacy_Backup!S5 -> Both are equal because they hold food | Y5: =Legacy_Backup!T5 -> Box Q, because it solves practical daily problems of leakage | Z5: =Legacy_Backup!U5 -> D | AA5: =Legacy_Backup!W5 -> Box Q, because it solves practical daily problems is the best choice because it directly applies value proposition to the situation and addresses the stated need with a practical, responsible action. | AB5: =Legacy_Backup!X5 -> Builds practical entrepreneurship for future study, work and responsible citizenship. | AC5: =Legacy_Backup!M5 -> Entrepreneurship | AD5: =IF(UPPER(Legacy_Backup!O5)="YES",A5&".png","NA") -> 08_EM_CE_004.png | AE5: =Legacy_Backup!AB5 | AH5: =IF(LEFT(Legacy_Backup!AC5,1)="v",Legacy_Backup!AC5,"v"&Legacy_Backup!AC5) -> v1.0
A6: 08_EM_RD_005 | B6: 8 | C6: 1 | D6: Entrepreneurship Mindset | E6: EM | F6: 3 | G6: Risk-Taking and Decision Making | H6: RD | I6: RD-T01 | J6: =Legacy_Backup!G6 -> Risk and Decision Making | K6: =TEXT(COUNTIF($E$2:E6,E6),"000") -> 005 | L6: =Legacy_Backup!H6 -> Reduce risk through a small test | M6: =IFERROR(__xludf.DUMMYFUNCTION("IF(REGEXMATCH(UPPER(Legacy_Backup!I6),""KNOW""),""Know"",IF(REGEXMATCH(UPPER(Legacy_Backup!I6),""IMAGINE|INNOVATION""),""Imagine"",""Think""))"),"Think") -> Think | N6: =IFERROR(__xludf.DUMMYFUNCTION("IF(REGEXMATCH(UPPER(Legacy_Backup!J6),""FUTURE""),""Future-Oriented"",IF(REGEXMATCH(UPPER(Legacy_Backup!J6),""KNOWLEDGE""),""Knowledge-Based"",IF(REGEXMATCH(UPPER(Legacy_Backup!J6),""DECISION""),""Decision-Making"",""Situation-Based"")))"),"Situation-Based") -> Situation-Based | O6: =IF(UPPER(Legacy_Backup!K6)="HARD","Difficult",PROPER(Legacy_Backup!K6)) -> Easy | P6: =IF(UPPER(Legacy_Backup!O6)="YES","Visual","Text") -> Text | Q6: =PROPER(Legacy_Backup!O6) -> No | R6: =IF(UPPER(Legacy_Backup!O6)="YES",IF(Legacy_Backup!Y6<>"",Legacy_Backup!Y6,"Image required"),"NA") -> NA | S6: =IF(UPPER(Legacy_Backup!O6)="YES",IF(Legacy_Backup!Z6<>"",Legacy_Backup!Z6,"Prompt required"),"NA") -> NA | T6: =IF(Legacy_Backup!L6<>"",PROPER(Legacy_Backup!L6),"Apply") -> Evaluate | U6: =Legacy_Backup!P6 -> A team can spend its full budget making 100 keychains or first make 10 samples. What is the wiser approach? | V6: =Legacy_Backup!Q6 -> Make 10, collect feedback, then decide | W6: =Legacy_Backup!R6 -> Make 100 immediately to save time | X6: =Legacy_Backup!S6 -> Buy a machine before testing demand | Y6: =Legacy_Backup!T6 -> Avoid making anything until everyone agrees | Z6: =Legacy_Backup!U6 -> A | AA6: =Legacy_Backup!W6 -> Make 10, collect feedback, then decide is the best choice because it directly applies risk and decision making to the situation and addresses the stated need with a practical, responsible action. | AB6: =Legacy_Backup!X6 -> Builds practical entrepreneurship for future study, work and responsible citizenship. | AC6: =Legacy_Backup!M6 -> Entrepreneurship | AD6: =IF(UPPER(Legacy_Backup!O6)="YES",A6&".png","NA") -> NA | AE6: =Legacy_Backup!AB6 | AH6: =IF(LEFT(Legacy_Backup!AC6,1)="v",Legacy_Backup!AC6,"v"&Legacy_Backup!AC6) -> v1.0
A7: 08_EM_OS_006 | B7: 8 | C7: 1 | D7: Entrepreneurship Mindset | E7: EM | F7: 1 | G7: Opportunity Spotting | H7: OS | I7: OS-T02 | J7: =Legacy_Backup!G7 -> Product Innovation | K7: =TEXT(COUNTIF($E$2:E7,E7),"000") -> 006 | L7: =Legacy_Backup!H7 -> Improve an existing solution for user benefit | M7: =IFERROR(__xludf.DUMMYFUNCTION("IF(REGEXMATCH(UPPER(Legacy_Backup!I7),""KNOW""),""Know"",IF(REGEXMATCH(UPPER(Legacy_Backup!I7),""IMAGINE|INNOVATION""),""Imagine"",""Think""))"),"Imagine") -> Imagine | N7: =IFERROR(__xludf.DUMMYFUNCTION("IF(REGEXMATCH(UPPER(Legacy_Backup!J7),""FUTURE""),""Future-Oriented"",IF(REGEXMATCH(UPPER(Legacy_Backup!J7),""KNOWLEDGE""),""Knowledge-Based"",IF(REGEXMATCH(UPPER(Legacy_Backup!J7),""DECISION""),""Decision-Making"",""Situation-Based"")))"),"Situation-Based") -> Situation-Based | O7: =IF(UPPER(Legacy_Backup!K7)="HARD","Difficult",PROPER(Legacy_Backup!K7)) -> Easy | P7: =IF(UPPER(Legacy_Backup!O7)="YES","Visual","Text") -> Text | Q7: =PROPER(Legacy_Backup!O7) -> No | R7: =IF(UPPER(Legacy_Backup!O7)="YES",IF(Legacy_Backup!Y7<>"",Legacy_Backup!Y7,"Image required"),"NA") -> NA | S7: =IF(UPPER(Legacy_Backup!O7)="YES",IF(Legacy_Backup!Z7<>"",Legacy_Backup!Z7,"Prompt required"),"NA") -> NA | T7: =IF(Legacy_Backup!L7<>"",PROPER(Legacy_Backup!L7),"Apply") -> Create | U7: =Legacy_Backup!P7 -> Students regularly forget to water classroom plants. Which idea is both innovative and practical? | V7: =Legacy_Backup!Q7 -> A poster saying plants need water | W7: =Legacy_Backup!R7 -> A low-cost moisture (dryness) indicator for soil | X7: =Legacy_Backup!S7 -> Replacing plants with plastic ones | Y7: =Legacy_Backup!T7 -> Asking one student to remember forever | Z7: =Legacy_Backup!U7 -> B | AA7: =Legacy_Backup!W7 -> A low-cost moisture indicator that changes colour when soil is dry is the best choice because it directly applies product innovation to the situation and addresses the stated need with a practical, responsible action. | AB7: =Legacy_Backup!X7 -> Builds practical entrepreneurship for future study, work and responsible citizenship. | AC7: =Legacy_Backup!M7 -> Entrepreneurship | AD7: =IF(UPPER(Legacy_Backup!O7)="YES",A7&".png","NA") -> NA | AE7: =Legacy_Backup!AB7 | AH7: =IF(LEFT(Legacy_Backup!AC7,1)="v",Legacy_Backup!AC7,"v"&Legacy_Backup!AC7) -> v1.0
A8: 08_EM_EF_007 | B8: 8 | C8: 1 | D8: Entrepreneurship Mindset | E8: EM | F8: 7 | G8: Ethics, Integrity, and Fairness | H8: EF | I8: EF-T01 | J8: =Legacy_Backup!G8 -> Ethics and Fairness | K8: =TEXT(COUNTIF($E$2:E8,E8),"000") -> 007 | L8: =Legacy_Backup!H8 -> Choose honest business behaviour | M8: =IFERROR(__xludf.DUMMYFUNCTION("IF(REGEXMATCH(UPPER(Legacy_Backup!I8),""KNOW""),""Know"",IF(REGEXMATCH(UPPER(Legacy_Backup!I8),""IMAGINE|INNOVATION""),""Imagine"",""Think""))"),"Think") -> Think | N8: =IFERROR(__xludf.DUMMYFUNCTION("IF(REGEXMATCH(UPPER(Legacy_Backup!J8),""FUTURE""),""Future-Oriented"",IF(REGEXMATCH(UPPER(Legacy_Backup!J8),""KNOWLEDGE""),""Knowledge-Based"",IF(REGEXMATCH(UPPER(Legacy_Backup!J8),""DECISION""),""Decision-Making"",""Situation-Based"")))"),"Situation-Based") -> Situation-Based | O8: =IF(UPPER(Legacy_Backup!K8)="HARD","Difficult",PROPER(Legacy_Backup!K8)) -> Easy | P8: =IF(UPPER(Legacy_Backup!O8)="YES","Visual","Text") -> Text | Q8: =PROPER(Legacy_Backup!O8) -> No | R8: =IF(UPPER(Legacy_Backup!O8)="YES",IF(Legacy_Backup!Y8<>"",Legacy_Backup!Y8,"Image required"),"NA") -> NA | S8: =IF(UPPER(Legacy_Backup!O8)="YES",IF(Legacy_Backup!Z8<>"",Legacy_Backup!Z8,"Prompt required"),"NA") -> NA | T8: =IF(Legacy_Backup!L8<>"",PROPER(Legacy_Backup!L8),"Apply") -> Apply | U8: =Legacy_Backup!P8 -> A seller notices that one batch of notebooks has weak binding. What should the seller do? | V8: =Legacy_Backup!Q8 -> Hide the problem with new covers | W8: =Legacy_Backup!R8 -> Sell them quickly to younger students | X8: =Legacy_Backup!S8 -> Tell buyers and replace the faulty notebooks | Y8: =Legacy_Backup!T8 -> Increase the price to appear premium | Z8: =Legacy_Backup!U8 -> C | AA8: =Legacy_Backup!W8 -> Tell buyers and replace or discount the faulty notebooks is the best choice because it directly applies ethics and fairness to the situation and addresses the stated need with a practical, responsible action. | AB8: =Legacy_Backup!X8 -> Builds practical entrepreneurship for future study, work and responsible citizenship. | AC8: =Legacy_Backup!M8 -> Entrepreneurship | AD8: =IF(UPPER(Legacy_Backup!O8)="YES",A8&".png","NA") -> NA | AE8: =Legacy_Backup!AB8 | AH8: =IF(LEFT(Legacy_Backup!AC8,1)="v",Legacy_Backup!AC8,"v"&Legacy_Backup!AC8) -> v1.0
A9: 08_EM_BA_008 | B9: 8 | C9: 1 | D9: Entrepreneurship Mindset | E9: EM | F9: 9 | G9: Business Acumen – Profit, Loss & Pricing | H9: BA | I9: BA-T01 | J9: =Legacy_Backup!G9 -> Pricing and Profit | K9: =TEXT(COUNTIF($E$2:E9,E9),"000") -> 008 | L9: =Legacy_Backup!H9 -> Choose a price using cost and customer value | M9: =IFERROR(__xludf.DUMMYFUNCTION("IF(REGEXMATCH(UPPER(Legacy_Backup!I9),""KNOW""),""Know"",IF(REGEXMATCH(UPPER(Legacy_Backup!I9),""IMAGINE|INNOVATION""),""Imagine"",""Think""))"),"Think") -> Think | N9: =IFERROR(__xludf.DUMMYFUNCTION("IF(REGEXMATCH(UPPER(Legacy_Backup!J9),""FUTURE""),""Future-Oriented"",IF(REGEXMATCH(UPPER(Legacy_Backup!J9),""KNOWLEDGE""),""Knowledge-Based"",IF(REGEXMATCH(UPPER(Legacy_Backup!J9),""DECISION""),""Decision-Making"",""Situation-Based"")))"),"Situation-Based") -> Situation-Based | O9: =IF(UPPER(Legacy_Backup!K9)="HARD","Difficult",PROPER(Legacy_Backup!K9)) -> Easy | P9: =IF(UPPER(Legacy_Backup!O9)="YES","Visual","Text") -> Text | Q9: =PROPER(Legacy_Backup!O9) -> No | R9: =IF(UPPER(Legacy_Backup!O9)="YES",IF(Legacy_Backup!Y9<>"",Legacy_Backup!Y9,"Image required"),"NA") -> NA | S9: =IF(UPPER(Legacy_Backup!O9)="YES",IF(Legacy_Backup!Z9<>"",Legacy_Backup!Z9,"Prompt required"),"NA") -> NA | T9: =IF(Legacy_Backup!L9<>"",PROPER(Legacy_Backup!L9),"Apply") -> Analyze | U9: =Legacy_Backup!P9 -> A bookmark costs ₹12 to make. Students say they would comfortably pay ₹20. Which price is most reasonable for a small profit? | V9: =Legacy_Backup!Q9 -> ₹8 | W9: =Legacy_Backup!R9 -> ₹12 | X9: =Legacy_Backup!S9 -> ₹40 | Y9: =Legacy_Backup!T9 -> ₹18 | Z9: =Legacy_Backup!U9 -> D | AA9: =Legacy_Backup!W9 -> ₹18 is the best choice because it directly applies pricing and profit to the situation and addresses the stated need with a practical, responsible action. | AB9: =Legacy_Backup!X9 -> Builds practical entrepreneurship for future study, work and responsible citizenship. | AC9: =Legacy_Backup!M9 -> Entrepreneurship | AD9: =IF(UPPER(Legacy_Backup!O9)="YES",A9&".png","NA") -> NA | AE9: =Legacy_Backup!AB9 | AH9: =IF(LEFT(Legacy_Backup!AC9,1)="v",Legacy_Backup!AC9,"v"&Legacy_Backup!AC9) -> v1.0
A10: 08_EM_TC_009 | B10: 8 | C10: 1 | D10: Entrepreneurship Mindset | E10: EM | F10: 5 | G10: Teamwork and Communication | H10: TC | I10: TC-T01 | J10: =Legacy_Backup!G10 -> Teamwork and Communication | K10: =TEXT(COUNTIF($E$2:E10,E10),"000") -> 009 | L10: =Legacy_Backup!H10 -> Assign work according to team strengths | M10: =IFERROR(__xludf.DUMMYFUNCTION("IF(REGEXMATCH(UPPER(Legacy_Backup!I10),""KNOW""),""Know"",IF(REGEXMATCH(UPPER(Legacy_Backup!I10),""IMAGINE|INNOVATION""),""Imagine"",""Think""))"),"Think") -> Think | N10: =IFERROR(__xludf.DUMMYFUNCTION("IF(REGEXMATCH(UPPER(Legacy_Backup!J10),""FUTURE""),""Future-Oriented"",IF(REGEXMATCH(UPPER(Legacy_Backup!J10),""KNOWLEDGE""),""Knowledge-Based"",IF(REGEXMATCH(UPPER(Legacy_Backup!J10),""DECISION""),""Decision-Making"",""Situation-Based"")))"),"Situation-Based") -> Situation-Based | O10: =IF(UPPER(Legacy_Backup!K10)="HARD","Difficult",PROPER(Legacy_Backup!K10)) -> Easy | P10: =IF(UPPER(Legacy_Backup!O10)="YES","Visual","Text") -> Visual | Q10: =PROPER(Legacy_Backup!O10) -> Yes | R10: =IF(UPPER(Legacy_Backup!O10)="YES",IF(Legacy_Backup!Y10<>"",Legacy_Backup!Y10,"Image required"),"NA") -> A clean Grade 8 educational table or chart illustrating: The team chart shows: Aman—drawing, Beena—speaking, Charu—calculations, Dev—organising. Who should present the final pitch? | S10: =IF(UPPER(Legacy_Backup!O10)="YES",IF(Legacy_Backup!Z10<>"",Legacy_Backup!Z10,"Prompt required"),"NA") -> Create a clear, age-appropriate educational visual for Grade 8. Show only the information needed for this MCQ: The team chart shows: Aman—drawing, Beena—speaking, Charu—calculations, Dev—organising. Who should present the final pitch? Use a light background, simple labels, high contrast, no answer clues, landscape 4:3. | T10: =IF(Legacy_Backup!L10<>"",PROPER(Legacy_Backup!L10),"Apply") -> Analyze | U10: =Legacy_Backup!P10 -> The team chart shows: Aman—drawing, Beena—speaking, Charu—calculations, Dev—organising. Who should present the final pitch? | V10: =Legacy_Backup!Q10 -> Beena | W10: =Legacy_Backup!R10 -> Aman | X10: =Legacy_Backup!S10 -> Charu | Y10: =Legacy_Backup!T10 -> Dev | Z10: =Legacy_Backup!U10 -> A | AA10: =Legacy_Backup!W10 -> Beena is the best choice because it directly applies teamwork and communication to the situation and addresses the stated need with a practical, responsible action. | AB10: =Legacy_Backup!X10 -> Builds practical entrepreneurship for future study, work and responsible citizenship. | AC10: =Legacy_Backup!M10 -> Entrepreneurship | AD10: =IF(UPPER(Legacy_Backup!O10)="YES",A10&".png","NA") -> 08_EM_TC_009.png | AE10: =Legacy_Backup!AB10 | AH10: =IF(LEFT(Legacy_Backup!AC10,1)="v",Legacy_Backup!AC10,"v"&Legacy_Backup!AC10) -> v1.0
A11: 08_EM_OI_010 | B11: 8 | C11: 1 | D11: Entrepreneurship Mindset | E11: EM | F11: 2 | G11: Ownership and Initiative | H11: OI | I11: OI-T01 | J11: =Legacy_Backup!G11 -> Ownership and Initiative | K11: =TEXT(COUNTIF($E$2:E11,E11),"000") -> 010 | L11: =Legacy_Backup!H11 -> Demonstrate initiative when a plan faces a barrier | M11: =IFERROR(__xludf.DUMMYFUNCTION("IF(REGEXMATCH(UPPER(Legacy_Backup!I11),""KNOW""),""Know"",IF(REGEXMATCH(UPPER(Legacy_Backup!I11),""IMAGINE|INNOVATION""),""Imagine"",""Think""))"),"Think") -> Think | N11: =IFERROR(__xludf.DUMMYFUNCTION("IF(REGEXMATCH(UPPER(Legacy_Backup!J11),""FUTURE""),""Future-Oriented"",IF(REGEXMATCH(UPPER(Legacy_Backup!J11),""KNOWLEDGE""),""Knowledge-Based"",IF(REGEXMATCH(UPPER(Legacy_Backup!J11),""DECISION""),""Decision-Making"",""Situation-Based"")))"),"Situation-Based") -> Situation-Based | O11: =IF(UPPER(Legacy_Backup!K11)="HARD","Difficult",PROPER(Legacy_Backup!K11)) -> Easy | P11: =IF(UPPER(Legacy_Backup!O11)="YES","Visual","Text") -> Visual | Q11: =PROPER(Legacy_Backup!O11) -> Yes | R11: =IF(UPPER(Legacy_Backup!O11)="YES",IF(Legacy_Backup!Y11<>"",Legacy_Backup!Y11,"Image required"),"NA") -> A clean Grade 8 educational real-life scene illustrating: A venue cancels one day before a student sale. What should the team leader do first? | S11: =IF(UPPER(Legacy_Backup!O11)="YES",IF(Legacy_Backup!Z11<>"",Legacy_Backup!Z11,"Prompt required"),"NA") -> Create a clear, age-appropriate educational visual for Grade 8. Show only the information needed for this MCQ: A venue cancels one day before a student sale. What should the team leader do first? Use a light background, simple labels, high contrast, no answer clues, landscape 4:3. | T11: =IF(Legacy_Backup!L11<>"",PROPER(Legacy_Backup!L11),"Apply") -> Analyze | U11: =Legacy_Backup!P11 -> A venue cancels one day before a student sale. What should the team leader do first? | V11: =Legacy_Backup!Q11 -> Wait for someone else to solve it | W11: =Legacy_Backup!R11 -> Quickly identify another safe venue | X11: =Legacy_Backup!S11 -> Cancel without telling customers | Y11: =Legacy_Backup!T11 -> Blame the venue online | Z11: =Legacy_Backup!U11 -> B | AA11: =Legacy_Backup!W11 -> Quickly identify another safe venue and inform everyone is the best choice because it directly applies ownership and initiative to the situation and addresses the stated need with a practical, responsible action. | AB11: =Legacy_Backup!X11 -> Builds practical entrepreneurship for future study, work and responsible citizenship. | AC11: =Legacy_Backup!M11 -> Entrepreneurship | AD11: =IF(UPPER(Legacy_Backup!O11)="YES",A11&".png","NA") -> 08_EM_OI_010.png | AE11: =Legacy_Backup!AB11 | AH11: =IF(LEFT(Legacy_Backup!AC11,1)="v",Legacy_Backup!AC11,"v"&Legacy_Backup!AC11) -> v1.0
A12: 08_EM_CE_011 | B12: 8 | C12: 1 | D12: Entrepreneurship Mindset | E12: EM | F12: 6 | G12: Customer Understanding and Empathy | H12: CE | I12: CE-T03 | J12: =Legacy_Backup!G12 -> Customer Understanding | K12: =TEXT(COUNTIF($E$2:E12,E12),"000") -> 011 | L12: =Legacy_Backup!H12 -> Improve a product using evidence | M12: =IFERROR(__xludf.DUMMYFUNCTION("IF(REGEXMATCH(UPPER(Legacy_Backup!I12),""KNOW""),""Know"",IF(REGEXMATCH(UPPER(Legacy_Backup!I12),""IMAGINE|INNOVATION""),""Imagine"",""Think""))"),"Think") -> Think | N12: =IFERROR(__xludf.DUMMYFUNCTION("IF(REGEXMATCH(UPPER(Legacy_Backup!J12),""FUTURE""),""Future-Oriented"",IF(REGEXMATCH(UPPER(Legacy_Backup!J12),""KNOWLEDGE""),""Knowledge-Based"",IF(REGEXMATCH(UPPER(Legacy_Backup!J12),""DECISION""),""Decision-Making"",""Situation-Based"")))"),"Situation-Based") -> Situation-Based | O12: =IF(UPPER(Legacy_Backup!K12)="HARD","Difficult",PROPER(Legacy_Backup!K12)) -> Easy | P12: =IF(UPPER(Legacy_Backup!O12)="YES","Visual","Text") -> Text | Q12: =PROPER(Legacy_Backup!O12) -> No | R12: =IF(UPPER(Legacy_Backup!O12)="YES",IF(Legacy_Backup!Y12<>"",Legacy_Backup!Y12,"Image required"),"NA") -> NA | S12: =IF(UPPER(Legacy_Backup!O12)="YES",IF(Legacy_Backup!Z12<>"",Legacy_Backup!Z12,"Prompt required"),"NA") -> NA | T12: =IF(Legacy_Backup!L12<>"",PROPER(Legacy_Backup!L12),"Apply") -> Evaluate | U12: =Legacy_Backup!P12 -> After testing a pencil grip, 8 of 10 students say it slips. What is the best next step? | V12: =Legacy_Backup!Q12 -> Ignore them because two students liked it | W12: =Legacy_Backup!R12 -> Produce 500 grips immediately | X12: =Legacy_Backup!S12 -> Change the material and test the new version | Y12: =Legacy_Backup!T12 -> Change only the logo | Z12: =Legacy_Backup!U12 -> C | AA12: =Legacy_Backup!W12 -> Change the material and test the new version is the best choice because it directly applies customer understanding to the situation and addresses the stated need with a practical, responsible action. | AB12: =Legacy_Backup!X12 -> Builds practical entrepreneurship for future study, work and responsible citizenship. | AC12: =Legacy_Backup!M12 -> Entrepreneurship | AD12: =IF(UPPER(Legacy_Backup!O12)="YES",A12&".png","NA") -> NA | AE12: =Legacy_Backup!AB12 | AH12: =IF(LEFT(Legacy_Backup!AC12,1)="v",Legacy_Backup!AC12,"v"&Legacy_Backup!AC12) -> v1.0
A13: 08_EM_CE_012 | B13: 8 | C13: 1 | D13: Entrepreneurship Mindset | E13: EM | F13: 6 | G13: Customer Understanding and Empathy | H13: CE | I13: CE-T04 | J13: =Legacy_Backup!G13 -> Visual – shopkeeper talking | K13: =TEXT(COUNTIF($E$2:E13,E13),"000") -> 012 | L13: =Legacy_Backup!H13 -> Identify customer understanding from a visual scene. | M13: =IFERROR(__xludf.DUMMYFUNCTION("IF(REGEXMATCH(UPPER(Legacy_Backup!I13),""KNOW""),""Know"",IF(REGEXMATCH(UPPER(Legacy_Backup!I13),""IMAGINE|INNOVATION""),""Imagine"",""Think""))"),"Think") -> Think | N13: =IFERROR(__xludf.DUMMYFUNCTION("IF(REGEXMATCH(UPPER(Legacy_Backup!J13),""FUTURE""),""Future-Oriented"",IF(REGEXMATCH(UPPER(Legacy_Backup!J13),""KNOWLEDGE""),""Knowledge-Based"",IF(REGEXMATCH(UPPER(Legacy_Backup!J13),""DECISION""),""Decision-Making"",""Situation-Based"")))"),"Situation-Based") -> Situation-Based | O13: =IF(UPPER(Legacy_Backup!K13)="HARD","Difficult",PROPER(Legacy_Backup!K13)) -> Medium | P13: =IF(UPPER(Legacy_Backup!O13)="YES","Visual","Text") -> Visual | Q13: =PROPER(Legacy_Backup!O13) -> Yes | R13: =IF(UPPER(Legacy_Backup!O13)="YES",IF(Legacy_Backup!Y13<>"",Legacy_Backup!Y13,"Image required"),"NA") -> Shopkeeper speaking with a customer and noting something on a pad. | S13: =IF(UPPER(Legacy_Backup!O13)="YES",IF(Legacy_Backup!Z13<>"",Legacy_Backup!Z13,"Prompt required"),"NA") -> Draw a small shop with a shopkeeper listening to a customer, writing notes on a notepad. Show them facing each other. | T13: =IF(Legacy_Backup!L13<>"",PROPER(Legacy_Backup!L13),"Apply") -> Analyze | U13: =Legacy_Backup!P13 -> A shopkeeper listens to a customer and writes notes. What is this most likely showing? | V13: =Legacy_Backup!Q13 -> Understanding customer needs | W13: =Legacy_Backup!R13 -> Preparing to-do task list for customer | X13: =Legacy_Backup!S13 -> Preparing to close the shop forever | Y13: =Legacy_Backup!T13 -> Counting old stock without any reason | Z13: =Legacy_Backup!U13 -> A | AA13: =Legacy_Backup!W13 -> Listening and noting details suggests the shopkeeper is learning about customer needs. | AB13: =Legacy_Backup!X13 -> Normalises feedback collection as part of everyday business. | AC13: =Legacy_Backup!M13 -> Observing customer interaction. | AD13: =IF(UPPER(Legacy_Backup!O13)="YES",A13&".png","NA") -> 08_EM_CE_012.png | AE13: =Legacy_Backup!AB13 | AH13: =IF(LEFT(Legacy_Backup!AC13,1)="v",Legacy_Backup!AC13,"v"&Legacy_Backup!AC13) -> v1.0
A14: 08_EM_EF_013 | B14: 8 | C14: 1 | D14: Entrepreneurship Mindset | E14: EM | F14: 7 | G14: Ethics, Integrity, and Fairness | H14: EF | I14: EF-T02 | J14: =Legacy_Backup!G14 -> Visual – two students sharing | K14: =TEXT(COUNTIF($E$2:E14,E14),"000") -> 013 | L14: =Legacy_Backup!H14 -> Identify fairness in a simple sharing situation. | M14: =IFERROR(__xludf.DUMMYFUNCTION("IF(REGEXMATCH(UPPER(Legacy_Backup!I14),""KNOW""),""Know"",IF(REGEXMATCH(UPPER(Legacy_Backup!I14),""IMAGINE|INNOVATION""),""Imagine"",""Think""))"),"Know") -> Know | N14: =IFERROR(__xludf.DUMMYFUNCTION("IF(REGEXMATCH(UPPER(Legacy_Backup!J14),""FUTURE""),""Future-Oriented"",IF(REGEXMATCH(UPPER(Legacy_Backup!J14),""KNOWLEDGE""),""Knowledge-Based"",IF(REGEXMATCH(UPPER(Legacy_Backup!J14),""DECISION""),""Decision-Making"",""Situation-Based"")))"),"Situation-Based") -> Situation-Based | O14: =IF(UPPER(Legacy_Backup!K14)="HARD","Difficult",PROPER(Legacy_Backup!K14)) -> Medium | P14: =IF(UPPER(Legacy_Backup!O14)="YES","Visual","Text") -> Visual | Q14: =PROPER(Legacy_Backup!O14) -> Yes | R14: =IF(UPPER(Legacy_Backup!O14)="YES",IF(Legacy_Backup!Y14<>"",Legacy_Backup!Y14,"Image required"),"NA") -> Two students sharing equal parts of a snack. | S14: =IF(UPPER(Legacy_Backup!O14)="YES",IF(Legacy_Backup!Z14<>"",Legacy_Backup!Z14,"Prompt required"),"NA") -> Draw two students splitting a snack into equal parts and smiling. | T14: =IF(Legacy_Backup!L14<>"",PROPER(Legacy_Backup!L14),"Apply") -> Apply | U14: =Legacy_Backup!P14 -> Look at the image shpwing two friends What does this show? | V14: =Legacy_Backup!Q14 -> Fair sharing between friends | W14: =Legacy_Backup!R14 -> Debating on the choice of snack | X14: =Legacy_Backup!S14 -> Fighting over marks | Y14: =Legacy_Backup!T14 -> Ignoring each other completely | Z14: =Legacy_Backup!U14 -> A | AA14: =Legacy_Backup!W14 -> Equal division of a snack reflects fairness and consideration. | AB14: =Legacy_Backup!X14 -> Connects everyday fairness with ethical thinking in business. | AC14: =Legacy_Backup!M14 -> Everyday fairness. | AD14: =IF(UPPER(Legacy_Backup!O14)="YES",A14&".png","NA") -> 08_EM_EF_013.png | AE14: =Legacy_Backup!AB14 | AH14: =IF(LEFT(Legacy_Backup!AC14,1)="v",Legacy_Backup!AC14,"v"&Legacy_Backup!AC14) -> v1.0
A15: 08_PSI_PC_001 | B15: 8 | C15: 5 | D15: Problem Solving & Innovation | E15: PSI | F15: 25 | G15: Problem Solving with Creativity | H15: PC | I15: PC-T01 | J15: =Legacy_Backup!G15 -> Root Cause Analysis | K15: =TEXT(COUNTIF($E$2:E15,E15),"000") -> 001 | L15: =Legacy_Backup!H15 -> Identify causes before selecting solutions | M15: =IFERROR(__xludf.DUMMYFUNCTION("IF(REGEXMATCH(UPPER(Legacy_Backup!I15),""KNOW""),""Know"",IF(REGEXMATCH(UPPER(Legacy_Backup!I15),""IMAGINE|INNOVATION""),""Imagine"",""Think""))"),"Think") -> Think | N15: =IFERROR(__xludf.DUMMYFUNCTION("IF(REGEXMATCH(UPPER(Legacy_Backup!J15),""FUTURE""),""Future-Oriented"",IF(REGEXMATCH(UPPER(Legacy_Backup!J15),""KNOWLEDGE""),""Knowledge-Based"",IF(REGEXMATCH(UPPER(Legacy_Backup!J15),""DECISION""),""Decision-Making"",""Situation-Based"")))"),"Situation-Based") -> Situation-Based | O15: =IF(UPPER(Legacy_Backup!K15)="HARD","Difficult",PROPER(Legacy_Backup!K15)) -> Easy | P15: =IF(UPPER(Legacy_Backup!O15)="YES","Visual","Text") -> Text | Q15: =PROPER(Legacy_Backup!O15) -> No | R15: =IF(UPPER(Legacy_Backup!O15)="YES",IF(Legacy_Backup!Y15<>"",Legacy_Backup!Y15,"Image required"),"NA") -> NA | S15: =IF(UPPER(Legacy_Backup!O15)="YES",IF(Legacy_Backup!Z15<>"",Legacy_Backup!Z15,"Prompt required"),"NA") -> NA | T15: =IF(Legacy_Backup!L15<>"",PROPER(Legacy_Backup!L15),"Apply") -> Analyze | U15: =Legacy_Backup!P15 -> The school bus is late on four days. What should students do first? | V15: =Legacy_Backup!Q15 -> Meet the administration & request a new bus immediately | W15: =Legacy_Backup!R15 -> Record departure times, routes and delay reasons | X15: =Legacy_Backup!S15 -> Assume the driver is careless and seek change | Y15: =Legacy_Backup!T15 -> Cancel the bus service for students | Z15: =Legacy_Backup!U15 -> B | AA15: =Legacy_Backup!W15 -> Record departure times, routes and delay reasons is the best choice because it directly applies root cause analysis to the situation and addresses the stated need with a practical, responsible action. | AB15: =Legacy_Backup!X15 -> Builds practical problem solving for future study, work and responsible citizenship. | AC15: =Legacy_Backup!M15 -> Problem Solving | AD15: =IF(UPPER(Legacy_Backup!O15)="YES",A15&".png","NA") -> NA | AE15: =Legacy_Backup!AB15 | AH15: =IF(LEFT(Legacy_Backup!AC15,1)="v",Legacy_Backup!AC15,"v"&Legacy_Backup!AC15) -> v1.0
A16: 08_PSI_PC_002 | B16: 8 | C16: 5 | D16: Problem Solving & Innovation | E16: PSI | F16: 25 | G16: Problem Solving with Creativity | H16: PC | I16: PC-T02 | J16: =Legacy_Backup!G16 -> Prioritisation | K16: =TEXT(COUNTIF($E$2:E16,E16),"000") -> 002 | L16: =Legacy_Backup!H16 -> Prioritise a safety-critical issue | M16: =IFERROR(__xludf.DUMMYFUNCTION("IF(REGEXMATCH(UPPER(Legacy_Backup!I16),""KNOW""),""Know"",IF(REGEXMATCH(UPPER(Legacy_Backup!I16),""IMAGINE|INNOVATION""),""Imagine"",""Think""))"),"Think") -> Think | N16: =IFERROR(__xludf.DUMMYFUNCTION("IF(REGEXMATCH(UPPER(Legacy_Backup!J16),""FUTURE""),""Future-Oriented"",IF(REGEXMATCH(UPPER(Legacy_Backup!J16),""KNOWLEDGE""),""Knowledge-Based"",IF(REGEXMATCH(UPPER(Legacy_Backup!J16),""DECISION""),""Decision-Making"",""Situation-Based"")))"),"Situation-Based") -> Situation-Based | O16: =IF(UPPER(Legacy_Backup!K16)="HARD","Difficult",PROPER(Legacy_Backup!K16)) -> Easy | P16: =IF(UPPER(Legacy_Backup!O16)="YES","Visual","Text") -> Visual | Q16: =PROPER(Legacy_Backup!O16) -> Yes | R16: =IF(UPPER(Legacy_Backup!O16)="YES",IF(Legacy_Backup!Y16<>"",Legacy_Backup!Y16,"Image required"),"NA") -> A clean Grade 8 educational table or chart illustrating: A team lists four issues: faded poster, loose electric wire, slow Wi-Fi and untidy shelf. Which should be solved first? | S16: =IF(UPPER(Legacy_Backup!O16)="YES",IF(Legacy_Backup!Z16<>"",Legacy_Backup!Z16,"Prompt required"),"NA") -> Create a clear, age-appropriate educational visual for Grade 8. Show only the information needed for this MCQ: A team lists four issues: faded poster, loose electric wire, slow Wi-Fi and untidy shelf. Which should be solved first? Use a light background, simple labels, high contrast, no answer clues, landscape 4:3. | T16: =IF(Legacy_Backup!L16<>"",PROPER(Legacy_Backup!L16),"Apply") -> Analyze | U16: =Legacy_Backup!P16 -> A team lists four issues: faded poster, loose electric wire, slow Wi-Fi and untidy shelf. Which should be solved first? | V16: =Legacy_Backup!Q16 -> Faded poster | W16: =Legacy_Backup!R16 -> Slow Wi-Fi | X16: =Legacy_Backup!S16 -> Loose electric wire | Y16: =Legacy_Backup!T16 -> Untidy shelf | Z16: =Legacy_Backup!U16 -> C | AA16: =Legacy_Backup!W16 -> Loose electric wire is the best choice because it directly applies prioritisation to the situation and addresses the stated need with a practical, responsible action. | AB16: =Legacy_Backup!X16 -> Builds practical problem solving for future study, work and responsible citizenship. | AC16: =Legacy_Backup!M16 -> Problem Solving | AD16: =IF(UPPER(Legacy_Backup!O16)="YES",A16&".png","NA") -> 08_PSI_PC_002.png | AE16: =Legacy_Backup!AB16 | AH16: =IF(LEFT(Legacy_Backup!AC16,1)="v",Legacy_Backup!AC16,"v"&Legacy_Backup!AC16) -> v1.0
A17: 08_PSI_DI_003 | B17: 8 | C17: 5 | D17: Problem Solving & Innovation | E17: PSI | F17: 29 | G17: Data-based Innovation | H17: DI | I17: DI-T01 | J17: =Legacy_Backup!G17 -> Data-based Problem Solving | K17: =TEXT(COUNTIF($E$2:E17,E17),"000") -> 003 | L17: =Legacy_Backup!H17 -> Use data to identify a pattern | M17: =IFERROR(__xludf.DUMMYFUNCTION("IF(REGEXMATCH(UPPER(Legacy_Backup!I17),""KNOW""),""Know"",IF(REGEXMATCH(UPPER(Legacy_Backup!I17),""IMAGINE|INNOVATION""),""Imagine"",""Think""))"),"Think") -> Think | N17: =IFERROR(__xludf.DUMMYFUNCTION("IF(REGEXMATCH(UPPER(Legacy_Backup!J17),""FUTURE""),""Future-Oriented"",IF(REGEXMATCH(UPPER(Legacy_Backup!J17),""KNOWLEDGE""),""Knowledge-Based"",IF(REGEXMATCH(UPPER(Legacy_Backup!J17),""DECISION""),""Decision-Making"",""Situation-Based"")))"),"Situation-Based") -> Situation-Based | O17: =IF(UPPER(Legacy_Backup!K17)="HARD","Difficult",PROPER(Legacy_Backup!K17)) -> Easy | P17: =IF(UPPER(Legacy_Backup!O17)="YES","Visual","Text") -> Visual | Q17: =PROPER(Legacy_Backup!O17) -> Yes | R17: =IF(UPPER(Legacy_Backup!O17)="YES",IF(Legacy_Backup!Y17<>"",Legacy_Backup!Y17,"Image required"),"NA") -> A clean Grade 8 educational real-life scene illustrating: A table shows library crowding: Monday 20, Tuesday 22, Wednesday 45, Thursday 21 students. Which day should get an extra librarian? | S17: =IF(UPPER(Legacy_Backup!O17)="YES",IF(Legacy_Backup!Z17<>"",Legacy_Backup!Z17,"Prompt required"),"NA") -> Create a clear, age-appropriate educational visual for Grade 8. Show only the information needed for this MCQ: A table shows library crowding: Monday 20, Tuesday 22, Wednesday 45, Thursday 21 students. Which day should get an extra librarian? Use a light background, simple labels, high contrast, no answer clues, landscape 4:3. | T17: =IF(Legacy_Backup!L17<>"",PROPER(Legacy_Backup!L17),"Apply") -> Analyze | U17: =Legacy_Backup!P17 -> A table shows library crowding on weekdays. Which day is best suited for an extra librarian? | V17: =Legacy_Backup!Q17 -> Monday | W17: =Legacy_Backup!R17 -> Tuesday | X17: =Legacy_Backup!S17 -> Thursday | Y17: =Legacy_Backup!T17 -> Wednesday | Z17: =Legacy_Backup!U17 -> D | AA17: =Legacy_Backup!W17 -> Wednesday is the best choice because it directly applies data-based problem solving to the situation and addresses the stated need with a practical, responsible action. | AB17: =Legacy_Backup!X17 -> Builds practical problem solving for future study, work and responsible citizenship. | AC17: =Legacy_Backup!M17 -> Problem Solving | AD17: =IF(UPPER(Legacy_Backup!O17)="YES",A17&".png","NA") -> 08_PSI_DI_003.png | AE17: =Legacy_Backup!AB17 | AH17: =IF(LEFT(Legacy_Backup!AC17,1)="v",Legacy_Backup!AC17,"v"&Legacy_Backup!AC17) -> v1.0
A18: 08_PSI_DE_004 | B18: 8 | C18: 5 | D18: Problem Solving & Innovation | E18: PSI | F18: 28 | G18: Design Thinking & Ethics | H18: DE | I18: DE-T01 | J18: =Legacy_Backup!G18 -> Design Thinking | K18: =TEXT(COUNTIF($E$2:E18,E18),"000") -> 004 | L18: =Legacy_Backup!H18 -> Select a user-centred design improvement | M18: =IFERROR(__xludf.DUMMYFUNCTION("IF(REGEXMATCH(UPPER(Legacy_Backup!I18),""KNOW""),""Know"",IF(REGEXMATCH(UPPER(Legacy_Backup!I18),""IMAGINE|INNOVATION""),""Imagine"",""Think""))"),"Think") -> Think | N18: =IFERROR(__xludf.DUMMYFUNCTION("IF(REGEXMATCH(UPPER(Legacy_Backup!J18),""FUTURE""),""Future-Oriented"",IF(REGEXMATCH(UPPER(Legacy_Backup!J18),""KNOWLEDGE""),""Knowledge-Based"",IF(REGEXMATCH(UPPER(Legacy_Backup!J18),""DECISION""),""Decision-Making"",""Situation-Based"")))"),"Situation-Based") -> Situation-Based | O18: =IF(UPPER(Legacy_Backup!K18)="HARD","Difficult",PROPER(Legacy_Backup!K18)) -> Easy | P18: =IF(UPPER(Legacy_Backup!O18)="YES","Visual","Text") -> Text | Q18: =PROPER(Legacy_Backup!O18) -> No | R18: =IF(UPPER(Legacy_Backup!O18)="YES",IF(Legacy_Backup!Y18<>"",Legacy_Backup!Y18,"Image required"),"NA") -> NA | S18: =IF(UPPER(Legacy_Backup!O18)="YES",IF(Legacy_Backup!Z18<>"",Legacy_Backup!Z18,"Prompt required"),"NA") -> NA | T18: =IF(Legacy_Backup!L18<>"",PROPER(Legacy_Backup!L18),"Apply") -> Evaluate | U18: =Legacy_Backup!P18 -> A classroom dustbin has waste scattered around it, quite often. Which redesign best addresses the observed problem? | V18: =Legacy_Backup!Q18 -> A wider opening with clear labels | W18: =Legacy_Backup!R18 -> A taller decorative flag | X18: =Legacy_Backup!S18 -> A darker colour only | Y18: =Legacy_Backup!T18 -> A locked lid with a key | Z18: =Legacy_Backup!U18 -> A | AA18: =Legacy_Backup!W18 -> A wider opening with clear labels is the best choice because it directly applies design thinking to the situation and addresses the stated need with a practical, responsible action. | AB18: =Legacy_Backup!X18 -> Builds practical problem solving for future study, work and responsible citizenship. | AC18: =Legacy_Backup!M18 -> Problem Solving | AD18: =IF(UPPER(Legacy_Backup!O18)="YES",A18&".png","NA") -> NA | AE18: =Legacy_Backup!AB18 | AH18: =IF(LEFT(Legacy_Backup!AC18,1)="v",Legacy_Backup!AC18,"v"&Legacy_Backup!AC18) -> v1.0
A19: 08_PSI_PC_005 | B19: 8 | C19: 5 | D19: Problem Solving & Innovation | E19: PSI | F19: 25 | G19: Problem Solving with Creativity | H19: PC | I19: PC-T03 | J19: =Legacy_Backup!G19 -> Resource Allocation | K19: =TEXT(COUNTIF($E$2:E19,E19),"000") -> 005 | L19: =Legacy_Backup!H19 -> Use limited resources for maximum impact | M19: =IFERROR(__xludf.DUMMYFUNCTION("IF(REGEXMATCH(UPPER(Legacy_Backup!I19),""KNOW""),""Know"",IF(REGEXMATCH(UPPER(Legacy_Backup!I19),""IMAGINE|INNOVATION""),""Imagine"",""Think""))"),"Imagine") -> Imagine | N19: =IFERROR(__xludf.DUMMYFUNCTION("IF(REGEXMATCH(UPPER(Legacy_Backup!J19),""FUTURE""),""Future-Oriented"",IF(REGEXMATCH(UPPER(Legacy_Backup!J19),""KNOWLEDGE""),""Knowledge-Based"",IF(REGEXMATCH(UPPER(Legacy_Backup!J19),""DECISION""),""Decision-Making"",""Situation-Based"")))"),"Situation-Based") -> Situation-Based | O19: =IF(UPPER(Legacy_Backup!K19)="HARD","Difficult",PROPER(Legacy_Backup!K19)) -> Easy | P19: =IF(UPPER(Legacy_Backup!O19)="YES","Visual","Text") -> Text | Q19: =PROPER(Legacy_Backup!O19) -> No | R19: =IF(UPPER(Legacy_Backup!O19)="YES",IF(Legacy_Backup!Y19<>"",Legacy_Backup!Y19,"Image required"),"NA") -> NA | S19: =IF(UPPER(Legacy_Backup!O19)="YES",IF(Legacy_Backup!Z19<>"",Legacy_Backup!Z19,"Prompt required"),"NA") -> NA | T19: =IF(Legacy_Backup!L19<>"",PROPER(Legacy_Backup!L19),"Apply") -> Create | U19: =Legacy_Backup!P19 -> A team has ₹500 to reduce water waste. A tap washer costs ₹50 and fixes one leaking tap; a poster costs ₹100. Five taps leak. What should the team prioritise? | V19: =Legacy_Backup!Q19 -> Five posters | W19: =Legacy_Backup!R19 -> Repair the five leaking taps | X19: =Legacy_Backup!S19 -> One poster and no repairs | Y19: =Legacy_Backup!T19 -> Save all the money without acting | Z19: =Legacy_Backup!U19 -> B | AA19: =Legacy_Backup!W19 -> Repair the five leaking taps is the best choice because it directly applies resource allocation to the situation and addresses the stated need with a practical, responsible action. | AB19: =Legacy_Backup!X19 -> Builds practical problem solving for future study, work and responsible citizenship. | AC19: =Legacy_Backup!M19 -> Problem Solving | AD19: =IF(UPPER(Legacy_Backup!O19)="YES",A19&".png","NA") -> NA | AE19: =Legacy_Backup!AB19 | AH19: =IF(LEFT(Legacy_Backup!AC19,1)="v",Legacy_Backup!AC19,"v"&Legacy_Backup!AC19) -> v1.0
A20: 08_PSI_IA_006 | B20: 8 | C20: 5 | D20: Problem Solving & Innovation | E20: PSI | F20: 26 | G20: Innovation & Adaptability | H20: IA | I20: IA-T01 | J20: =Legacy_Backup!G20 -> Innovation and Adaptability | K20: =TEXT(COUNTIF($E$2:E20,E20),"000") -> 006 | L20: =Legacy_Backup!H20 -> Adapt a solution after testing | M20: =IFERROR(__xludf.DUMMYFUNCTION("IF(REGEXMATCH(UPPER(Legacy_Backup!I20),""KNOW""),""Know"",IF(REGEXMATCH(UPPER(Legacy_Backup!I20),""IMAGINE|INNOVATION""),""Imagine"",""Think""))"),"Think") -> Think | N20: =IFERROR(__xludf.DUMMYFUNCTION("IF(REGEXMATCH(UPPER(Legacy_Backup!J20),""FUTURE""),""Future-Oriented"",IF(REGEXMATCH(UPPER(Legacy_Backup!J20),""KNOWLEDGE""),""Knowledge-Based"",IF(REGEXMATCH(UPPER(Legacy_Backup!J20),""DECISION""),""Decision-Making"",""Situation-Based"")))"),"Situation-Based") -> Situation-Based | O20: =IF(UPPER(Legacy_Backup!K20)="HARD","Difficult",PROPER(Legacy_Backup!K20)) -> Easy | P20: =IF(UPPER(Legacy_Backup!O20)="YES","Visual","Text") -> Text | Q20: =PROPER(Legacy_Backup!O20) -> No | R20: =IF(UPPER(Legacy_Backup!O20)="YES",IF(Legacy_Backup!Y20<>"",Legacy_Backup!Y20,"Image required"),"NA") -> NA | S20: =IF(UPPER(Legacy_Backup!O20)="YES",IF(Legacy_Backup!Z20<>"",Legacy_Backup!Z20,"Prompt required"),"NA") -> NA | T20: =IF(Legacy_Backup!L20<>"",PROPER(Legacy_Backup!L20),"Apply") -> Apply | U20: =Legacy_Backup!P20 -> A cardboard phone stand bends during testing. Which change is most likely to improve it? | V20: =Legacy_Backup!Q20 -> Add more decoration | W20: =Legacy_Backup!R20 -> Use thinner cardboard | X20: =Legacy_Backup!S20 -> Add folded triangular supports | Y20: =Legacy_Backup!T20 -> Make the phone heavier | Z20: =Legacy_Backup!U20 -> C | AA20: =Legacy_Backup!W20 -> Add folded triangular supports is the best choice because it directly applies innovation and adaptability to the situation and addresses the stated need with a practical, responsible action. | AB20: =Legacy_Backup!X20 -> Builds practical problem solving for future study, work and responsible citizenship. | AC20: =Legacy_Backup!M20 -> Problem Solving | AD20: =IF(UPPER(Legacy_Backup!O20)="YES",A20&".png","NA") -> NA | AE20: =Legacy_Backup!AB20 | AH20: =IF(LEFT(Legacy_Backup!AC20,1)="v",Legacy_Backup!AC20,"v"&Legacy_Backup!AC20) -> v1.0
A21: 08_PSI_DI_007 | B21: 8 | C21: 5 | D21: Problem Solving & Innovation | E21: PSI | F21: 29 | G21: Data-based Innovation | H21: DI | I21: DI-T02 | J21: =Legacy_Backup!G21 -> Visual – bar chart of app usage | K21: =TEXT(COUNTIF($E$2:E21,E21),"000") -> 007 | L21: =Legacy_Backup!H21 -> Read a simple bar chart. | M21: =IFERROR(__xludf.DUMMYFUNCTION("IF(REGEXMATCH(UPPER(Legacy_Backup!I21),""KNOW""),""Know"",IF(REGEXMATCH(UPPER(Legacy_Backup!I21),""IMAGINE|INNOVATION""),""Imagine"",""Think""))"),"Think") -> Think | N21: =IFERROR(__xludf.DUMMYFUNCTION("IF(REGEXMATCH(UPPER(Legacy_Backup!J21),""FUTURE""),""Future-Oriented"",IF(REGEXMATCH(UPPER(Legacy_Backup!J21),""KNOWLEDGE""),""Knowledge-Based"",IF(REGEXMATCH(UPPER(Legacy_Backup!J21),""DECISION""),""Decision-Making"",""Situation-Based"")))"),"Situation-Based") -> Situation-Based | O21: =IF(UPPER(Legacy_Backup!K21)="HARD","Difficult",PROPER(Legacy_Backup!K21)) -> Medium | P21: =IF(UPPER(Legacy_Backup!O21)="YES","Visual","Text") -> Visual | Q21: =PROPER(Legacy_Backup!O21) -> Yes | R21: =IF(UPPER(Legacy_Backup!O21)="YES",IF(Legacy_Backup!Y21<>"",Legacy_Backup!Y21,"Image required"),"NA") -> Bar chart showing app usage increasing from Monday to Friday. | S21: =IF(UPPER(Legacy_Backup!O21)="YES",IF(Legacy_Backup!Z21<>"",Legacy_Backup!Z21,"Prompt required"),"NA") -> Create a bar chart with days Monday to Friday and usage values rising across the week. | T21: =IF(Legacy_Backup!L21<>"",PROPER(Legacy_Backup!L21),"Apply") -> Analyze | U21: =Legacy_Backup!P21 -> A bar chart shows a gaming app usage over a week. What does this suggest? | V21: =Legacy_Backup!Q21 -> More students use the app toward the end of the week | W21: =Legacy_Backup!R21 -> Students never use the app on week ends | X21: =Legacy_Backup!S21 -> The app only works on Friday | Y21: =Legacy_Backup!T21 -> The chart has no meaning as night data is not mentioned | Z21: =Legacy_Backup!U21 -> A | AA21: =Legacy_Backup!W21 -> The tallest bar shows the highest usage level. | AB21: =Legacy_Backup!X21 -> Helps students understand how charts support decisions. | AC21: =Legacy_Backup!M21 -> Interpreting visual data. | AD21: =IF(UPPER(Legacy_Backup!O21)="YES",A21&".png","NA") -> 08_PSI_DI_007.png | AE21: =Legacy_Backup!AB21 | AH21: =IF(LEFT(Legacy_Backup!AC21,1)="v",Legacy_Backup!AC21,"v"&Legacy_Backup!AC21) -> v1.0
A22: 08_PSI_PC_008 | B22: 8 | C22: 5 | D22: Problem Solving & Innovation | E22: PSI | F22: 25 | G22: Problem Solving with Creativity | H22: PC | I22: PC-T04 | J22: =Legacy_Backup!G22 -> Pattern Recognition | K22: =TEXT(COUNTIF($E$2:E22,E22),"000") -> 008 | L22: =Legacy_Backup!H22 -> Recognise a simple operational pattern | M22: =IFERROR(__xludf.DUMMYFUNCTION("IF(REGEXMATCH(UPPER(Legacy_Backup!I22),""KNOW""),""Know"",IF(REGEXMATCH(UPPER(Legacy_Backup!I22),""IMAGINE|INNOVATION""),""Imagine"",""Think""))"),"Think") -> Think | N22: =IFERROR(__xludf.DUMMYFUNCTION("IF(REGEXMATCH(UPPER(Legacy_Backup!J22),""FUTURE""),""Future-Oriented"",IF(REGEXMATCH(UPPER(Legacy_Backup!J22),""KNOWLEDGE""),""Knowledge-Based"",IF(REGEXMATCH(UPPER(Legacy_Backup!J22),""DECISION""),""Decision-Making"",""Situation-Based"")))"),"Situation-Based") -> Situation-Based | O22: =IF(UPPER(Legacy_Backup!K22)="HARD","Difficult",PROPER(Legacy_Backup!K22)) -> Easy | P22: =IF(UPPER(Legacy_Backup!O22)="YES","Visual","Text") -> Visual | Q22: =PROPER(Legacy_Backup!O22) -> Yes | R22: =IF(UPPER(Legacy_Backup!O22)="YES",IF(Legacy_Backup!Y22<>"",Legacy_Backup!Y22,"Image required"),"NA") -> A clean Grade 8 educational table or chart illustrating: A machine flashes colours in this order: red, blue, blue, red, blue, blue. What comes next if the pattern repeats? | S22: =IF(UPPER(Legacy_Backup!O22)="YES",IF(Legacy_Backup!Z22<>"",Legacy_Backup!Z22,"Prompt required"),"NA") -> Create a clear, age-appropriate educational visual for Grade 8. Show only the information needed for this MCQ: A machine flashes colours in this order: red, blue, blue, red, blue, blue. What comes next if the pattern repeats? Use a light background, simple labels, high contrast, no answer clues, landscape 4:3. | T22: =IF(Legacy_Backup!L22<>"",PROPER(Legacy_Backup!L22),"Apply") -> Analyze | U22: =Legacy_Backup!P22 -> A machine flashes colours in the order as shown in the image. What comes next if the pattern repeats? | V22: =Legacy_Backup!Q22 -> Red | W22: =Legacy_Backup!R22 -> Blue | X22: =Legacy_Backup!S22 -> Green | Y22: =Legacy_Backup!T22 -> Yellow | Z22: =Legacy_Backup!U22 -> A | AA22: =Legacy_Backup!W22 -> Red is the best choice because it directly applies pattern recognition to the situation and addresses the stated need with a practical, responsible action. | AB22: =Legacy_Backup!X22 -> Builds practical problem solving for future study, work and responsible citizenship. | AC22: =Legacy_Backup!M22 -> Problem Solving | AD22: =IF(UPPER(Legacy_Backup!O22)="YES",A22&".png","NA") -> 08_PSI_PC_008.png | AE22: =Legacy_Backup!AB22 | AH22: =IF(LEFT(Legacy_Backup!AC22,1)="v",Legacy_Backup!AC22,"v"&Legacy_Backup!AC22) -> v1.0
A23: 08_PSI_VT_009 | B23: 8 | C23: 5 | D23: Problem Solving & Innovation | E23: PSI | F23: 27 | G23: Validation & Trial | H23: VT | I23: VT-T01 | J23: =Legacy_Backup!G23 -> Validation and Trial | K23: =TEXT(COUNTIF($E$2:E23,E23),"000") -> 009 | L23: =Legacy_Backup!H23 -> Choose an appropriate prototype test | M23: =IFERROR(__xludf.DUMMYFUNCTION("IF(REGEXMATCH(UPPER(Legacy_Backup!I23),""KNOW""),""Know"",IF(REGEXMATCH(UPPER(Legacy_Backup!I23),""IMAGINE|INNOVATION""),""Imagine"",""Think""))"),"Think") -> Think | N23: =IFERROR(__xludf.DUMMYFUNCTION("IF(REGEXMATCH(UPPER(Legacy_Backup!J23),""FUTURE""),""Future-Oriented"",IF(REGEXMATCH(UPPER(Legacy_Backup!J23),""KNOWLEDGE""),""Knowledge-Based"",IF(REGEXMATCH(UPPER(Legacy_Backup!J23),""DECISION""),""Decision-Making"",""Situation-Based"")))"),"Situation-Based") -> Situation-Based | O23: =IF(UPPER(Legacy_Backup!K23)="HARD","Difficult",PROPER(Legacy_Backup!K23)) -> Easy | P23: =IF(UPPER(Legacy_Backup!O23)="YES","Visual","Text") -> Visual | Q23: =PROPER(Legacy_Backup!O23) -> Yes | R23: =IF(UPPER(Legacy_Backup!O23)="YES",IF(Legacy_Backup!Y23<>"",Legacy_Backup!Y23,"Image required"),"NA") -> A clean Grade 8 educational real-life scene illustrating: A team designs a low-cost reading lamp. Which test gives the most useful evidence? | S23: =IF(UPPER(Legacy_Backup!O23)="YES",IF(Legacy_Backup!Z23<>"",Legacy_Backup!Z23,"Prompt required"),"NA") -> Create a clear, age-appropriate educational visual for Grade 8. Show only the information needed for this MCQ: A team designs a low-cost reading lamp. Which test gives the most useful evidence? Use a light background, simple labels, high contrast, no answer clues, landscape 4:3. | T23: =IF(Legacy_Backup!L23<>"",PROPER(Legacy_Backup!L23),"Apply") -> Analyze | U23: =Legacy_Backup!P23 -> A team designs a low-cost reading lamp. Which test gives the most useful evidence? | V23: =Legacy_Backup!Q23 -> Ask the designer whether it looks good | W23: =Legacy_Backup!R23 -> Let several students use it and record findings | X23: =Legacy_Backup!S23 -> Count how many stickers are on it | Y23: =Legacy_Backup!T23 -> Compare its body colour with another lamp | Z23: =Legacy_Backup!U23 -> B | AA23: =Legacy_Backup!W23 -> Let several students use it and record brightness, stability and heat is the best choice because it directly applies validation and trial to the situation and addresses the stated need with a practical, responsible action. | AB23: =Legacy_Backup!X23 -> Builds practical problem solving for future study, work and responsible citizenship. | AC23: =Legacy_Backup!M23 -> Problem Solving | AD23: =IF(UPPER(Legacy_Backup!O23)="YES",A23&".png","NA") -> 08_PSI_VT_009.png | AE23: =Legacy_Backup!AB23 | AH23: =IF(LEFT(Legacy_Backup!AC23,1)="v",Legacy_Backup!AC23,"v"&Legacy_Backup!AC23) -> v1.0
A24: 08_PSI_PC_010 | B24: 8 | C24: 5 | D24: Problem Solving & Innovation | E24: PSI | F24: 25 | G24: Problem Solving with Creativity | H24: PC | I24: PC-T05 | J24: =Legacy_Backup!G24 -> Cause and Effect | K24: =TEXT(COUNTIF($E$2:E24,E24),"000") -> 010 | L24: =Legacy_Backup!H24 -> Separate symptoms from likely causes | M24: =IFERROR(__xludf.DUMMYFUNCTION("IF(REGEXMATCH(UPPER(Legacy_Backup!I24),""KNOW""),""Know"",IF(REGEXMATCH(UPPER(Legacy_Backup!I24),""IMAGINE|INNOVATION""),""Imagine"",""Think""))"),"Think") -> Think | N24: =IFERROR(__xludf.DUMMYFUNCTION("IF(REGEXMATCH(UPPER(Legacy_Backup!J24),""FUTURE""),""Future-Oriented"",IF(REGEXMATCH(UPPER(Legacy_Backup!J24),""KNOWLEDGE""),""Knowledge-Based"",IF(REGEXMATCH(UPPER(Legacy_Backup!J24),""DECISION""),""Decision-Making"",""Situation-Based"")))"),"Situation-Based") -> Situation-Based | O24: =IF(UPPER(Legacy_Backup!K24)="HARD","Difficult",PROPER(Legacy_Backup!K24)) -> Easy | P24: =IF(UPPER(Legacy_Backup!O24)="YES","Visual","Text") -> Text | Q24: =PROPER(Legacy_Backup!O24) -> No | R24: =IF(UPPER(Legacy_Backup!O24)="YES",IF(Legacy_Backup!Y24<>"",Legacy_Backup!Y24,"Image required"),"NA") -> NA | S24: =IF(UPPER(Legacy_Backup!O24)="YES",IF(Legacy_Backup!Z24<>"",Legacy_Backup!Z24,"Prompt required"),"NA") -> NA | T24: =IF(Legacy_Backup!L24<>"",PROPER(Legacy_Backup!L24),"Apply") -> Evaluate | U24: =Legacy_Backup!P24 -> A classroom becomes very hot every afternoon. What is the best way to investigate the cause? | V24: =Legacy_Backup!Q24 -> Buy new curtains and install AC | W24: =Legacy_Backup!R24 -> Move the class permanently to a new place | X24: =Legacy_Backup!S24 -> Measure ventilation and temperature at different times | Y24: =Legacy_Backup!T24 -> Switch off all lights for one minute to cool down | Z24: =Legacy_Backup!U24 -> C | AA24: =Legacy_Backup!W24 -> Measure sunlight, ventilation and temperature at different times is the best choice because it directly applies cause and effect to the situation and addresses the stated need with a practical, responsible action. | AB24: =Legacy_Backup!X24 -> Builds practical problem solving for future study, work and responsible citizenship. | AC24: =Legacy_Backup!M24 -> Problem Solving | AD24: =IF(UPPER(Legacy_Backup!O24)="YES",A24&".png","NA") -> NA | AE24: =Legacy_Backup!AB24 | AH24: =IF(LEFT(Legacy_Backup!AC24,1)="v",Legacy_Backup!AC24,"v"&Legacy_Backup!AC24) -> v1.0
A25: 08_PSI_PC_011 | B25: 8 | C25: 5 | D25: Problem Solving & Innovation | E25: PSI | F25: 25 | G25: Problem Solving with Creativity | H25: PC | I25: PC-T06 | J25: =Legacy_Backup!G25 -> Decision Making | K25: =TEXT(COUNTIF($E$2:E25,E25),"000") -> 011 | L25: =Legacy_Backup!H25 -> Compare alternatives using agreed criteria | M25: =IFERROR(__xludf.DUMMYFUNCTION("IF(REGEXMATCH(UPPER(Legacy_Backup!I25),""KNOW""),""Know"",IF(REGEXMATCH(UPPER(Legacy_Backup!I25),""IMAGINE|INNOVATION""),""Imagine"",""Think""))"),"Imagine") -> Imagine | N25: =IFERROR(__xludf.DUMMYFUNCTION("IF(REGEXMATCH(UPPER(Legacy_Backup!J25),""FUTURE""),""Future-Oriented"",IF(REGEXMATCH(UPPER(Legacy_Backup!J25),""KNOWLEDGE""),""Knowledge-Based"",IF(REGEXMATCH(UPPER(Legacy_Backup!J25),""DECISION""),""Decision-Making"",""Situation-Based"")))"),"Situation-Based") -> Situation-Based | O25: =IF(UPPER(Legacy_Backup!K25)="HARD","Difficult",PROPER(Legacy_Backup!K25)) -> Easy | P25: =IF(UPPER(Legacy_Backup!O25)="YES","Visual","Text") -> Text | Q25: =PROPER(Legacy_Backup!O25) -> No | R25: =IF(UPPER(Legacy_Backup!O25)="YES",IF(Legacy_Backup!Y25<>"",Legacy_Backup!Y25,"Image required"),"NA") -> NA | S25: =IF(UPPER(Legacy_Backup!O25)="YES",IF(Legacy_Backup!Z25<>"",Legacy_Backup!Z25,"Prompt required"),"NA") -> NA | T25: =IF(Legacy_Backup!L25<>"",PROPER(Legacy_Backup!L25),"Apply") -> Create | U25: =Legacy_Backup!P25 -> Three bridge models are scored out of 5: P—strength 5, cost 2; Q—strength 4, cost 4; R—strength 2, cost 5. If both strength and cost matter equally, which is the balanced choice? | V25: =Legacy_Backup!Q25 -> P | W25: =Legacy_Backup!R25 -> R | X25: =Legacy_Backup!S25 -> All are equal | Y25: =Legacy_Backup!T25 -> Q | Z25: =Legacy_Backup!U25 -> D | AA25: =Legacy_Backup!W25 -> Q is the best choice because it directly applies decision making to the situation and addresses the stated need with a practical, responsible action. | AB25: =Legacy_Backup!X25 -> Builds practical problem solving for future study, work and responsible citizenship. | AC25: =Legacy_Backup!M25 -> Problem Solving | AD25: =IF(UPPER(Legacy_Backup!O25)="YES",A25&".png","NA") -> NA | AE25: =Legacy_Backup!AB25 | AH25: =IF(LEFT(Legacy_Backup!AC25,1)="v",Legacy_Backup!AC25,"v"&Legacy_Backup!AC25) -> v1.0
A26: 08_PSI_PC_012 | B26: 8 | C26: 5 | D26: Problem Solving & Innovation | E26: PSI | F26: 25 | G26: Problem Solving with Creativity | H26: PC | I26: PC-T07 | J26: =Legacy_Backup!G26 -> Creative Problem Solving | K26: =TEXT(COUNTIF($E$2:E26,E26),"000") -> 012 | L26: =Legacy_Backup!H26 -> Generate a practical improvement under constraints | M26: =IFERROR(__xludf.DUMMYFUNCTION("IF(REGEXMATCH(UPPER(Legacy_Backup!I26),""KNOW""),""Know"",IF(REGEXMATCH(UPPER(Legacy_Backup!I26),""IMAGINE|INNOVATION""),""Imagine"",""Think""))"),"Think") -> Think | N26: =IFERROR(__xludf.DUMMYFUNCTION("IF(REGEXMATCH(UPPER(Legacy_Backup!J26),""FUTURE""),""Future-Oriented"",IF(REGEXMATCH(UPPER(Legacy_Backup!J26),""KNOWLEDGE""),""Knowledge-Based"",IF(REGEXMATCH(UPPER(Legacy_Backup!J26),""DECISION""),""Decision-Making"",""Situation-Based"")))"),"Situation-Based") -> Situation-Based | O26: =IF(UPPER(Legacy_Backup!K26)="HARD","Difficult",PROPER(Legacy_Backup!K26)) -> Easy | P26: =IF(UPPER(Legacy_Backup!O26)="YES","Visual","Text") -> Text | Q26: =PROPER(Legacy_Backup!O26) -> No | R26: =IF(UPPER(Legacy_Backup!O26)="YES",IF(Legacy_Backup!Y26<>"",Legacy_Backup!Y26,"Image required"),"NA") -> NA | S26: =IF(UPPER(Legacy_Backup!O26)="YES",IF(Legacy_Backup!Z26<>"",Legacy_Backup!Z26,"Prompt required"),"NA") -> NA | T26: =IF(Legacy_Backup!L26<>"",PROPER(Legacy_Backup!L26),"Apply") -> Apply | U26: =Legacy_Backup!P26 -> Students need a handwashing reminder where electricity is unavailable. Which solution is most suitable? | V26: =Legacy_Backup!Q26 -> A waterproof flip-sign placed near the tap | W26: =Legacy_Backup!R26 -> A television screen with big messsage | X26: =Legacy_Backup!S26 -> A phone app with sound & internet | Y26: =Legacy_Backup!T26 -> A loudspeaker used all day with regular announcements | Z26: =Legacy_Backup!U26 -> A | AA26: =Legacy_Backup!W26 -> A waterproof flip-sign placed near the tap is the best choice because it directly applies creative problem solving to the situation and addresses the stated need with a practical, responsible action. | AB26: =Legacy_Backup!X26 -> Builds practical problem solving for future study, work and responsible citizenship. | AC26: =Legacy_Backup!M26 -> Problem Solving | AD26: =IF(UPPER(Legacy_Backup!O26)="YES",A26&".png","NA") -> NA | AE26: =Legacy_Backup!AB26 | AH26: =IF(LEFT(Legacy_Backup!AC26,1)="v",Legacy_Backup!AC26,"v"&Legacy_Backup!AC26) -> v1.0
A27: 08_ETD_AIM_001 | B27: 8 | C27: 2 | D27: Emerging Technologies & Digital Readiness | E27: ETD | F27: 13 | G27: Artificial Intelligence & Machine Learning | H27: AIM | I27: AIM-T01 | J27: =Legacy_Backup!G27 -> AI Responsibility | K27: =TEXT(COUNTIF($E$2:E27,E27),"000") -> 001 | L27: =Legacy_Backup!H27 -> Use AI transparently and responsibly | M27: =IFERROR(__xludf.DUMMYFUNCTION("IF(REGEXMATCH(UPPER(Legacy_Backup!I27),""KNOW""),""Know"",IF(REGEXMATCH(UPPER(Legacy_Backup!I27),""IMAGINE|INNOVATION""),""Imagine"",""Think""))"),"Think") -> Think | N27: =IFERROR(__xludf.DUMMYFUNCTION("IF(REGEXMATCH(UPPER(Legacy_Backup!J27),""FUTURE""),""Future-Oriented"",IF(REGEXMATCH(UPPER(Legacy_Backup!J27),""KNOWLEDGE""),""Knowledge-Based"",IF(REGEXMATCH(UPPER(Legacy_Backup!J27),""DECISION""),""Decision-Making"",""Situation-Based"")))"),"Situation-Based") -> Situation-Based | O27: =IF(UPPER(Legacy_Backup!K27)="HARD","Difficult",PROPER(Legacy_Backup!K27)) -> Easy | P27: =IF(UPPER(Legacy_Backup!O27)="YES","Visual","Text") -> Text | Q27: =PROPER(Legacy_Backup!O27) -> No | R27: =IF(UPPER(Legacy_Backup!O27)="YES",IF(Legacy_Backup!Y27<>"",Legacy_Backup!Y27,"Image required"),"NA") -> NA | S27: =IF(UPPER(Legacy_Backup!O27)="YES",IF(Legacy_Backup!Z27<>"",Legacy_Backup!Z27,"Prompt required"),"NA") -> NA | T27: =IF(Legacy_Backup!L27<>"",PROPER(Legacy_Backup!L27),"Apply") -> Analyze | U27: =Legacy_Backup!P27 -> Arjun uses an AI tool to suggest ideas for his science project. What should he do? | V27: =Legacy_Backup!Q27 -> Submit the output from AI and boost of being smart | W27: =Legacy_Backup!R27 -> Verify the facts, rewrite in his words and mention AI assistance | X27: =Legacy_Backup!S27 -> Hide the use of AI from his teacher and use reasoning to claim own | Y27: =Legacy_Backup!T27 -> Give output to another AI and make it better | Z27: =Legacy_Backup!U27 -> B | AA27: =Legacy_Backup!W27 -> Check the facts, rewrite in his words and mention AI assistance is the best choice because it directly applies ai responsibility to the situation and addresses the stated need with a practical, responsible action. | AB27: =Legacy_Backup!X27 -> Builds practical digital readiness for future study, work and responsible citizenship. | AC27: =Legacy_Backup!M27 -> Digital Readiness | AD27: =IF(UPPER(Legacy_Backup!O27)="YES",A27&".png","NA") -> NA | AE27: =Legacy_Backup!AB27 | AH27: =IF(LEFT(Legacy_Backup!AC27,1)="v",Legacy_Backup!AC27,"v"&Legacy_Backup!AC27) -> v1.0
A28: 08_ETD_DSC_002 | B28: 8 | C28: 2 | D28: Emerging Technologies & Digital Readiness | E28: ETD | F28: 15 | G28: Digital Safety & Cyber Security | H28: DSC | I28: DSC-T01 | J28: =Legacy_Backup!G28 -> Cyber Safety | K28: =TEXT(COUNTIF($E$2:E28,E28),"000") -> 002 | L28: =Legacy_Backup!H28 -> Respond safely to a suspicious message | M28: =IFERROR(__xludf.DUMMYFUNCTION("IF(REGEXMATCH(UPPER(Legacy_Backup!I28),""KNOW""),""Know"",IF(REGEXMATCH(UPPER(Legacy_Backup!I28),""IMAGINE|INNOVATION""),""Imagine"",""Think""))"),"Think") -> Think | N28: =IFERROR(__xludf.DUMMYFUNCTION("IF(REGEXMATCH(UPPER(Legacy_Backup!J28),""FUTURE""),""Future-Oriented"",IF(REGEXMATCH(UPPER(Legacy_Backup!J28),""KNOWLEDGE""),""Knowledge-Based"",IF(REGEXMATCH(UPPER(Legacy_Backup!J28),""DECISION""),""Decision-Making"",""Situation-Based"")))"),"Situation-Based") -> Situation-Based | O28: =IF(UPPER(Legacy_Backup!K28)="HARD","Difficult",PROPER(Legacy_Backup!K28)) -> Easy | P28: =IF(UPPER(Legacy_Backup!O28)="YES","Visual","Text") -> Visual | Q28: =PROPER(Legacy_Backup!O28) -> Yes | R28: =IF(UPPER(Legacy_Backup!O28)="YES",IF(Legacy_Backup!Y28<>"",Legacy_Backup!Y28,"Image required"),"NA") -> A clean Grade 8 educational table or chart illustrating: A message says, “Your game account will close in 10 minutes—send your password now.” What is the safest response? | S28: =IF(UPPER(Legacy_Backup!O28)="YES",IF(Legacy_Backup!Z28<>"",Legacy_Backup!Z28,"Prompt required"),"NA") -> Create a clear, age-appropriate educational visual for Grade 8. Show only the information needed for this MCQ: A message says, “Your game account will close in 10 minutes—send your password now.” What is the safest response? Use a light background, simple labels, high contrast, no answer clues, landscape 4:3. | T28: =IF(Legacy_Backup!L28<>"",PROPER(Legacy_Backup!L28),"Apply") -> Analyze | U28: =Legacy_Backup!P28 -> Abhishek receives this message on his mobile phone (refer to the image). What is the safest response? | V28: =Legacy_Backup!Q28 -> Send only half the password | W28: =Legacy_Backup!R28 -> Forward it to friends | X28: =Legacy_Backup!S28 -> Do not reply; verify the message | Y28: =Legacy_Backup!T28 -> Click the link to see what happens | Z28: =Legacy_Backup!U28 -> C | AA28: =Legacy_Backup!W28 -> Do not reply; report and verify through the official app is the best choice because it directly applies cyber safety to the situation and addresses the stated need with a practical, responsible action. | AB28: =Legacy_Backup!X28 -> Builds practical digital readiness for future study, work and responsible citizenship. | AC28: =Legacy_Backup!M28 -> Digital Readiness | AD28: =IF(UPPER(Legacy_Backup!O28)="YES",A28&".png","NA") -> 08_ETD_DSC_002.png | AE28: =Legacy_Backup!AB28 | AH28: =IF(LEFT(Legacy_Backup!AC28,1)="v",Legacy_Backup!AC28,"v"&Legacy_Backup!AC28) -> v1.0
A29: 08_ETD_CTL_003 | B29: 8 | C29: 2 | D29: Emerging Technologies & Digital Readiness | E29: ETD | F29: 11 | G29: Computational Thinking & Coding Logic | H29: CTL | I29: CTL-T01 | J29: =Legacy_Backup!G29 -> Flowcharts | K29: =TEXT(COUNTIF($E$2:E29,E29),"000") -> 003 | L29: =Legacy_Backup!H29 -> Apply computational thinking to design a simple solution | M29: =IFERROR(__xludf.DUMMYFUNCTION("IF(REGEXMATCH(UPPER(Legacy_Backup!I29),""KNOW""),""Know"",IF(REGEXMATCH(UPPER(Legacy_Backup!I29),""IMAGINE|INNOVATION""),""Imagine"",""Think""))"),"Imagine") -> Imagine | N29: =IFERROR(__xludf.DUMMYFUNCTION("IF(REGEXMATCH(UPPER(Legacy_Backup!J29),""FUTURE""),""Future-Oriented"",IF(REGEXMATCH(UPPER(Legacy_Backup!J29),""KNOWLEDGE""),""Knowledge-Based"",IF(REGEXMATCH(UPPER(Legacy_Backup!J29),""DECISION""),""Decision-Making"",""Situation-Based"")))"),"Future-Oriented") -> Future-Oriented | O29: =IF(UPPER(Legacy_Backup!K29)="HARD","Difficult",PROPER(Legacy_Backup!K29)) -> Difficult | P29: =IF(UPPER(Legacy_Backup!O29)="YES","Visual","Text") -> Visual | Q29: =PROPER(Legacy_Backup!O29) -> Yes | R29: =IF(UPPER(Legacy_Backup!O29)="YES",IF(Legacy_Backup!Y29<>"",Legacy_Backup!Y29,"Image required"),"NA") -> An illustration showing a young Indian student standing next to a whiteboard. On the whiteboard, there is a simple flowchart with boxes and arrows showing steps: "Start" at the top, then an arrow to a diamond-shaped box with text "Is it raining?" Inside the diamond, there are two arrows coming out. One arrow labelled "Yes" leads to a rectangular box saying "Take umbrella". The other arrow labelled "No" leads to a rectangular box saying "Go outside". Both paths then join and lead to a final box saying "End". The student is pointing at the flowchart with a marker in hand. The background shows a classroom setting with a window showing a cloudy sky. | S29: =IF(UPPER(Legacy_Backup!O29)="YES",IF(Legacy_Backup!Z29<>"",Legacy_Backup!Z29,"Prompt required"),"NA") -> A colorful cartoon-style illustration of a 14-year-old Indian student standing next to a whiteboard in a classroom. On the whiteboard, a simple flowchart is drawn with boxes and arrows showing: "Start" at the top, then an arrow to a diamond-shaped box with text "Is it raining?" Inside the diamond, two arrows come out—one labelled "Yes" leading to a rectangular box "Take umbrella" and one labelled "No" leading to a rectangular box "Go outside". Both paths then join and lead to a final box "End". The student is pointing at the flowchart with a marker. The background shows a classroom with desks and a window with a cloudy sky. Bright, engaging, educational style for 14-year-olds. | T29: =IF(Legacy_Backup!L29<>"",PROPER(Legacy_Backup!L29),"Apply") -> Apply | U29: =Legacy_Backup!P29 -> Look at the flowchart on the whiteboard. What decision does this flowchart help the student make? | V29: =Legacy_Backup!Q29 -> Enjoy the rain and go out | W29: =Legacy_Backup!R29 -> Whether to take an umbrella before going outside | X29: =Legacy_Backup!S29 -> Which umbrealla is best to use | Y29: =Legacy_Backup!T29 -> What time to leave for school in the morning | Z29: =Legacy_Backup!U29 -> B | AA29: =Legacy_Backup!W29 -> The flowchart shows a clear decision: if it is raining, take an umbrella; if not, go outside without one—helping decide whether to carry an umbrella. | AB29: =Legacy_Backup!X29 -> Flowcharts are visual tools used in coding and planning to map out decisions and processes—helping you think clearly before taking action. | AC29: =Legacy_Backup!M29 -> Ability to read and interpret flowcharts | AD29: =IF(UPPER(Legacy_Backup!O29)="YES",A29&".png","NA") -> 08_ETD_CTL_003.png | AE29: =Legacy_Backup!AB29 | AH29: =IF(LEFT(Legacy_Backup!AC29,1)="v",Legacy_Backup!AC29,"v"&Legacy_Backup!AC29) -> v1.0
A30: 08_ETD_DSC_004 | B30: 8 | C30: 2 | D30: Emerging Technologies & Digital Readiness | E30: ETD | F30: 15 | G30: Digital Safety & Cyber Security | H30: DSC | I30: DSC-T02 | J30: =Legacy_Backup!G30 -> Digital Privacy | K30: =TEXT(COUNTIF($E$2:E30,E30),"000") -> 004 | L30: =Legacy_Backup!H30 -> Choose privacy-protecting settings | M30: =IFERROR(__xludf.DUMMYFUNCTION("IF(REGEXMATCH(UPPER(Legacy_Backup!I30),""KNOW""),""Know"",IF(REGEXMATCH(UPPER(Legacy_Backup!I30),""IMAGINE|INNOVATION""),""Imagine"",""Think""))"),"Think") -> Think | N30: =IFERROR(__xludf.DUMMYFUNCTION("IF(REGEXMATCH(UPPER(Legacy_Backup!J30),""FUTURE""),""Future-Oriented"",IF(REGEXMATCH(UPPER(Legacy_Backup!J30),""KNOWLEDGE""),""Knowledge-Based"",IF(REGEXMATCH(UPPER(Legacy_Backup!J30),""DECISION""),""Decision-Making"",""Situation-Based"")))"),"Situation-Based") -> Situation-Based | O30: =IF(UPPER(Legacy_Backup!K30)="HARD","Difficult",PROPER(Legacy_Backup!K30)) -> Easy | P30: =IF(UPPER(Legacy_Backup!O30)="YES","Visual","Text") -> Text | Q30: =PROPER(Legacy_Backup!O30) -> No | R30: =IF(UPPER(Legacy_Backup!O30)="YES",IF(Legacy_Backup!Y30<>"",Legacy_Backup!Y30,"Image required"),"NA") -> NA | S30: =IF(UPPER(Legacy_Backup!O30)="YES",IF(Legacy_Backup!Z30<>"",Legacy_Backup!Z30,"Prompt required"),"NA") -> NA | T30: =IF(Legacy_Backup!L30<>"",PROPER(Legacy_Backup!L30),"Apply") -> Evaluate | U30: =Legacy_Backup!P30 -> Pooja's social media profile shows her phone number, home address, school name and hobby visible publicly. Which change is most important? | V30: =Legacy_Backup!Q30 -> Hide personal contact and location details | W30: =Legacy_Backup!R30 -> Add more photographs and interests | X30: =Legacy_Backup!S30 -> Use a brighter & recent profile picture | Y30: =Legacy_Backup!T30 -> Invite friends to share their contact numbers & photos | Z30: =Legacy_Backup!U30 -> A | AA30: =Legacy_Backup!W30 -> Hide personal contact and location details is the best choice because it directly applies digital privacy to the situation and addresses the stated need with a practical, responsible action. | AB30: =Legacy_Backup!X30 -> Builds practical digital readiness for future study, work and responsible citizenship. | AC30: =Legacy_Backup!M30 -> Digital Readiness | AD30: =IF(UPPER(Legacy_Backup!O30)="YES",A30&".png","NA") -> NA | AE30: =Legacy_Backup!AB30 | AH30: =IF(LEFT(Legacy_Backup!AC30,1)="v",Legacy_Backup!AC30,"v"&Legacy_Backup!AC30) -> v1.0
A31: 08_ETD_CTL_005 | B31: 8 | C31: 2 | D31: Emerging Technologies & Digital Readiness | E31: ETD | F31: 11 | G31: Computational Thinking & Coding Logic | H31: CTL | I31: CTL-T02 | J31: =Legacy_Backup!G31 -> Computational Thinking | K31: =TEXT(COUNTIF($E$2:E31,E31),"000") -> 005 | L31: =Legacy_Backup!H31 -> Break a task into logical steps | M31: =IFERROR(__xludf.DUMMYFUNCTION("IF(REGEXMATCH(UPPER(Legacy_Backup!I31),""KNOW""),""Know"",IF(REGEXMATCH(UPPER(Legacy_Backup!I31),""IMAGINE|INNOVATION""),""Imagine"",""Think""))"),"Imagine") -> Imagine | N31: =IFERROR(__xludf.DUMMYFUNCTION("IF(REGEXMATCH(UPPER(Legacy_Backup!J31),""FUTURE""),""Future-Oriented"",IF(REGEXMATCH(UPPER(Legacy_Backup!J31),""KNOWLEDGE""),""Knowledge-Based"",IF(REGEXMATCH(UPPER(Legacy_Backup!J31),""DECISION""),""Decision-Making"",""Situation-Based"")))"),"Situation-Based") -> Situation-Based | O31: =IF(UPPER(Legacy_Backup!K31)="HARD","Difficult",PROPER(Legacy_Backup!K31)) -> Easy | P31: =IF(UPPER(Legacy_Backup!O31)="YES","Visual","Text") -> Text | Q31: =PROPER(Legacy_Backup!O31) -> No | R31: =IF(UPPER(Legacy_Backup!O31)="YES",IF(Legacy_Backup!Y31<>"",Legacy_Backup!Y31,"Image required"),"NA") -> NA | S31: =IF(UPPER(Legacy_Backup!O31)="YES",IF(Legacy_Backup!Z31<>"",Legacy_Backup!Z31,"Prompt required"),"NA") -> NA | T31: =IF(Legacy_Backup!L31<>"",PROPER(Legacy_Backup!L31),"Apply") -> Create | U31: =Legacy_Backup!P31 -> A robot must collect paper, avoid chairs and reach a bin. What should the programmer do first? | V31: =Legacy_Backup!Q31 -> Write one long command and run the robot | W31: =Legacy_Backup!R31 -> Break the task into smaller steps (sense, avoid, move) | X31: =Legacy_Backup!S31 -> Study and remove non useful sensors | Y31: =Legacy_Backup!T31 -> Ask the robot to guess and operate on own | Z31: =Legacy_Backup!U31 -> B | AA31: =Legacy_Backup!W31 -> Break the task into sense, move, avoid and drop steps is the best choice because it directly applies computational thinking to the situation and addresses the stated need with a practical, responsible action. | AB31: =Legacy_Backup!X31 -> Builds practical digital readiness for future study, work and responsible citizenship. | AC31: =Legacy_Backup!M31 -> Digital Readiness | AD31: =IF(UPPER(Legacy_Backup!O31)="YES",A31&".png","NA") -> NA | AE31: =Legacy_Backup!AB31 | AH31: =IF(LEFT(Legacy_Backup!AC31,1)="v",Legacy_Backup!AC31,"v"&Legacy_Backup!AC31) -> v1.0
A32: 08_ETD_DLT_006 | B32: 8 | C32: 2 | D32: Emerging Technologies & Digital Readiness | E32: ETD | F32: 16 | G32: Data Literacy & Digital Tools | H32: DLT | I32: DLT-T01 | J32: =Legacy_Backup!G32 -> Technology for Inclusion | K32: =TEXT(COUNTIF($E$2:E32,E32),"000") -> 006 | L32: =Legacy_Backup!H32 -> Select technology that improves accessibility | M32: =IFERROR(__xludf.DUMMYFUNCTION("IF(REGEXMATCH(UPPER(Legacy_Backup!I32),""KNOW""),""Know"",IF(REGEXMATCH(UPPER(Legacy_Backup!I32),""IMAGINE|INNOVATION""),""Imagine"",""Think""))"),"Think") -> Think | N32: =IFERROR(__xludf.DUMMYFUNCTION("IF(REGEXMATCH(UPPER(Legacy_Backup!J32),""FUTURE""),""Future-Oriented"",IF(REGEXMATCH(UPPER(Legacy_Backup!J32),""KNOWLEDGE""),""Knowledge-Based"",IF(REGEXMATCH(UPPER(Legacy_Backup!J32),""DECISION""),""Decision-Making"",""Situation-Based"")))"),"Situation-Based") -> Situation-Based | O32: =IF(UPPER(Legacy_Backup!K32)="HARD","Difficult",PROPER(Legacy_Backup!K32)) -> Easy | P32: =IF(UPPER(Legacy_Backup!O32)="YES","Visual","Text") -> Text | Q32: =PROPER(Legacy_Backup!O32) -> No | R32: =IF(UPPER(Legacy_Backup!O32)="YES",IF(Legacy_Backup!Y32<>"",Legacy_Backup!Y32,"Image required"),"NA") -> NA | S32: =IF(UPPER(Legacy_Backup!O32)="YES",IF(Legacy_Backup!Z32<>"",Legacy_Backup!Z32,"Prompt required"),"NA") -> NA | T32: =IF(Legacy_Backup!L32<>"",PROPER(Legacy_Backup!L32),"Apply") -> Apply | U32: =Legacy_Backup!P32 -> Which feature best helps a visually impaired student use a learning website? | V32: =Legacy_Backup!Q32 -> Flashing advertisements | W32: =Legacy_Backup!R32 -> Tiny decorative text | X32: =Legacy_Backup!S32 -> Screen-reader labels and keyboard navigation | Y32: =Legacy_Backup!T32 -> Automatic video sound | Z32: =Legacy_Backup!U32 -> C | AA32: =Legacy_Backup!W32 -> Screen-reader labels and keyboard navigation is the best choice because it directly applies technology for inclusion to the situation and addresses the stated need with a practical, responsible action. | AB32: =Legacy_Backup!X32 -> Builds practical digital readiness for future study, work and responsible citizenship. | AC32: =Legacy_Backup!M32 -> Digital Readiness | AD32: =IF(UPPER(Legacy_Backup!O32)="YES",A32&".png","NA") -> NA | AE32: =Legacy_Backup!AB32 | AH32: =IF(LEFT(Legacy_Backup!AC32,1)="v",Legacy_Backup!AC32,"v"&Legacy_Backup!AC32) -> v1.0
A33: 08_ETD_DLT_007 | B33: 8 | C33: 2 | D33: Emerging Technologies & Digital Readiness | E33: ETD | F33: 16 | G33: Data Literacy & Digital Tools | H33: DLT | I33: DLT-T02 | J33: =Legacy_Backup!G33 -> Misinformation Detection | K33: =TEXT(COUNTIF($E$2:E33,E33),"000") -> 007 | L33: =Legacy_Backup!H33 -> Verify an online claim before sharing | M33: =IFERROR(__xludf.DUMMYFUNCTION("IF(REGEXMATCH(UPPER(Legacy_Backup!I33),""KNOW""),""Know"",IF(REGEXMATCH(UPPER(Legacy_Backup!I33),""IMAGINE|INNOVATION""),""Imagine"",""Think""))"),"Think") -> Think | N33: =IFERROR(__xludf.DUMMYFUNCTION("IF(REGEXMATCH(UPPER(Legacy_Backup!J33),""FUTURE""),""Future-Oriented"",IF(REGEXMATCH(UPPER(Legacy_Backup!J33),""KNOWLEDGE""),""Knowledge-Based"",IF(REGEXMATCH(UPPER(Legacy_Backup!J33),""DECISION""),""Decision-Making"",""Situation-Based"")))"),"Situation-Based") -> Situation-Based | O33: =IF(UPPER(Legacy_Backup!K33)="HARD","Difficult",PROPER(Legacy_Backup!K33)) -> Easy | P33: =IF(UPPER(Legacy_Backup!O33)="YES","Visual","Text") -> Text | Q33: =PROPER(Legacy_Backup!O33) -> No | R33: =IF(UPPER(Legacy_Backup!O33)="YES",IF(Legacy_Backup!Y33<>"",Legacy_Backup!Y33,"Image required"),"NA") -> NA | S33: =IF(UPPER(Legacy_Backup!O33)="YES",IF(Legacy_Backup!Z33<>"",Legacy_Backup!Z33,"Prompt required"),"NA") -> NA | T33: =IF(Legacy_Backup!L33<>"",PROPER(Legacy_Backup!L33),"Apply") -> Analyze | U33: =Legacy_Backup!P33 -> A viral post claims school is closed, but gives no source. What should a student do? | V33: =Legacy_Backup!Q33 -> Share it quickly | W33: =Legacy_Backup!R33 -> Believe it because many people liked it | X33: =Legacy_Backup!S33 -> Add an exciting caption | Y33: =Legacy_Backup!T33 -> Check the official school channel before sharing | Z33: =Legacy_Backup!U33 -> D | AA33: =Legacy_Backup!W33 -> Check the official school channel before sharing is the best choice because it directly applies misinformation detection to the situation and addresses the stated need with a practical, responsible action. | AB33: =Legacy_Backup!X33 -> Builds practical digital readiness for future study, work and responsible citizenship. | AC33: =Legacy_Backup!M33 -> Digital Readiness | AD33: =IF(UPPER(Legacy_Backup!O33)="YES",A33&".png","NA") -> NA | AE33: =Legacy_Backup!AB33 | AH33: =IF(LEFT(Legacy_Backup!AC33,1)="v",Legacy_Backup!AC33,"v"&Legacy_Backup!AC33) -> v1.0
A34: 08_ETD_DSC_008 | B34: 8 | C34: 2 | D34: Emerging Technologies & Digital Readiness | E34: ETD | F34: 15 | G34: Digital Safety & Cyber Security | H34: DSC | I34: DSC-T03 | J34: =Legacy_Backup!G34 -> Digital Footprint | K34: =TEXT(COUNTIF($E$2:E34,E34),"000") -> 008 | L34: =Legacy_Backup!H34 -> Recognise the long-term effect of online actions | M34: =IFERROR(__xludf.DUMMYFUNCTION("IF(REGEXMATCH(UPPER(Legacy_Backup!I34),""KNOW""),""Know"",IF(REGEXMATCH(UPPER(Legacy_Backup!I34),""IMAGINE|INNOVATION""),""Imagine"",""Think""))"),"Think") -> Think | N34: =IFERROR(__xludf.DUMMYFUNCTION("IF(REGEXMATCH(UPPER(Legacy_Backup!J34),""FUTURE""),""Future-Oriented"",IF(REGEXMATCH(UPPER(Legacy_Backup!J34),""KNOWLEDGE""),""Knowledge-Based"",IF(REGEXMATCH(UPPER(Legacy_Backup!J34),""DECISION""),""Decision-Making"",""Situation-Based"")))"),"Situation-Based") -> Situation-Based | O34: =IF(UPPER(Legacy_Backup!K34)="HARD","Difficult",PROPER(Legacy_Backup!K34)) -> Easy | P34: =IF(UPPER(Legacy_Backup!O34)="YES","Visual","Text") -> Visual | Q34: =PROPER(Legacy_Backup!O34) -> Yes | R34: =IF(UPPER(Legacy_Backup!O34)="YES",IF(Legacy_Backup!Y34<>"",Legacy_Backup!Y34,"Image required"),"NA") -> A clean Grade 8 educational table or chart illustrating: A diagram shows a post being copied, screenshotted and forwarded. What lesson does it communicate? | S34: =IF(UPPER(Legacy_Backup!O34)="YES",IF(Legacy_Backup!Z34<>"",Legacy_Backup!Z34,"Prompt required"),"NA") -> Create a clear, age-appropriate educational visual for Grade 8. Show only the information needed for this MCQ: A diagram shows a post being copied, screenshotted and forwarded. What lesson does it communicate? Use a light background, simple labels, high contrast, no answer clues, landscape 4:3. | T34: =IF(Legacy_Backup!L34<>"",PROPER(Legacy_Backup!L34),"Apply") -> Analyze | U34: =Legacy_Backup!P34 -> A person does this- copied, screenshotted and forwards a social media post. What lesson does it communicate? | V34: =Legacy_Backup!Q34 -> Online posts can remain and spread even after deletion | W34: =Legacy_Backup!R34 -> Deleted posts always disappear everywhere | X34: =Legacy_Backup!S34 -> Only famous people have digital footprints | Y34: =Legacy_Backup!T34 -> Screenshots cannot be shared | Z34: =Legacy_Backup!U34 -> A | AA34: =Legacy_Backup!W34 -> Online posts can remain and spread even after deletion is the best choice because it directly applies digital footprint to the situation and addresses the stated need with a practical, responsible action. | AB34: =Legacy_Backup!X34 -> Builds practical digital readiness for future study, work and responsible citizenship. | AC34: =Legacy_Backup!M34 -> Digital Readiness | AD34: =IF(UPPER(Legacy_Backup!O34)="YES",A34&".png","NA") -> 08_ETD_DSC_008.png | AE34: =Legacy_Backup!AB34 | AH34: =IF(LEFT(Legacy_Backup!AC34,1)="v",Legacy_Backup!AC34,"v"&Legacy_Backup!AC34) -> v1.0
A35: 08_ETD_FDT_009 | B35: 8 | C35: 2 | D35: Emerging Technologies & Digital Readiness | E35: ETD | F35: 14 | G35: Frontier & Deep Technologies | H35: FDT | I35: FDT-T01 | J35: =Legacy_Backup!G35 -> Emerging Technology | K35: =TEXT(COUNTIF($E$2:E35,E35),"000") -> 009 | L35: =Legacy_Backup!H35 -> Match a technology to a useful application | M35: =IFERROR(__xludf.DUMMYFUNCTION("IF(REGEXMATCH(UPPER(Legacy_Backup!I35),""KNOW""),""Know"",IF(REGEXMATCH(UPPER(Legacy_Backup!I35),""IMAGINE|INNOVATION""),""Imagine"",""Think""))"),"Think") -> Think | N35: =IFERROR(__xludf.DUMMYFUNCTION("IF(REGEXMATCH(UPPER(Legacy_Backup!J35),""FUTURE""),""Future-Oriented"",IF(REGEXMATCH(UPPER(Legacy_Backup!J35),""KNOWLEDGE""),""Knowledge-Based"",IF(REGEXMATCH(UPPER(Legacy_Backup!J35),""DECISION""),""Decision-Making"",""Situation-Based"")))"),"Situation-Based") -> Situation-Based | O35: =IF(UPPER(Legacy_Backup!K35)="HARD","Difficult",PROPER(Legacy_Backup!K35)) -> Easy | P35: =IF(UPPER(Legacy_Backup!O35)="YES","Visual","Text") -> Visual | Q35: =PROPER(Legacy_Backup!O35) -> Yes | R35: =IF(UPPER(Legacy_Backup!O35)="YES",IF(Legacy_Backup!Y35<>"",Legacy_Backup!Y35,"Image required"),"NA") -> A clean Grade 8 educational real-life scene illustrating: A farmer wants to check crop health across a large field quickly. Which tool is most suitable? | S35: =IF(UPPER(Legacy_Backup!O35)="YES",IF(Legacy_Backup!Z35<>"",Legacy_Backup!Z35,"Prompt required"),"NA") -> Create a clear, age-appropriate educational visual for Grade 8. Show only the information needed for this MCQ: A farmer wants to check crop health across a large field quickly. Which tool is most suitable? Use a light background, simple labels, high contrast, no answer clues, landscape 4:3. | T35: =IF(Legacy_Backup!L35<>"",PROPER(Legacy_Backup!L35),"Apply") -> Analyze | U35: =Legacy_Backup!P35 -> A farmer wants to check crop health across a large field quickly. Which method/tool is most suitable? | V35: =Legacy_Backup!Q35 -> A good running track in the field | W35: =Legacy_Backup!R35 -> A camera-equipped drone | X35: =Legacy_Backup!S35 -> A big team to go around and check the crop | Y35: =Legacy_Backup!T35 -> A barcode on the gate | Z35: =Legacy_Backup!U35 -> B | AA35: =Legacy_Backup!W35 -> A camera-equipped drone is the best choice because it directly applies emerging technology to the situation and addresses the stated need with a practical, responsible action. | AB35: =Legacy_Backup!X35 -> Builds practical digital readiness for future study, work and responsible citizenship. | AC35: =Legacy_Backup!M35 -> Digital Readiness | AD35: =IF(UPPER(Legacy_Backup!O35)="YES",A35&".png","NA") -> 08_ETD_FDT_009.png | AE35: =Legacy_Backup!AB35 | AH35: =IF(LEFT(Legacy_Backup!AC35,1)="v",Legacy_Backup!AC35,"v"&Legacy_Backup!AC35) -> v1.0
A36: 08_ETD_DLT_010 | B36: 8 | C36: 2 | D36: Emerging Technologies & Digital Readiness | E36: ETD | F36: 16 | G36: Data Literacy & Digital Tools | H36: DLT | I36: DLT-T03 | J36: =Legacy_Backup!G36 -> Digital Wellbeing | K36: =TEXT(COUNTIF($E$2:E36,E36),"000") -> 010 | L36: =Legacy_Backup!H36 -> Design a balanced technology routine | M36: =IFERROR(__xludf.DUMMYFUNCTION("IF(REGEXMATCH(UPPER(Legacy_Backup!I36),""KNOW""),""Know"",IF(REGEXMATCH(UPPER(Legacy_Backup!I36),""IMAGINE|INNOVATION""),""Imagine"",""Think""))"),"Think") -> Think | N36: =IFERROR(__xludf.DUMMYFUNCTION("IF(REGEXMATCH(UPPER(Legacy_Backup!J36),""FUTURE""),""Future-Oriented"",IF(REGEXMATCH(UPPER(Legacy_Backup!J36),""KNOWLEDGE""),""Knowledge-Based"",IF(REGEXMATCH(UPPER(Legacy_Backup!J36),""DECISION""),""Decision-Making"",""Situation-Based"")))"),"Situation-Based") -> Situation-Based | O36: =IF(UPPER(Legacy_Backup!K36)="HARD","Difficult",PROPER(Legacy_Backup!K36)) -> Easy | P36: =IF(UPPER(Legacy_Backup!O36)="YES","Visual","Text") -> Text | Q36: =PROPER(Legacy_Backup!O36) -> No | R36: =IF(UPPER(Legacy_Backup!O36)="YES",IF(Legacy_Backup!Y36<>"",Legacy_Backup!Y36,"Image required"),"NA") -> NA | S36: =IF(UPPER(Legacy_Backup!O36)="YES",IF(Legacy_Backup!Z36<>"",Legacy_Backup!Z36,"Prompt required"),"NA") -> NA | T36: =IF(Legacy_Backup!L36<>"",PROPER(Legacy_Backup!L36),"Apply") -> Evaluate | U36: =Legacy_Backup!P36 -> Which plan best supports healthy digital habits during study? | V36: =Legacy_Backup!Q36 -> Keep every notification on | W36: =Legacy_Backup!R36 -> Study with five entertainment tabs open | X36: =Legacy_Backup!S36 -> Use focus mode, take timed breaks and keep the phone away | Y36: =Legacy_Backup!T36 -> Use the phone throughout the night | Z36: =Legacy_Backup!U36 -> C | AA36: =Legacy_Backup!W36 -> Use focus mode, take timed breaks and keep the phone away is the best choice because it directly applies digital wellbeing to the situation and addresses the stated need with a practical, responsible action. | AB36: =Legacy_Backup!X36 -> Builds practical digital readiness for future study, work and responsible citizenship. | AC36: =Legacy_Backup!M36 -> Digital Readiness | AD36: =IF(UPPER(Legacy_Backup!O36)="YES",A36&".png","NA") -> NA | AE36: =Legacy_Backup!AB36 | AH36: =IF(LEFT(Legacy_Backup!AC36,1)="v",Legacy_Backup!AC36,"v"&Legacy_Backup!AC36) -> v1.0
A37: 08_FRG_SCA_001 | B37: 8 | C37: 3 | D37: Future Readiness & Global Awareness | E37: FRG | F37: 18 | G37: Sustainability & Climate Awareness | H37: SCA | I37: SCA-T01 | J37: =Legacy_Backup!G37 -> Climate Responsibility | K37: =TEXT(COUNTIF($E$2:E37,E37),"000") -> 001 | L37: =Legacy_Backup!H37 -> Choose a locally effective climate action | M37: =IFERROR(__xludf.DUMMYFUNCTION("IF(REGEXMATCH(UPPER(Legacy_Backup!I37),""KNOW""),""Know"",IF(REGEXMATCH(UPPER(Legacy_Backup!I37),""IMAGINE|INNOVATION""),""Imagine"",""Think""))"),"Imagine") -> Imagine | N37: =IFERROR(__xludf.DUMMYFUNCTION("IF(REGEXMATCH(UPPER(Legacy_Backup!J37),""FUTURE""),""Future-Oriented"",IF(REGEXMATCH(UPPER(Legacy_Backup!J37),""KNOWLEDGE""),""Knowledge-Based"",IF(REGEXMATCH(UPPER(Legacy_Backup!J37),""DECISION""),""Decision-Making"",""Situation-Based"")))"),"Situation-Based") -> Situation-Based | O37: =IF(UPPER(Legacy_Backup!K37)="HARD","Difficult",PROPER(Legacy_Backup!K37)) -> Easy | P37: =IF(UPPER(Legacy_Backup!O37)="YES","Visual","Text") -> Text | Q37: =PROPER(Legacy_Backup!O37) -> No | R37: =IF(UPPER(Legacy_Backup!O37)="YES",IF(Legacy_Backup!Y37<>"",Legacy_Backup!Y37,"Image required"),"NA") -> NA | S37: =IF(UPPER(Legacy_Backup!O37)="YES",IF(Legacy_Backup!Z37<>"",Legacy_Backup!Z37,"Prompt required"),"NA") -> NA | T37: =IF(Legacy_Backup!L37<>"",PROPER(Legacy_Backup!L37),"Apply") -> Create | U37: =Legacy_Backup!P37 -> A neighbourhood wants to reduce summer heat. Which action offers the broadest long-term benefit? | V37: =Legacy_Backup!Q37 -> Paint every wall black | W37: =Legacy_Backup!R37 -> Run outdoor coolers all day | X37: =Legacy_Backup!S37 -> Remove soil and add concrete | Y37: =Legacy_Backup!T37 -> Plant and care for native shade trees | Z37: =Legacy_Backup!U37 -> D | AA37: =Legacy_Backup!W37 -> Plant and care for native shade trees is the best choice because it directly applies climate responsibility to the situation and addresses the stated need with a practical, responsible action. | AB37: =Legacy_Backup!X37 -> Builds practical global awareness for future study, work and responsible citizenship. | AC37: =Legacy_Backup!M37 -> Global Awareness | AD37: =IF(UPPER(Legacy_Backup!O37)="YES",A37&".png","NA") -> NA | AE37: =Legacy_Backup!AB37 | AH37: =IF(LEFT(Legacy_Backup!AC37,1)="v",Legacy_Backup!AC37,"v"&Legacy_Backup!AC37) -> v1.0
A38: 08_FRG_GAW_002 | B38: 8 | C38: 3 | D38: Future Readiness & Global Awareness | E38: FRG | F38: 19 | G38: Global Awareness | H38: GAW | I38: GAW-T01 | J38: =Legacy_Backup!G38 -> Global Interdependence | K38: =TEXT(COUNTIF($E$2:E38,E38),"000") -> 002 | L38: =Legacy_Backup!H38 -> Understand how events in one place affect others | M38: =IFERROR(__xludf.DUMMYFUNCTION("IF(REGEXMATCH(UPPER(Legacy_Backup!I38),""KNOW""),""Know"",IF(REGEXMATCH(UPPER(Legacy_Backup!I38),""IMAGINE|INNOVATION""),""Imagine"",""Think""))"),"Think") -> Think | N38: =IFERROR(__xludf.DUMMYFUNCTION("IF(REGEXMATCH(UPPER(Legacy_Backup!J38),""FUTURE""),""Future-Oriented"",IF(REGEXMATCH(UPPER(Legacy_Backup!J38),""KNOWLEDGE""),""Knowledge-Based"",IF(REGEXMATCH(UPPER(Legacy_Backup!J38),""DECISION""),""Decision-Making"",""Situation-Based"")))"),"Situation-Based") -> Situation-Based | O38: =IF(UPPER(Legacy_Backup!K38)="HARD","Difficult",PROPER(Legacy_Backup!K38)) -> Easy | P38: =IF(UPPER(Legacy_Backup!O38)="YES","Visual","Text") -> Text | Q38: =PROPER(Legacy_Backup!O38) -> No | R38: =IF(UPPER(Legacy_Backup!O38)="YES",IF(Legacy_Backup!Y38<>"",Legacy_Backup!Y38,"Image required"),"NA") -> NA | S38: =IF(UPPER(Legacy_Backup!O38)="YES",IF(Legacy_Backup!Z38<>"",Legacy_Backup!Z38,"Prompt required"),"NA") -> NA | T38: =IF(Legacy_Backup!L38<>"",PROPER(Legacy_Backup!L38),"Apply") -> Apply | U38: =Legacy_Backup!P38 -> A port delay causes imported computer parts to arrive late. What does this best show? | V38: =Legacy_Backup!Q38 -> Global supply chains connect producers and buyers | W38: =Legacy_Backup!R38 -> Countries are completely independent and do not need imports | X38: =Legacy_Backup!S38 -> Only ports & shipping industry are affected by trade | Y38: =Legacy_Backup!T38 -> Local shops & manufacturers never depend on imports | Z38: =Legacy_Backup!U38 -> A | AA38: =Legacy_Backup!W38 -> Global supply chains connect producers and buyers is the best choice because it directly applies global interdependence to the situation and addresses the stated need with a practical, responsible action. | AB38: =Legacy_Backup!X38 -> Builds practical global awareness for future study, work and responsible citizenship. | AC38: =Legacy_Backup!M38 -> Global Awareness | AD38: =IF(UPPER(Legacy_Backup!O38)="YES",A38&".png","NA") -> NA | AE38: =Legacy_Backup!AB38 | AH38: =IF(LEFT(Legacy_Backup!AC38,1)="v",Legacy_Backup!AC38,"v"&Legacy_Backup!AC38) -> v1.0
A39: 08_FRG_FWC_003 | B39: 8 | C39: 3 | D39: Future Readiness & Global Awareness | E39: FRG | F39: 17 | G39: Future of Work, Careers & Lifelong Learning | H39: FWC | I39: FWC-T01 | J39: =Legacy_Backup!G39 -> Future Skills | K39: =TEXT(COUNTIF($E$2:E39,E39),"000") -> 003 | L39: =Legacy_Backup!H39 -> Interpret information about changing work | M39: =IFERROR(__xludf.DUMMYFUNCTION("IF(REGEXMATCH(UPPER(Legacy_Backup!I39),""KNOW""),""Know"",IF(REGEXMATCH(UPPER(Legacy_Backup!I39),""IMAGINE|INNOVATION""),""Imagine"",""Think""))"),"Think") -> Think | N39: =IFERROR(__xludf.DUMMYFUNCTION("IF(REGEXMATCH(UPPER(Legacy_Backup!J39),""FUTURE""),""Future-Oriented"",IF(REGEXMATCH(UPPER(Legacy_Backup!J39),""KNOWLEDGE""),""Knowledge-Based"",IF(REGEXMATCH(UPPER(Legacy_Backup!J39),""DECISION""),""Decision-Making"",""Situation-Based"")))"),"Situation-Based") -> Situation-Based | O39: =IF(UPPER(Legacy_Backup!K39)="HARD","Difficult",PROPER(Legacy_Backup!K39)) -> Easy | P39: =IF(UPPER(Legacy_Backup!O39)="YES","Visual","Text") -> Text | Q39: =PROPER(Legacy_Backup!O39) -> No | R39: =IF(UPPER(Legacy_Backup!O39)="YES",IF(Legacy_Backup!Y39<>"",Legacy_Backup!Y39,"Image required"),"NA") -> NA | S39: =IF(UPPER(Legacy_Backup!O39)="YES",IF(Legacy_Backup!Z39<>"",Legacy_Backup!Z39,"Prompt required"),"NA") -> NA | T39: =IF(Legacy_Backup!L39<>"",PROPER(Legacy_Backup!L39),"Apply") -> Analyze | U39: =Legacy_Backup!P39 -> A chart shows demand rising for data analysis, communication and green-energy skills. Which plan best prepares a student? | V39: =Legacy_Backup!Q39 -> Learn all 20 skills to prepare for everything | W39: =Legacy_Backup!R39 -> Learning digital, communication and sustainability skills | X39: =Legacy_Backup!S39 -> Learn technology usage and Driving skills for gig jobs | Y39: =Legacy_Backup!T39 -> Ignore new technology & advancements as they keep changing | Z39: =Legacy_Backup!U39 -> B | AA39: =Legacy_Backup!W39 -> Develop a mix of digital, communication and sustainability skills is the best choice because it directly applies future skills to the situation and addresses the stated need with a practical, responsible action. | AB39: =Legacy_Backup!X39 -> Builds practical global awareness for future study, work and responsible citizenship. | AC39: =Legacy_Backup!M39 -> Global Awareness | AD39: =IF(UPPER(Legacy_Backup!O39)="YES",A39&".png","NA") -> NA | AE39: =Legacy_Backup!AB39 | AH39: =IF(LEFT(Legacy_Backup!AC39,1)="v",Legacy_Backup!AC39,"v"&Legacy_Backup!AC39) -> v1.0
A40: 08_FRG_GAW_004 | B40: 8 | C40: 3 | D40: Future Readiness & Global Awareness | E40: FRG | F40: 19 | G40: Global Awareness | H40: GAW | I40: GAW-T02 | J40: =Legacy_Backup!G40 -> Cultural Awareness | K40: =TEXT(COUNTIF($E$2:E40,E40),"000") -> 004 | L40: =Legacy_Backup!H40 -> Respond respectfully to cultural differences | M40: =IFERROR(__xludf.DUMMYFUNCTION("IF(REGEXMATCH(UPPER(Legacy_Backup!I40),""KNOW""),""Know"",IF(REGEXMATCH(UPPER(Legacy_Backup!I40),""IMAGINE|INNOVATION""),""Imagine"",""Think""))"),"Think") -> Think | N40: =IFERROR(__xludf.DUMMYFUNCTION("IF(REGEXMATCH(UPPER(Legacy_Backup!J40),""FUTURE""),""Future-Oriented"",IF(REGEXMATCH(UPPER(Legacy_Backup!J40),""KNOWLEDGE""),""Knowledge-Based"",IF(REGEXMATCH(UPPER(Legacy_Backup!J40),""DECISION""),""Decision-Making"",""Situation-Based"")))"),"Situation-Based") -> Situation-Based | O40: =IF(UPPER(Legacy_Backup!K40)="HARD","Difficult",PROPER(Legacy_Backup!K40)) -> Easy | P40: =IF(UPPER(Legacy_Backup!O40)="YES","Visual","Text") -> Visual | Q40: =PROPER(Legacy_Backup!O40) -> Yes | R40: =IF(UPPER(Legacy_Backup!O40)="YES",IF(Legacy_Backup!Y40<>"",Legacy_Backup!Y40,"Image required"),"NA") -> A clean Grade 8 educational table or chart illustrating: An image shows students from several countries sharing different festival foods. What is the most respectful response? | S40: =IF(UPPER(Legacy_Backup!O40)="YES",IF(Legacy_Backup!Z40<>"",Legacy_Backup!Z40,"Prompt required"),"NA") -> Create a clear, age-appropriate educational visual for Grade 8. Show only the information needed for this MCQ: An image shows students from several countries sharing different festival foods. What is the most respectful response? Use a light background, simple labels, high contrast, no answer clues, landscape 4:3. | T40: =IF(Legacy_Backup!L40<>"",PROPER(Legacy_Backup!L40),"Apply") -> Analyze | U40: =Legacy_Backup!P40 -> A group of students is meeting. What is the most respectful response | V40: =Legacy_Backup!Q40 -> Make fun of unfamiliar food that they don't like | W40: =Legacy_Backup!R40 -> Insist everyone eat the same food in a sequence | X40: =Legacy_Backup!S40 -> Ask questions and learn about each tradition/food | Y40: =Legacy_Backup!T40 -> Avoid speaking to students from other cultures | Z40: =Legacy_Backup!U40 -> C | AA40: =Legacy_Backup!W40 -> Ask respectful questions and learn about each tradition is the best choice because it directly applies cultural awareness to the situation and addresses the stated need with a practical, responsible action. | AB40: =Legacy_Backup!X40 -> Builds practical global awareness for future study, work and responsible citizenship. | AC40: =Legacy_Backup!M40 -> Global Awareness | AD40: =IF(UPPER(Legacy_Backup!O40)="YES",A40&".png","NA") -> 08_FRG_GAW_004.png | AE40: =Legacy_Backup!AB40 | AH40: =IF(LEFT(Legacy_Backup!AC40,1)="v",Legacy_Backup!AC40,"v"&Legacy_Backup!AC40) -> v1.0
A41: 08_FRG_FWC_005 | B41: 8 | C41: 3 | D41: Future Readiness & Global Awareness | E41: FRG | F41: 17 | G41: Future of Work, Careers & Lifelong Learning | H41: FWC | I41: FWC-T02 | J41: =Legacy_Backup!G41 -> Future Skills | K41: =TEXT(COUNTIF($E$2:E41,E41),"000") -> 005 | L41: =Legacy_Backup!H41 -> Identify the skills that will remain valuable in the future workplace. | M41: =IFERROR(__xludf.DUMMYFUNCTION("IF(REGEXMATCH(UPPER(Legacy_Backup!I41),""KNOW""),""Know"",IF(REGEXMATCH(UPPER(Legacy_Backup!I41),""IMAGINE|INNOVATION""),""Imagine"",""Think""))"),"Know") -> Know | N41: =IFERROR(__xludf.DUMMYFUNCTION("IF(REGEXMATCH(UPPER(Legacy_Backup!J41),""FUTURE""),""Future-Oriented"",IF(REGEXMATCH(UPPER(Legacy_Backup!J41),""KNOWLEDGE""),""Knowledge-Based"",IF(REGEXMATCH(UPPER(Legacy_Backup!J41),""DECISION""),""Decision-Making"",""Situation-Based"")))"),"Knowledge-Based") -> Knowledge-Based | O41: =IF(UPPER(Legacy_Backup!K41)="HARD","Difficult",PROPER(Legacy_Backup!K41)) -> Easy | P41: =IF(UPPER(Legacy_Backup!O41)="YES","Visual","Text") -> Visual | Q41: =PROPER(Legacy_Backup!O41) -> Yes | R41: =IF(UPPER(Legacy_Backup!O41)="YES",IF(Legacy_Backup!Y41<>"",Legacy_Backup!Y41,"Image required"),"NA") -> Four students are shown performing different activities: Student A memorizing a textbook Student B solving a puzzle with teammates Student C copying notes from another student Student D decorating a notebook | S41: =IF(UPPER(Legacy_Backup!O41)="YES",IF(Legacy_Backup!Z41<>"",Legacy_Backup!Z41,"Prompt required"),"NA") -> Flat vector illustration, educational style, white background. Four Grade-8 students shown in four equal panels. Panel A: student memorizing from a textbook. Panel B: two students collaborating to solve a puzzle using sticky notes. Panel C: student copying homework. Panel D: student decorating a notebook. Bright colors, clean design, no text inside the illustration. | T41: =IF(Legacy_Backup!L41<>"",PROPER(Legacy_Backup!L41),"Apply") -> Apply | U41: =Legacy_Backup!P41 -> Look at the picture. Which student is demonstrating one of the most important future-ready skills? | V41: =Legacy_Backup!Q41 -> Student A | W41: =Legacy_Backup!R41 -> Student B | X41: =Legacy_Backup!S41 -> Student C | Y41: =Legacy_Backup!T41 -> Student D | Z41: =Legacy_Backup!U41 -> B | AA41: =Legacy_Backup!W41 -> Collaboration and problem-solving are considered among the most important future skills. | AB41: =Legacy_Backup!X41 -> The jobs of tomorrow will reward people who can work together to solve new and complex problems. | AC41: =Legacy_Backup!M41 -> Collaboration & Problem Solving | AD41: =IF(UPPER(Legacy_Backup!O41)="YES",A41&".png","NA") -> 08_FRG_FWC_005.png | AE41: =Legacy_Backup!AB41 | AH41: =IF(LEFT(Legacy_Backup!AC41,1)="v",Legacy_Backup!AC41,"v"&Legacy_Backup!AC41) -> v1.0
A42: 08_FRG_SCA_006 | B42: 8 | C42: 3 | D42: Future Readiness & Global Awareness | E42: FRG | F42: 18 | G42: Sustainability & Climate Awareness | H42: SCA | I42: SCA-T02 | J42: =Legacy_Backup!G42 -> Community Resilience | K42: =TEXT(COUNTIF($E$2:E42,E42),"000") -> 006 | L42: =Legacy_Backup!H42 -> Plan for a disruption using available resources | M42: =IFERROR(__xludf.DUMMYFUNCTION("IF(REGEXMATCH(UPPER(Legacy_Backup!I42),""KNOW""),""Know"",IF(REGEXMATCH(UPPER(Legacy_Backup!I42),""IMAGINE|INNOVATION""),""Imagine"",""Think""))"),"Think") -> Think | N42: =IFERROR(__xludf.DUMMYFUNCTION("IF(REGEXMATCH(UPPER(Legacy_Backup!J42),""FUTURE""),""Future-Oriented"",IF(REGEXMATCH(UPPER(Legacy_Backup!J42),""KNOWLEDGE""),""Knowledge-Based"",IF(REGEXMATCH(UPPER(Legacy_Backup!J42),""DECISION""),""Decision-Making"",""Situation-Based"")))"),"Situation-Based") -> Situation-Based | O42: =IF(UPPER(Legacy_Backup!K42)="HARD","Difficult",PROPER(Legacy_Backup!K42)) -> Easy | P42: =IF(UPPER(Legacy_Backup!O42)="YES","Visual","Text") -> Text | Q42: =PROPER(Legacy_Backup!O42) -> No | R42: =IF(UPPER(Legacy_Backup!O42)="YES",IF(Legacy_Backup!Y42<>"",Legacy_Backup!Y42,"Image required"),"NA") -> NA | S42: =IF(UPPER(Legacy_Backup!O42)="YES",IF(Legacy_Backup!Z42<>"",Legacy_Backup!Z42,"Prompt required"),"NA") -> NA | T42: =IF(Legacy_Backup!L42<>"",PROPER(Legacy_Backup!L42),"Apply") -> Evaluate | U42: =Legacy_Backup!P42 -> Heavy rain may cut electricity for a day. Which school plan is most useful? | V42: =Legacy_Backup!Q42 -> Prepare emergency lights and other measures | W42: =Legacy_Backup!R42 -> Wait until the power fails and do not act | X42: =Legacy_Backup!S42 -> Cancel all planning & activities | Y42: =Legacy_Backup!T42 -> Ask students & teachers to bring oil lamps | Z42: =Legacy_Backup!U42 -> A | AA42: =Legacy_Backup!W42 -> Prepare emergency lights, contacts and safe assembly procedures is the best choice because it directly applies community resilience to the situation and addresses the stated need with a practical, responsible action. | AB42: =Legacy_Backup!X42 -> Builds practical global awareness for future study, work and responsible citizenship. | AC42: =Legacy_Backup!M42 -> Global Awareness | AD42: =IF(UPPER(Legacy_Backup!O42)="YES",A42&".png","NA") -> NA | AE42: =Legacy_Backup!AB42 | AH42: =IF(LEFT(Legacy_Backup!AC42,1)="v",Legacy_Backup!AC42,"v"&Legacy_Backup!AC42) -> v1.0
A43: 08_FRG_GAW_007 | B43: 8 | C43: 3 | D43: Future Readiness & Global Awareness | E43: FRG | F43: 19 | G43: Global Awareness | H43: GAW | I43: GAW-T03 | J43: =Legacy_Backup!G43 -> Global Citizenship | K43: =TEXT(COUNTIF($E$2:E43,E43),"000") -> 007 | L43: =Legacy_Backup!H43 -> Choose responsible action on a shared global issue | M43: =IFERROR(__xludf.DUMMYFUNCTION("IF(REGEXMATCH(UPPER(Legacy_Backup!I43),""KNOW""),""Know"",IF(REGEXMATCH(UPPER(Legacy_Backup!I43),""IMAGINE|INNOVATION""),""Imagine"",""Think""))"),"Imagine") -> Imagine | N43: =IFERROR(__xludf.DUMMYFUNCTION("IF(REGEXMATCH(UPPER(Legacy_Backup!J43),""FUTURE""),""Future-Oriented"",IF(REGEXMATCH(UPPER(Legacy_Backup!J43),""KNOWLEDGE""),""Knowledge-Based"",IF(REGEXMATCH(UPPER(Legacy_Backup!J43),""DECISION""),""Decision-Making"",""Situation-Based"")))"),"Situation-Based") -> Situation-Based | O43: =IF(UPPER(Legacy_Backup!K43)="HARD","Difficult",PROPER(Legacy_Backup!K43)) -> Easy | P43: =IF(UPPER(Legacy_Backup!O43)="YES","Visual","Text") -> Text | Q43: =PROPER(Legacy_Backup!O43) -> No | R43: =IF(UPPER(Legacy_Backup!O43)="YES",IF(Legacy_Backup!Y43<>"",Legacy_Backup!Y43,"Image required"),"NA") -> NA | S43: =IF(UPPER(Legacy_Backup!O43)="YES",IF(Legacy_Backup!Z43<>"",Legacy_Backup!Z43,"Prompt required"),"NA") -> NA | T43: =IF(Legacy_Backup!L43<>"",PROPER(Legacy_Backup!L43),"Apply") -> Create | U43: =Legacy_Backup!P43 -> Students learn that electronic waste is often dumped unsafely. What is the best response? | V43: =Legacy_Backup!Q43 -> Throw devices into general waste | W43: =Legacy_Backup!R43 -> Use authorised e-waste collection and extend device life | X43: =Legacy_Backup!S43 -> Burn old wires | Y43: =Legacy_Backup!T43 -> Buy a new device every year | Z43: =Legacy_Backup!U43 -> B | AA43: =Legacy_Backup!W43 -> Use authorised e-waste collection and extend device life is the best choice because it directly applies global citizenship to the situation and addresses the stated need with a practical, responsible action. | AB43: =Legacy_Backup!X43 -> Builds practical global awareness for future study, work and responsible citizenship. | AC43: =Legacy_Backup!M43 -> Global Awareness | AD43: =IF(UPPER(Legacy_Backup!O43)="YES",A43&".png","NA") -> NA | AE43: =Legacy_Backup!AB43 | AH43: =IF(LEFT(Legacy_Backup!AC43,1)="v",Legacy_Backup!AC43,"v"&Legacy_Backup!AC43) -> v1.0
A44: 08_FRG_FWC_008 | B44: 8 | C44: 3 | D44: Future Readiness & Global Awareness | E44: FRG | F44: 17 | G44: Future of Work, Careers & Lifelong Learning | H44: FWC | I44: FWC-T03 | J44: =Legacy_Backup!G44 -> Adaptability | K44: =TEXT(COUNTIF($E$2:E44,E44),"000") -> 008 | L44: =Legacy_Backup!H44 -> Learn and adjust when future conditions change | M44: =IFERROR(__xludf.DUMMYFUNCTION("IF(REGEXMATCH(UPPER(Legacy_Backup!I44),""KNOW""),""Know"",IF(REGEXMATCH(UPPER(Legacy_Backup!I44),""IMAGINE|INNOVATION""),""Imagine"",""Think""))"),"Think") -> Think | N44: =IFERROR(__xludf.DUMMYFUNCTION("IF(REGEXMATCH(UPPER(Legacy_Backup!J44),""FUTURE""),""Future-Oriented"",IF(REGEXMATCH(UPPER(Legacy_Backup!J44),""KNOWLEDGE""),""Knowledge-Based"",IF(REGEXMATCH(UPPER(Legacy_Backup!J44),""DECISION""),""Decision-Making"",""Situation-Based"")))"),"Situation-Based") -> Situation-Based | O44: =IF(UPPER(Legacy_Backup!K44)="HARD","Difficult",PROPER(Legacy_Backup!K44)) -> Easy | P44: =IF(UPPER(Legacy_Backup!O44)="YES","Visual","Text") -> Text | Q44: =PROPER(Legacy_Backup!O44) -> No | R44: =IF(UPPER(Legacy_Backup!O44)="YES",IF(Legacy_Backup!Y44<>"",Legacy_Backup!Y44,"Image required"),"NA") -> NA | S44: =IF(UPPER(Legacy_Backup!O44)="YES",IF(Legacy_Backup!Z44<>"",Legacy_Backup!Z44,"Prompt required"),"NA") -> NA | T44: =IF(Legacy_Backup!L44<>"",PROPER(Legacy_Backup!L44),"Apply") -> Apply | U44: =Legacy_Backup!P44 -> A timeline shows a student learning spreadsheet skills, receiving feedback, practising, and improving. Which future-ready quality is shown? | V44: =Legacy_Backup!Q44 -> Avoiding change as feedback is not good | W44: =Legacy_Backup!R44 -> Working on an Excel sheet is the most important skill | X44: =Legacy_Backup!S44 -> Adaptability through continuous learning | Y44: =Legacy_Backup!T44 -> Waiting for perfect instructions from teacher | Z44: =Legacy_Backup!U44 -> C | AA44: =Legacy_Backup!W44 -> Adaptability through continuous learning is the best choice because it directly applies adaptability to the situation and addresses the stated need with a practical, responsible action. | AB44: =Legacy_Backup!X44 -> Builds practical global awareness for future study, work and responsible citizenship. | AC44: =Legacy_Backup!M44 -> Global Awareness | AD44: =IF(UPPER(Legacy_Backup!O44)="YES",A44&".png","NA") -> NA | AE44: =Legacy_Backup!AB44 | AH44: =IF(LEFT(Legacy_Backup!AC44,1)="v",Legacy_Backup!AC44,"v"&Legacy_Backup!AC44) -> v1.0
A45: 08_FRD_MMD_001 | B45: 8 | C45: 4 | D45: Financial Readiness | E45: FRD | F45: 22 | G45: Money Management & Smart Decision Making | H45: MMD | I45: MMD-T01 | J45: =Legacy_Backup!G45 -> Budgeting | K45: =TEXT(COUNTIF($E$2:E45,E45),"000") -> 001 | L45: =Legacy_Backup!H45 -> Distinguish needs from wants in a limited budget | M45: =IFERROR(__xludf.DUMMYFUNCTION("IF(REGEXMATCH(UPPER(Legacy_Backup!I45),""KNOW""),""Know"",IF(REGEXMATCH(UPPER(Legacy_Backup!I45),""IMAGINE|INNOVATION""),""Imagine"",""Think""))"),"Think") -> Think | N45: =IFERROR(__xludf.DUMMYFUNCTION("IF(REGEXMATCH(UPPER(Legacy_Backup!J45),""FUTURE""),""Future-Oriented"",IF(REGEXMATCH(UPPER(Legacy_Backup!J45),""KNOWLEDGE""),""Knowledge-Based"",IF(REGEXMATCH(UPPER(Legacy_Backup!J45),""DECISION""),""Decision-Making"",""Situation-Based"")))"),"Situation-Based") -> Situation-Based | O45: =IF(UPPER(Legacy_Backup!K45)="HARD","Difficult",PROPER(Legacy_Backup!K45)) -> Easy | P45: =IF(UPPER(Legacy_Backup!O45)="YES","Visual","Text") -> Text | Q45: =PROPER(Legacy_Backup!O45) -> No | R45: =IF(UPPER(Legacy_Backup!O45)="YES",IF(Legacy_Backup!Y45<>"",Legacy_Backup!Y45,"Image required"),"NA") -> NA | S45: =IF(UPPER(Legacy_Backup!O45)="YES",IF(Legacy_Backup!Z45<>"",Legacy_Backup!Z45,"Prompt required"),"NA") -> NA | T45: =IF(Legacy_Backup!L45<>"",PROPER(Legacy_Backup!L45),"Apply") -> Analyze | U45: =Legacy_Backup!P45 -> Meera has ₹500. She needs a notebook for ₹120 and bus fare of ₹200, and wants headphones for ₹350. What is the wisest choice? | V45: =Legacy_Backup!Q45 -> Buy headphones first | W45: =Legacy_Backup!R45 -> Borrow money for all three | X45: =Legacy_Backup!S45 -> Spend everything on snacks | Y45: =Legacy_Backup!T45 -> Pay for the notebook and bus fare, then save the rest | Z45: =Legacy_Backup!U45 -> D | AA45: =Legacy_Backup!W45 -> Pay for the notebook and bus fare, then save the rest is the best choice because it directly applies budgeting to the situation and addresses the stated need with a practical, responsible action. | AB45: =Legacy_Backup!X45 -> Builds practical financial awareness for future study, work and responsible citizenship. | AC45: =Legacy_Backup!M45 -> Financial Awareness | AD45: =IF(UPPER(Legacy_Backup!O45)="YES",A45&".png","NA") -> NA | AE45: =Legacy_Backup!AB45 | AH45: =IF(LEFT(Legacy_Backup!AC45,1)="v",Legacy_Backup!AC45,"v"&Legacy_Backup!AC45) -> v1.0
A46: 08_FRD_SIF_002 | B46: 8 | C46: 4 | D46: Financial Readiness | E46: FRD | F46: 23 | G46: Saving & Investing for the Future | H46: SIF | I46: SIF-T01 | J46: =Legacy_Backup!G46 -> Saving Goals | K46: =TEXT(COUNTIF($E$2:E46,E46),"000") -> 002 | L46: =Legacy_Backup!H46 -> Make a simple saving plan | M46: =IFERROR(__xludf.DUMMYFUNCTION("IF(REGEXMATCH(UPPER(Legacy_Backup!I46),""KNOW""),""Know"",IF(REGEXMATCH(UPPER(Legacy_Backup!I46),""IMAGINE|INNOVATION""),""Imagine"",""Think""))"),"Think") -> Think | N46: =IFERROR(__xludf.DUMMYFUNCTION("IF(REGEXMATCH(UPPER(Legacy_Backup!J46),""FUTURE""),""Future-Oriented"",IF(REGEXMATCH(UPPER(Legacy_Backup!J46),""KNOWLEDGE""),""Knowledge-Based"",IF(REGEXMATCH(UPPER(Legacy_Backup!J46),""DECISION""),""Decision-Making"",""Situation-Based"")))"),"Situation-Based") -> Situation-Based | O46: =IF(UPPER(Legacy_Backup!K46)="HARD","Difficult",PROPER(Legacy_Backup!K46)) -> Easy | P46: =IF(UPPER(Legacy_Backup!O46)="YES","Visual","Text") -> Visual | Q46: =PROPER(Legacy_Backup!O46) -> Yes | R46: =IF(UPPER(Legacy_Backup!O46)="YES",IF(Legacy_Backup!Y46<>"",Legacy_Backup!Y46,"Image required"),"NA") -> A clean Grade 8 educational table or chart illustrating: A student wants ₹600 for a course in six months. How much should be saved each month? | S46: =IF(UPPER(Legacy_Backup!O46)="YES",IF(Legacy_Backup!Z46<>"",Legacy_Backup!Z46,"Prompt required"),"NA") -> Create a clear, age-appropriate educational visual for Grade 8. Show only the information needed for this MCQ: A student wants ₹600 for a course in six months. How much should be saved each month? Use a light background, simple labels, high contrast, no answer clues, landscape 4:3. | T46: =IF(Legacy_Backup!L46<>"",PROPER(Legacy_Backup!L46),"Apply") -> Analyze | U46: =Legacy_Backup!P46 -> Study the image. How much should be saved each month to achieve the goal? | V46: =Legacy_Backup!Q46 -> ₹100 | W46: =Legacy_Backup!R46 -> ₹50 | X46: =Legacy_Backup!S46 -> ₹75 | Y46: =Legacy_Backup!T46 -> ₹150 | Z46: =Legacy_Backup!U46 -> A | AA46: =Legacy_Backup!W46 -> ₹100 is the best choice because it directly applies saving goals to the situation and addresses the stated need with a practical, responsible action. | AB46: =Legacy_Backup!X46 -> Builds practical financial awareness for future study, work and responsible citizenship. | AC46: =Legacy_Backup!M46 -> Financial Awareness | AD46: =IF(UPPER(Legacy_Backup!O46)="YES",A46&".png","NA") -> 08_FRD_SIF_002.png | AE46: =Legacy_Backup!AB46 | AH46: =IF(LEFT(Legacy_Backup!AC46,1)="v",Legacy_Backup!AC46,"v"&Legacy_Backup!AC46) -> v1.0
A47: 08_FRD_MMD_003 | B47: 8 | C47: 4 | D47: Financial Readiness | E47: FRD | F47: 22 | G47: Money Management & Smart Decision Making | H47: MMD | I47: MMD-T02 | J47: =Legacy_Backup!G47 -> Price Comparison | K47: =TEXT(COUNTIF($E$2:E47,E47),"000") -> 003 | L47: =Legacy_Backup!H47 -> Compare value using unit prices | M47: =IFERROR(__xludf.DUMMYFUNCTION("IF(REGEXMATCH(UPPER(Legacy_Backup!I47),""KNOW""),""Know"",IF(REGEXMATCH(UPPER(Legacy_Backup!I47),""IMAGINE|INNOVATION""),""Imagine"",""Think""))"),"Think") -> Think | N47: =IFERROR(__xludf.DUMMYFUNCTION("IF(REGEXMATCH(UPPER(Legacy_Backup!J47),""FUTURE""),""Future-Oriented"",IF(REGEXMATCH(UPPER(Legacy_Backup!J47),""KNOWLEDGE""),""Knowledge-Based"",IF(REGEXMATCH(UPPER(Legacy_Backup!J47),""DECISION""),""Decision-Making"",""Situation-Based"")))"),"Situation-Based") -> Situation-Based | O47: =IF(UPPER(Legacy_Backup!K47)="HARD","Difficult",PROPER(Legacy_Backup!K47)) -> Easy | P47: =IF(UPPER(Legacy_Backup!O47)="YES","Visual","Text") -> Visual | Q47: =PROPER(Legacy_Backup!O47) -> Yes | R47: =IF(UPPER(Legacy_Backup!O47)="YES",IF(Legacy_Backup!Y47<>"",Legacy_Backup!Y47,"Image required"),"NA") -> A clean Grade 8 educational real-life scene illustrating: A chart shows 5 pens for ₹50 and 8 similar pens for ₹72. Which pack has the lower cost per pen? | S47: =IF(UPPER(Legacy_Backup!O47)="YES",IF(Legacy_Backup!Z47<>"",Legacy_Backup!Z47,"Prompt required"),"NA") -> Create a clear, age-appropriate educational visual for Grade 8. Show only the information needed for this MCQ: A chart shows 5 pens for ₹50 and 8 similar pens for ₹72. Which pack has the lower cost per pen? Use a light background, simple labels, high contrast, no answer clues, landscape 4:3. | T47: =IF(Legacy_Backup!L47<>"",PROPER(Legacy_Backup!L47),"Apply") -> Analyze | U47: =Legacy_Backup!P47 -> Study the chart. Which pack has the lower cost per pen? | V47: =Legacy_Backup!Q47 -> The 5-pen pack | W47: =Legacy_Backup!R47 -> The 8-pen pack | X47: =Legacy_Backup!S47 -> Both cost the same per pen | Y47: =Legacy_Backup!T47 -> There is not enough information | Z47: =Legacy_Backup!U47 -> B | AA47: =Legacy_Backup!W47 -> The 8-pen pack is the best choice because it directly applies price comparison to the situation and addresses the stated need with a practical, responsible action. | AB47: =Legacy_Backup!X47 -> Builds practical financial awareness for future study, work and responsible citizenship. | AC47: =Legacy_Backup!M47 -> Financial Awareness | AD47: =IF(UPPER(Legacy_Backup!O47)="YES",A47&".png","NA") -> 08_FRD_MMD_003.png | AE47: =Legacy_Backup!AB47 | AH47: =IF(LEFT(Legacy_Backup!AC47,1)="v",Legacy_Backup!AC47,"v"&Legacy_Backup!AC47) -> v1.0
A48: 08_FRD_DBS_004 | B48: 8 | C48: 4 | D48: Financial Readiness | E48: FRD | F48: 24 | G48: Digital Banking, Payments & Financial Safety | H48: DBS | I48: DBS-T01 | J48: =Legacy_Backup!G48 -> Digital Payment Safety | K48: =TEXT(COUNTIF($E$2:E48,E48),"000") -> 004 | L48: =Legacy_Backup!H48 -> Protect financial information during payment | M48: =IFERROR(__xludf.DUMMYFUNCTION("IF(REGEXMATCH(UPPER(Legacy_Backup!I48),""KNOW""),""Know"",IF(REGEXMATCH(UPPER(Legacy_Backup!I48),""IMAGINE|INNOVATION""),""Imagine"",""Think""))"),"Think") -> Think | N48: =IFERROR(__xludf.DUMMYFUNCTION("IF(REGEXMATCH(UPPER(Legacy_Backup!J48),""FUTURE""),""Future-Oriented"",IF(REGEXMATCH(UPPER(Legacy_Backup!J48),""KNOWLEDGE""),""Knowledge-Based"",IF(REGEXMATCH(UPPER(Legacy_Backup!J48),""DECISION""),""Decision-Making"",""Situation-Based"")))"),"Situation-Based") -> Situation-Based | O48: =IF(UPPER(Legacy_Backup!K48)="HARD","Difficult",PROPER(Legacy_Backup!K48)) -> Easy | P48: =IF(UPPER(Legacy_Backup!O48)="YES","Visual","Text") -> Text | Q48: =PROPER(Legacy_Backup!O48) -> No | R48: =IF(UPPER(Legacy_Backup!O48)="YES",IF(Legacy_Backup!Y48<>"",Legacy_Backup!Y48,"Image required"),"NA") -> NA | S48: =IF(UPPER(Legacy_Backup!O48)="YES",IF(Legacy_Backup!Z48<>"",Legacy_Backup!Z48,"Prompt required"),"NA") -> NA | T48: =IF(Legacy_Backup!L48<>"",PROPER(Legacy_Backup!L48),"Apply") -> Evaluate | U48: =Legacy_Backup!P48 -> A caller asks Raja for an OTP to “confirm a refund.” What should the account holder do? | V48: =Legacy_Backup!Q48 -> Share it if the caller sounds polite | W48: =Legacy_Backup!R48 -> Share only the last two digits | X48: =Legacy_Backup!S48 -> Never share the OTP | Y48: =Legacy_Backup!T48 -> Post the OTP in the help chat | Z48: =Legacy_Backup!U48 -> C | AA48: =Legacy_Backup!W48 -> Never share the OTP and contact the bank through an official channel is the best choice because it directly applies digital payment safety to the situation and addresses the stated need with a practical, responsible action. | AB48: =Legacy_Backup!X48 -> Builds practical financial awareness for future study, work and responsible citizenship. | AC48: =Legacy_Backup!M48 -> Financial Awareness | AD48: =IF(UPPER(Legacy_Backup!O48)="YES",A48&".png","NA") -> NA | AE48: =Legacy_Backup!AB48 | AH48: =IF(LEFT(Legacy_Backup!AC48,1)="v",Legacy_Backup!AC48,"v"&Legacy_Backup!AC48) -> v1.0
A49: 08_FRD_MMD_005 | B49: 8 | C49: 4 | D49: Financial Readiness | E49: FRD | F49: 22 | G49: Money Management & Smart Decision Making | H49: MMD | I49: MMD-T03 | J49: =Legacy_Backup!G49 -> Income and Expense | K49: =TEXT(COUNTIF($E$2:E49,E49),"000") -> 005 | L49: =Legacy_Backup!H49 -> Calculate remaining money after expenses | M49: =IFERROR(__xludf.DUMMYFUNCTION("IF(REGEXMATCH(UPPER(Legacy_Backup!I49),""KNOW""),""Know"",IF(REGEXMATCH(UPPER(Legacy_Backup!I49),""IMAGINE|INNOVATION""),""Imagine"",""Think""))"),"Imagine") -> Imagine | N49: =IFERROR(__xludf.DUMMYFUNCTION("IF(REGEXMATCH(UPPER(Legacy_Backup!J49),""FUTURE""),""Future-Oriented"",IF(REGEXMATCH(UPPER(Legacy_Backup!J49),""KNOWLEDGE""),""Knowledge-Based"",IF(REGEXMATCH(UPPER(Legacy_Backup!J49),""DECISION""),""Decision-Making"",""Situation-Based"")))"),"Situation-Based") -> Situation-Based | O49: =IF(UPPER(Legacy_Backup!K49)="HARD","Difficult",PROPER(Legacy_Backup!K49)) -> Easy | P49: =IF(UPPER(Legacy_Backup!O49)="YES","Visual","Text") -> Text | Q49: =PROPER(Legacy_Backup!O49) -> No | R49: =IF(UPPER(Legacy_Backup!O49)="YES",IF(Legacy_Backup!Y49<>"",Legacy_Backup!Y49,"Image required"),"NA") -> NA | S49: =IF(UPPER(Legacy_Backup!O49)="YES",IF(Legacy_Backup!Z49<>"",Legacy_Backup!Z49,"Prompt required"),"NA") -> NA | T49: =IF(Legacy_Backup!L49<>"",PROPER(Legacy_Backup!L49),"Apply") -> Create | U49: =Legacy_Backup!P49 -> Kabir earns ₹800 from a weekend project and spends ₹250 on materials and ₹150 on travel. How much remains? | V49: =Legacy_Backup!Q49 -> ₹300 | W49: =Legacy_Backup!R49 -> ₹500 | X49: =Legacy_Backup!S49 -> ₹600 | Y49: =Legacy_Backup!T49 -> ₹400 | Z49: =Legacy_Backup!U49 -> D | AA49: =Legacy_Backup!W49 -> ₹400 is the best choice because it directly applies income and expense to the situation and addresses the stated need with a practical, responsible action. | AB49: =Legacy_Backup!X49 -> Builds practical financial awareness for future study, work and responsible citizenship. | AC49: =Legacy_Backup!M49 -> Financial Awareness | AD49: =IF(UPPER(Legacy_Backup!O49)="YES",A49&".png","NA") -> NA | AE49: =Legacy_Backup!AB49 | AH49: =IF(LEFT(Legacy_Backup!AC49,1)="v",Legacy_Backup!AC49,"v"&Legacy_Backup!AC49) -> v1.0
A50: 08_FRD_SIF_006 | B50: 8 | C50: 4 | D50: Financial Readiness | E50: FRD | F50: 23 | G50: Saving & Investing for the Future | H50: SIF | I50: SIF-T02 | J50: =Legacy_Backup!G50 -> Financial Risk | K50: =TEXT(COUNTIF($E$2:E50,E50),"000") -> 006 | L50: =Legacy_Backup!H50 -> Choose a low-risk response to an unrealistic offer | M50: =IFERROR(__xludf.DUMMYFUNCTION("IF(REGEXMATCH(UPPER(Legacy_Backup!I50),""KNOW""),""Know"",IF(REGEXMATCH(UPPER(Legacy_Backup!I50),""IMAGINE|INNOVATION""),""Imagine"",""Think""))"),"Think") -> Think | N50: =IFERROR(__xludf.DUMMYFUNCTION("IF(REGEXMATCH(UPPER(Legacy_Backup!J50),""FUTURE""),""Future-Oriented"",IF(REGEXMATCH(UPPER(Legacy_Backup!J50),""KNOWLEDGE""),""Knowledge-Based"",IF(REGEXMATCH(UPPER(Legacy_Backup!J50),""DECISION""),""Decision-Making"",""Situation-Based"")))"),"Situation-Based") -> Situation-Based | O50: =IF(UPPER(Legacy_Backup!K50)="HARD","Difficult",PROPER(Legacy_Backup!K50)) -> Easy | P50: =IF(UPPER(Legacy_Backup!O50)="YES","Visual","Text") -> Text | Q50: =PROPER(Legacy_Backup!O50) -> No | R50: =IF(UPPER(Legacy_Backup!O50)="YES",IF(Legacy_Backup!Y50<>"",Legacy_Backup!Y50,"Image required"),"NA") -> NA | S50: =IF(UPPER(Legacy_Backup!O50)="YES",IF(Legacy_Backup!Z50<>"",Legacy_Backup!Z50,"Prompt required"),"NA") -> NA | T50: =IF(Legacy_Backup!L50<>"",PROPER(Legacy_Backup!L50),"Apply") -> Apply | U50: =Legacy_Backup!P50 -> An online ad promises to double money in two days with “zero risk.” What should a student do? | V50: =Legacy_Backup!Q50 -> Avoid it and discuss it with a trusted adult | W50: =Legacy_Backup!R50 -> Invest immediately and wait for the results | X50: =Legacy_Backup!S50 -> Borrow money from friends to invest more | Y50: =Legacy_Backup!T50 -> Share it with classmates & invite them to earn more money | Z50: =Legacy_Backup!U50 -> A | AA50: =Legacy_Backup!W50 -> Avoid it and discuss it with a trusted adult is the best choice because it directly applies financial risk to the situation and addresses the stated need with a practical, responsible action. | AB50: =Legacy_Backup!X50 -> Builds practical financial awareness for future study, work and responsible citizenship. | AC50: =Legacy_Backup!M50 -> Financial Awareness | AD50: =IF(UPPER(Legacy_Backup!O50)="YES",A50&".png","NA") -> NA | AE50: =Legacy_Backup!AB50 | AH50: =IF(LEFT(Legacy_Backup!AC50,1)="v",Legacy_Backup!AC50,"v"&Legacy_Backup!AC50) -> v1.0
A51: 08_FRD_MMD_007 | B51: 8 | C51: 4 | D51: Financial Readiness | E51: FRD | F51: 22 | G51: Money Management & Smart Decision Making | H51: MMD | I51: MMD-T04 | J51: =Legacy_Backup!G51 -> Responsible Borrowing | K51: =TEXT(COUNTIF($E$2:E51,E51),"000") -> 007 | L51: =Legacy_Backup!H51 -> Understand the obligation created by borrowing | M51: =IFERROR(__xludf.DUMMYFUNCTION("IF(REGEXMATCH(UPPER(Legacy_Backup!I51),""KNOW""),""Know"",IF(REGEXMATCH(UPPER(Legacy_Backup!I51),""IMAGINE|INNOVATION""),""Imagine"",""Think""))"),"Think") -> Think | N51: =IFERROR(__xludf.DUMMYFUNCTION("IF(REGEXMATCH(UPPER(Legacy_Backup!J51),""FUTURE""),""Future-Oriented"",IF(REGEXMATCH(UPPER(Legacy_Backup!J51),""KNOWLEDGE""),""Knowledge-Based"",IF(REGEXMATCH(UPPER(Legacy_Backup!J51),""DECISION""),""Decision-Making"",""Situation-Based"")))"),"Situation-Based") -> Situation-Based | O51: =IF(UPPER(Legacy_Backup!K51)="HARD","Difficult",PROPER(Legacy_Backup!K51)) -> Easy | P51: =IF(UPPER(Legacy_Backup!O51)="YES","Visual","Text") -> Text | Q51: =PROPER(Legacy_Backup!O51) -> No | R51: =IF(UPPER(Legacy_Backup!O51)="YES",IF(Legacy_Backup!Y51<>"",Legacy_Backup!Y51,"Image required"),"NA") -> NA | S51: =IF(UPPER(Legacy_Backup!O51)="YES",IF(Legacy_Backup!Z51<>"",Legacy_Backup!Z51,"Prompt required"),"NA") -> NA | T51: =IF(Legacy_Backup!L51<>"",PROPER(Legacy_Backup!L51),"Apply") -> Analyze | U51: =Legacy_Backup!P51 -> A student borrows ₹300 from a friend for a necessary book. Which action is most responsible? | V51: =Legacy_Backup!Q51 -> Avoid mentioning repayment | W51: =Legacy_Backup!R51 -> Agree on when and how the money will be repaid | X51: =Legacy_Backup!S51 -> Borrow from another friend to buy a game | Y51: =Legacy_Backup!T51 -> Promise an amount that cannot be paid | Z51: =Legacy_Backup!U51 -> B | AA51: =Legacy_Backup!W51 -> Agree on when and how the money will be repaid is the best choice because it directly applies responsible borrowing to the situation and addresses the stated need with a practical, responsible action. | AB51: =Legacy_Backup!X51 -> Builds practical financial awareness for future study, work and responsible citizenship. | AC51: =Legacy_Backup!M51 -> Financial Awareness | AD51: =IF(UPPER(Legacy_Backup!O51)="YES",A51&".png","NA") -> NA | AE51: =Legacy_Backup!AB51 | AH51: =IF(LEFT(Legacy_Backup!AC51,1)="v",Legacy_Backup!AC51,"v"&Legacy_Backup!AC51) -> v1.0

Sheet Legacy_Backup
A1: Question ID | B1: Grade | C1: Part Code | D1: Part Name | E1: Section Code | F1: Section Name | G1: Topic | H1: Learning Objective | I1: Question Type | J1: Question Category | K1: Difficulty | L1: Bloom Level | M1: Competency Assessed | N1: Question Format | O1: Visual Required | P1: Question | Q1: Option A | R1: Option B | S1: Option C | T1: Option D | U1: Correct Option | V1: Correct Answer | W1: Explanation | X1: Future Ready Insight | Y1: Image Description | Z1: Canva Prompt | AA1: Image Filename | AB1: Reviewer Comments | AC1: Version | AD1: Image Link
A2: EM-OS-08-001 | B2: 8 | C2: EM | D2: Entrepreneurship Mindset | E2: OS | F2: Opportunity Spotting | G2: Opportunity Spotting | H2: Identify useful opportunities from everyday problems | I2: Situational MCQ | J2: Application-Based | K2: Easy | L2: Apply | M2: Entrepreneurship | N2: MCQ - Single Correct | O2: No | P2: A school canteen has long queues and students often miss part of lunch. Which idea best turns this problem into an opportunity? | Q2: Start a pre-order system for students | R2: Sell more items only after lunch | S2: Ask students to bring food every day | T2: Close one counter to reduce confusion | U2: A | V2: Start a pre-order system for students | W2: Start a pre-order system with fixed pickup slots is the best choice because it directly applies opportunity spotting to the situation and addresses the stated need with a practical, responsible action. | X2: Builds practical entrepreneurship for future study, work and responsible citizenship. | AC2: 1.0
A3: EM-CU-08-002 | B3: 8 | C3: EM | D3: Entrepreneurship Mindset | E3: CU | F3: Customer Understanding | G3: Customer Understanding | H3: Use customer feedback before designing a solution | I3: Case-Based Question | J3: Application-Based | K3: Easy | L3: Analyze | M3: Entrepreneurship | N3: MCQ - Single Correct | O3: No | P3: Riya wants to sell reusable water bottles at school. What should she do first? | Q3: Order 200 bottles in her favourite colour | R3: Ask students about their preferences /liking | S3: Copy the most expensive bottle online | T3: Print posters before deciding the product | U3: B | V3: Ask students about their preferences /liking | W3: Ask students about size, price and features they prefer is the best choice because it directly applies customer understanding to the situation and addresses the stated need with a practical, responsible action. | X3: Builds practical entrepreneurship for future study, work and responsible citizenship. | AC3: 1.0
A4: EM-PAR-08-003 | B4: 8 | C4: EM | D4: Entrepreneurship Mindset | E4: PAR | F4: Planning and Resource Use | G4: Planning and Resource Use | H4: Select a plan that uses limited resources wisely | I4: Data Interpretation | J4: Application-Based | K4: Easy | L4: Analyze | M4: Entrepreneurship | N4: MCQ - Single Correct | O4: Yes | P4: Four teams need the art room. Refer to the chart showing booking data. Which day gives a new team the best chance to work without delay? | Q4: Monday | R4: Tuesday | S4: Wednesday | T4: Thursday | U4: C | V4: Wednesday | W4: Wednesday is the best choice because it directly applies planning and resource use to the situation and addresses the stated need with a practical, responsible action. | X4: Builds practical entrepreneurship for future study, work and responsible citizenship. | Y4: A clean Grade 8 educational table or chart illustrating: Four teams need the art room. The booking chart shows: Monday 2 teams, Tuesday 1, Wednesday 0, Thursday 3. Which day gives a new team the best chance to work without delay? | Z4: Create a clear, age-appropriate educational visual for Grade 8. Show only the information needed for this MCQ: Four teams need the art room. The booking chart shows: Monday 2 teams, Tuesday 1, Wednesday 0, Thursday 3. Which day gives a new team the best chance to work without delay? Use a light background, simple labels, high contrast, no answer clues, landscape 4:3. | AA4: EM_PAR_08_003.png | AC4: 1.0
A5: EM-VP-08-004 | B5: 8 | C5: EM | D5: Entrepreneurship Mindset | E5: VP | F5: Value Proposition | G5: Value Proposition | H5: Connect a product benefit to a customer need | I5: Visual Question | J5: Application-Based | K5: Easy | L5: Analyze | M5: Entrepreneurship | N5: MCQ - Single Correct | O5: Yes | P5: An image shows two lunch boxes: Box P & Box Q . Which is the stronger value proposition for students to use? | Q5: Box P, because style is always most important | R5: Box P, because cleaning does not matter | S5: Both are equal because they hold food | T5: Box Q, because it solves practical daily problems of leakage | U5: D | V5: Box Q, because it solves practical daily problems | W5: Box Q, because it solves practical daily problems is the best choice because it directly applies value proposition to the situation and addresses the stated need with a practical, responsible action. | X5: Builds practical entrepreneurship for future study, work and responsible citizenship. | Y5: A clean Grade 8 educational real-life scene illustrating: An image shows two lunch boxes: Box P is stylish but leaks; Box Q is simple, leak-proof and easy to clean. Which is the stronger value proposition for students? | Z5: Create a clear, age-appropriate educational visual for Grade 8. Show only the information needed for this MCQ: An image shows two lunch boxes: Box P is stylish but leaks; Box Q is simple, leak-proof and easy to clean. Which is the stronger value proposition for students? Use a light background, simple labels, high contrast, no answer clues, landscape 4:3. | AA5: EM_VP_08_004.png | AC5: 1.0
A6: EM-RAD-08-005 | B6: 8 | C6: EM | D6: Entrepreneurship Mindset | E6: RAD | F6: Risk and Decision Making | G6: Risk and Decision Making | H6: Reduce risk through a small test | I6: Problem Solving Challenge | J6: Application-Based | K6: Easy | L6: Evaluate | M6: Entrepreneurship | N6: MCQ - Single Correct | O6: No | P6: A team can spend its full budget making 100 keychains or first make 10 samples. What is the wiser approach? | Q6: Make 10, collect feedback, then decide | R6: Make 100 immediately to save time | S6: Buy a machine before testing demand | T6: Avoid making anything until everyone agrees | U6: A | V6: Make 10, collect feedback, then decide | W6: Make 10, collect feedback, then decide is the best choice because it directly applies risk and decision making to the situation and addresses the stated need with a practical, responsible action. | X6: Builds practical entrepreneurship for future study, work and responsible citizenship. | AC6: 1.0
A7: EM-PI-08-006 | B7: 8 | C7: EM | D7: Entrepreneurship Mindset | E7: PI | F7: Product Innovation | G7: Product Innovation | H7: Improve an existing solution for user benefit | I7: Innovation Scenario | J7: Application-Based | K7: Easy | L7: Create | M7: Entrepreneurship | N7: MCQ - Single Correct | O7: No | P7: Students regularly forget to water classroom plants. Which idea is both innovative and practical? | Q7: A poster saying plants need water | R7: A low-cost moisture (dryness) indicator for soil | S7: Replacing plants with plastic ones | T7: Asking one student to remember forever | U7: B | V7: A low-cost moisture (dryness) indicator for soil | W7: A low-cost moisture indicator that changes colour when soil is dry is the best choice because it directly applies product innovation to the situation and addresses the stated need with a practical, responsible action. | X7: Builds practical entrepreneurship for future study, work and responsible citizenship. | AC7: 1.0
A8: EM-EAF-08-007 | B8: 8 | C8: EM | D8: Entrepreneurship Mindset | E8: EAF | F8: Ethics and Fairness | G8: Ethics and Fairness | H8: Choose honest business behaviour | I8: Situational MCQ | J8: Application-Based | K8: Easy | L8: Apply | M8: Entrepreneurship | N8: MCQ - Single Correct | O8: No | P8: A seller notices that one batch of notebooks has weak binding. What should the seller do? | Q8: Hide the problem with new covers | R8: Sell them quickly to younger students | S8: Tell buyers and replace the faulty notebooks | T8: Increase the price to appear premium | U8: C | V8: Tell buyers and replace the faulty notebooks | W8: Tell buyers and replace or discount the faulty notebooks is the best choice because it directly applies ethics and fairness to the situation and addresses the stated need with a practical, responsible action. | X8: Builds practical entrepreneurship for future study, work and responsible citizenship. | AC8: 1.0
A9: EM-PAP-08-008 | B9: 8 | C9: EM | D9: Entrepreneurship Mindset | E9: PAP | F9: Pricing and Profit | G9: Pricing and Profit | H9: Choose a price using cost and customer value | I9: Case-Based Question | J9: Application-Based | K9: Easy | L9: Analyze | M9: Entrepreneurship | N9: MCQ - Single Correct | O9: No | P9: A bookmark costs ₹12 to make. Students say they would comfortably pay ₹20. Which price is most reasonable for a small profit? | Q9: ₹8 | R9: ₹12 | S9: ₹40 | T9: ₹18 | U9: D | V9: ₹18 | W9: ₹18 is the best choice because it directly applies pricing and profit to the situation and addresses the stated need with a practical, responsible action. | X9: Builds practical entrepreneurship for future study, work and responsible citizenship. | AC9: 1.0
A10: EM-TAC-08-009 | B10: 8 | C10: EM | D10: Entrepreneurship Mindset | E10: TAC | F10: Teamwork and Communication | G10: Teamwork and Communication | H10: Assign work according to team strengths | I10: Data Interpretation | J10: Application-Based | K10: Easy | L10: Analyze | M10: Entrepreneurship | N10: MCQ - Single Correct | O10: Yes | P10: The team chart shows: Aman—drawing, Beena—speaking, Charu—calculations, Dev—organising. Who should present the final pitch? | Q10: Beena | R10: Aman | S10: Charu | T10: Dev | U10: A | V10: Beena | W10: Beena is the best choice because it directly applies teamwork and communication to the situation and addresses the stated need with a practical, responsible action. | X10: Builds practical entrepreneurship for future study, work and responsible citizenship. | Y10: A clean Grade 8 educational table or chart illustrating: The team chart shows: Aman—drawing, Beena—speaking, Charu—calculations, Dev—organising. Who should present the final pitch? | Z10: Create a clear, age-appropriate educational visual for Grade 8. Show only the information needed for this MCQ: The team chart shows: Aman—drawing, Beena—speaking, Charu—calculations, Dev—organising. Who should present the final pitch? Use a light background, simple labels, high contrast, no answer clues, landscape 4:3. | AA10: EM_TAC_08_009.png | AC10: 1.0
A11: EM-OAI-08-010 | B11: 8 | C11: EM | D11: Entrepreneurship Mindset | E11: OAI | F11: Ownership and Initiative | G11: Ownership and Initiative | H11: Demonstrate initiative when a plan faces a barrier | I11: Visual Question | J11: Application-Based | K11: Easy | L11: Analyze | M11: Entrepreneurship | N11: MCQ - Single Correct | O11: Yes | P11: A venue cancels one day before a student sale. What should the team leader do first? | Q11: Wait for someone else to solve it | R11: Quickly identify another safe venue | S11: Cancel without telling customers | T11: Blame the venue online | U11: B | V11: Quickly identify another safe venue and inform everyone | W11: Quickly identify another safe venue and inform everyone is the best choice because it directly applies ownership and initiative to the situation and addresses the stated need with a practical, responsible action. | X11: Builds practical entrepreneurship for future study, work and responsible citizenship. | Y11: A clean Grade 8 educational real-life scene illustrating: A venue cancels one day before a student sale. What should the team leader do first? | Z11: Create a clear, age-appropriate educational visual for Grade 8. Show only the information needed for this MCQ: A venue cancels one day before a student sale. What should the team leader do first? Use a light background, simple labels, high contrast, no answer clues, landscape 4:3. | AA11: EM_OAI_08_010.png | AC11: 1.0
A12: EM-CU-08-011 | B12: 8 | C12: EM | D12: Entrepreneurship Mindset | E12: CU | F12: Customer Understanding | G12: Customer Understanding | H12: Improve a product using evidence | I12: Problem Solving Challenge | J12: Application-Based | K12: Easy | L12: Evaluate | M12: Entrepreneurship | N12: MCQ - Single Correct | O12: No | P12: After testing a pencil grip, 8 of 10 students say it slips. What is the best next step? | Q12: Ignore them because two students liked it | R12: Produce 500 grips immediately | S12: Change the material and test the new version | T12: Change only the logo | U12: C | V12: Change the material and test the new version | W12: Change the material and test the new version is the best choice because it directly applies customer understanding to the situation and addresses the stated need with a practical, responsible action. | X12: Builds practical entrepreneurship for future study, work and responsible citizenship. | AC12: 1.0
A13: EM-CE-006 | B13: 8 | C13: EM | D13: Entrepreneurship Mindset | E13: CE | F13: Customer Understanding and Empathy | G13: Visual – shopkeeper talking | H13: Identify customer understanding from a visual scene. | I13: Think | J13: Situation | K13: Medium | L13: Analyze | M13: Observing customer interaction. | N13: Visual | O13: Yes | P13: A shopkeeper listens to a customer and writes notes. What is this most likely showing? | Q13: Understanding customer needs | R13: Preparing to-do task list for customer | S13: Preparing to close the shop forever | T13: Counting old stock without any reason | U13: A | V13: Understanding customer needs | W13: Listening and noting details suggests the shopkeeper is learning about customer needs. | X13: Normalises feedback collection as part of everyday business. | Y13: Shopkeeper speaking with a customer and noting something on a pad. | Z13: Draw a small shop with a shopkeeper listening to a customer, writing notes on a notepad. Show them facing each other. | AA13: EM_CE_Q6_shop_listen.png | AC13: v1.0 | AD13: https://drive.google.com/file/d/1ay_yDgfZRPR5cQjF-2mImgVJ6XPMn-jE/view?usp=drive_link
A14: EM-EF-008 | B14: 8 | C14: EM | D14: Entrepreneurship Mindset | E14: EF | F14: Ethics, Integrity and Fairness | G14: Visual – two students sharing | H14: Identify fairness in a simple sharing situation. | I14: Know | J14: Situation | K14: Medium | L14: Apply | M14: Everyday fairness. | N14: Visual | O14: Yes | P14: Look at the image shpwing two friends What does this show? | Q14: Fair sharing between friends | R14: Debating on the choice of snack | S14: Fighting over marks | T14: Ignoring each other completely | U14: A | V14: Fair sharing between friends | W14: Equal division of a snack reflects fairness and consideration. | X14: Connects everyday fairness with ethical thinking in business. | Y14: Two students sharing equal parts of a snack. | Z14: Draw two students splitting a snack into equal parts and smiling. | AA14: EM_EF_Q8_share_snack.png | AC14: v1.0 | AD14: https://drive.google.com/file/d/15BvoleShZfFtxLdz7GQHinhqrVvNeBFR/view?usp=drive_link
A15: PSI-RCA-08-001 | B15: 8 | C15: PSI | D15: Problem Solving & Innovation | E15: RCA | F15: Root Cause Analysis | G15: Root Cause Analysis | H15: Identify causes before selecting solutions | I15: Case-Based Question | J15: Application-Based | K15: Easy | L15: Analyze | M15: Problem Solving | N15: MCQ - Single Correct | O15: No | P15: The school bus is late on four days. What should students do first? | Q15: Meet the administration & request a new bus immediately | R15: Record departure times, routes and delay reasons | S15: Assume the driver is careless and seek change | T15: Cancel the bus service for students | U15: B | V15: Record departure times, routes and delay reasons | W15: Record departure times, routes and delay reasons is the best choice because it directly applies root cause analysis to the situation and addresses the stated need with a practical, responsible action. | X15: Builds practical problem solving for future study, work and responsible citizenship. | AC15: 1.0
A16: PSI-P-08-002 | B16: 8 | C16: PSI | D16: Problem Solving & Innovation | E16: P | F16: Prioritisation | G16: Prioritisation | H16: Prioritise a safety-critical issue | I16: Data Interpretation | J16: Application-Based | K16: Easy | L16: Analyze | M16: Problem Solving | N16: MCQ - Single Correct | O16: Yes | P16: A team lists four issues: faded poster, loose electric wire, slow Wi-Fi and untidy shelf. Which should be solved first? | Q16: Faded poster | R16: Slow Wi-Fi | S16: Loose electric wire | T16: Untidy shelf | U16: C | V16: Loose electric wire | W16: Loose electric wire is the best choice because it directly applies prioritisation to the situation and addresses the stated need with a practical, responsible action. | X16: Builds practical problem solving for future study, work and responsible citizenship. | Y16: A clean Grade 8 educational table or chart illustrating: A team lists four issues: faded poster, loose electric wire, slow Wi-Fi and untidy shelf. Which should be solved first? | Z16: Create a clear, age-appropriate educational visual for Grade 8. Show only the information needed for this MCQ: A team lists four issues: faded poster, loose electric wire, slow Wi-Fi and untidy shelf. Which should be solved first? Use a light background, simple labels, high contrast, no answer clues, landscape 4:3. | AA16: PSI_P_08_002.png | AC16: 1.0
A17: PSI-DPS-08-003 | B17: 8 | C17: PSI | D17: Problem Solving & Innovation | E17: DPS | F17: Data-based Problem Solving | G17: Data-based Problem Solving | H17: Use data to identify a pattern | I17: Visual Question | J17: Application-Based | K17: Easy | L17: Analyze | M17: Problem Solving | N17: MCQ - Single Correct | O17: Yes | P17: A table shows library crowding on weekdays. Which day is best suited for an extra librarian? | Q17: Monday | R17: Tuesday | S17: Thursday | T17: Wednesday | U17: D | V17: Wednesday | W17: Wednesday is the best choice because it directly applies data-based problem solving to the situation and addresses the stated need with a practical, responsible action. | X17: Builds practical problem solving for future study, work and responsible citizenship. | Y17: A clean Grade 8 educational real-life scene illustrating: A table shows library crowding: Monday 20, Tuesday 22, Wednesday 45, Thursday 21 students. Which day should get an extra librarian? | Z17: Create a clear, age-appropriate educational visual for Grade 8. Show only the information needed for this MCQ: A table shows library crowding: Monday 20, Tuesday 22, Wednesday 45, Thursday 21 students. Which day should get an extra librarian? Use a light background, simple labels, high contrast, no answer clues, landscape 4:3. | AA17: PSI_DPS_08_003.png | AC17: 1.0
A18: PSI-DT-08-004 | B18: 8 | C18: PSI | D18: Problem Solving & Innovation | E18: DT | F18: Design Thinking | G18: Design Thinking | H18: Select a user-centred design improvement | I18: Problem Solving Challenge | J18: Application-Based | K18: Easy | L18: Evaluate | M18: Problem Solving | N18: MCQ - Single Correct | O18: No | P18: A classroom dustbin has waste scattered around it, quite often. Which redesign best addresses the observed problem? | Q18: A wider opening with clear labels | R18: A taller decorative flag | S18: A darker colour only | T18: A locked lid with a key | U18: A | V18: A wider opening with clear labels | W18: A wider opening with clear labels is the best choice because it directly applies design thinking to the situation and addresses the stated need with a practical, responsible action. | X18: Builds practical problem solving for future study, work and responsible citizenship. | AC18: 1.0
A19: PSI-RA-08-005 | B19: 8 | C19: PSI | D19: Problem Solving & Innovation | E19: RA | F19: Resource Allocation | G19: Resource Allocation | H19: Use limited resources for maximum impact | I19: Innovation Scenario | J19: Application-Based | K19: Easy | L19: Create | M19: Problem Solving | N19: MCQ - Single Correct | O19: No | P19: A team has ₹500 to reduce water waste. A tap washer costs ₹50 and fixes one leaking tap; a poster costs ₹100. Five taps leak. What should the team prioritise? | Q19: Five posters | R19: Repair the five leaking taps | S19: One poster and no repairs | T19: Save all the money without acting | U19: B | V19: Repair the five leaking taps | W19: Repair the five leaking taps is the best choice because it directly applies resource allocation to the situation and addresses the stated need with a practical, responsible action. | X19: Builds practical problem solving for future study, work and responsible citizenship. | AC19: 1.0
A20: PSI-IAA-08-006 | B20: 8 | C20: PSI | D20: Problem Solving & Innovation | E20: IAA | F20: Innovation and Adaptability | G20: Innovation and Adaptability | H20: Adapt a solution after testing | I20: Situational MCQ | J20: Application-Based | K20: Easy | L20: Apply | M20: Problem Solving | N20: MCQ - Single Correct | O20: No | P20: A cardboard phone stand bends during testing. Which change is most likely to improve it? | Q20: Add more decoration | R20: Use thinner cardboard | S20: Add folded triangular supports | T20: Make the phone heavier | U20: C | V20: Add folded triangular supports | W20: Add folded triangular supports is the best choice because it directly applies innovation and adaptability to the situation and addresses the stated need with a practical, responsible action. | X20: Builds practical problem solving for future study, work and responsible citizenship. | AC20: 1.0
A21: PSI-DI-007 | B21: 8 | C21: PSI | D21: Problem Solving & Innovation | E21: DI | F21: Data-based Innovation | G21: Visual – bar chart of app usage | H21: Read a simple bar chart. | I21: Think | J21: Situation | K21: Medium | L21: Analyze | M21: Interpreting visual data. | N21: Visual | O21: Yes | P21: A bar chart shows a gaming app usage over a week. What does this suggest? | Q21: More students use the app toward the end of the week | R21: Students never use the app on week ends | S21: The app only works on Friday | T21: The chart has no meaning as night data is not mentioned | U21: A | V21: More students use the app toward the end of the week | W21: The tallest bar shows the highest usage level. | X21: Helps students understand how charts support decisions. | Y21: Bar chart showing app usage increasing from Monday to Friday. | Z21: Create a bar chart with days Monday to Friday and usage values rising across the week. | AA21: PSI_DI_Q7_bar_chart_usage.png | AC21: v1.0 | AD21: https://drive.google.com/file/d/1KY2pKd7sAoPVxCng0gRf9wSMTWcsXvHY/view?usp=drive_link
A22: PSI-PR-08-008 | B22: 8 | C22: PSI | D22: Problem Solving & Innovation | E22: PR | F22: Pattern Recognition | G22: Pattern Recognition | H22: Recognise a simple operational pattern | I22: Data Interpretation | J22: Application-Based | K22: Easy | L22: Analyze | M22: Problem Solving | N22: MCQ - Single Correct | O22: Yes | P22: A machine flashes colours in the order as shown in the image. What comes next if the pattern repeats? | Q22: Red | R22: Blue | S22: Green | T22: Yellow | U22: A | V22: Red | W22: Red is the best choice because it directly applies pattern recognition to the situation and addresses the stated need with a practical, responsible action. | X22: Builds practical problem solving for future study, work and responsible citizenship. | Y22: A clean Grade 8 educational table or chart illustrating: A machine flashes colours in this order: red, blue, blue, red, blue, blue. What comes next if the pattern repeats? | Z22: Create a clear, age-appropriate educational visual for Grade 8. Show only the information needed for this MCQ: A machine flashes colours in this order: red, blue, blue, red, blue, blue. What comes next if the pattern repeats? Use a light background, simple labels, high contrast, no answer clues, landscape 4:3. | AA22: PSI_PR_08_008.png | AC22: 1.0
A23: PSI-VAT-08-009 | B23: 8 | C23: PSI | D23: Problem Solving & Innovation | E23: VAT | F23: Validation and Trial | G23: Validation and Trial | H23: Choose an appropriate prototype test | I23: Visual Question | J23: Application-Based | K23: Easy | L23: Analyze | M23: Problem Solving | N23: MCQ - Single Correct | O23: Yes | P23: A team designs a low-cost reading lamp. Which test gives the most useful evidence? | Q23: Ask the designer whether it looks good | R23: Let several students use it and record findings | S23: Count how many stickers are on it | T23: Compare its body colour with another lamp | U23: B | V23: Let several students use it and record brightness, stability and heat | W23: Let several students use it and record brightness, stability and heat is the best choice because it directly applies validation and trial to the situation and addresses the stated need with a practical, responsible action. | X23: Builds practical problem solving for future study, work and responsible citizenship. | Y23: A clean Grade 8 educational real-life scene illustrating: A team designs a low-cost reading lamp. Which test gives the most useful evidence? | Z23: Create a clear, age-appropriate educational visual for Grade 8. Show only the information needed for this MCQ: A team designs a low-cost reading lamp. Which test gives the most useful evidence? Use a light background, simple labels, high contrast, no answer clues, landscape 4:3. | AA23: PSI_VAT_08_009.png | AC23: 1.0
A24: PSI-CAE-08-010 | B24: 8 | C24: PSI | D24: Problem Solving & Innovation | E24: CAE | F24: Cause and Effect | G24: Cause and Effect | H24: Separate symptoms from likely causes | I24: Problem Solving Challenge | J24: Application-Based | K24: Easy | L24: Evaluate | M24: Problem Solving | N24: MCQ - Single Correct | O24: No | P24: A classroom becomes very hot every afternoon. What is the best way to investigate the cause? | Q24: Buy new curtains and install AC | R24: Move the class permanently to a new place | S24: Measure ventilation and temperature at different times | T24: Switch off all lights for one minute to cool down | U24: C | V24: Measure ventilation and temperature at different times | W24: Measure sunlight, ventilation and temperature at different times is the best choice because it directly applies cause and effect to the situation and addresses the stated need with a practical, responsible action. | X24: Builds practical problem solving for future study, work and responsible citizenship. | AC24: 1.0
A25: PSI-DM-08-011 | B25: 8 | C25: PSI | D25: Problem Solving & Innovation | E25: DM | F25: Decision Making | G25: Decision Making | H25: Compare alternatives using agreed criteria | I25: Innovation Scenario | J25: Application-Based | K25: Easy | L25: Create | M25: Problem Solving | N25: MCQ - Single Correct | O25: No | P25: Three bridge models are scored out of 5: P—strength 5, cost 2; Q—strength 4, cost 4; R—strength 2, cost 5. If both strength and cost matter equally, which is the balanced choice? | Q25: P | R25: R | S25: All are equal | T25: Q | U25: D | V25: Q | W25: Q is the best choice because it directly applies decision making to the situation and addresses the stated need with a practical, responsible action. | X25: Builds practical problem solving for future study, work and responsible citizenship. | AC25: 1.0
A26: PSI-CPS-08-012 | B26: 8 | C26: PSI | D26: Problem Solving & Innovation | E26: CPS | F26: Creative Problem Solving | G26: Creative Problem Solving | H26: Generate a practical improvement under constraints | I26: Situational MCQ | J26: Application-Based | K26: Easy | L26: Apply | M26: Problem Solving | N26: MCQ - Single Correct | O26: No | P26: Students need a handwashing reminder where electricity is unavailable. Which solution is most suitable? | Q26: A waterproof flip-sign placed near the tap | R26: A television screen with big messsage | S26: A phone app with sound & internet | T26: A loudspeaker used all day with regular announcements | U26: A | V26: A waterproof flip-sign placed near the tap | W26: A waterproof flip-sign placed near the tap is the best choice because it directly applies creative problem solving to the situation and addresses the stated need with a practical, responsible action. | X26: Builds practical problem solving for future study, work and responsible citizenship. | AC26: 1.0
A27: ETDR-AR-08-001 | B27: 8 | C27: ETDR | D27: Emerging Technologies & Digital Readiness | E27: AR | F27: AI Responsibility | G27: AI Responsibility | H27: Use AI transparently and responsibly | I27: Case-Based Question | J27: Application-Based | K27: Easy | L27: Analyze | M27: Digital Readiness | N27: MCQ - Single Correct | O27: No | P27: Arjun uses an AI tool to suggest ideas for his science project. What should he do? | Q27: Submit the output from AI and boost of being smart | R27: Verify the facts, rewrite in his words and mention AI assistance | S27: Hide the use of AI from his teacher and use reasoning to claim own | T27: Give output to another AI and make it better | U27: B | V27: Check the facts, rewrite in his words and mention AI assistance | W27: Check the facts, rewrite in his words and mention AI assistance is the best choice because it directly applies ai responsibility to the situation and addresses the stated need with a practical, responsible action. | X27: Builds practical digital readiness for future study, work and responsible citizenship. | AC27: 1.0
A28: ETDR-CS-08-002 | B28: 8 | C28: ETDR | D28: Emerging Technologies & Digital Readiness | E28: CS | F28: Cyber Safety | G28: Cyber Safety | H28: Respond safely to a suspicious message | I28: Data Interpretation | J28: Application-Based | K28: Easy | L28: Analyze | M28: Digital Readiness | N28: MCQ - Single Correct | O28: Yes | P28: Abhishek receives this message on his mobile phone (refer to the image). What is the safest response? | Q28: Send only half the password | R28: Forward it to friends | S28: Do not reply; verify the message | T28: Click the link to see what happens | U28: C | V28: Do not reply; report and verify through the official app | W28: Do not reply; report and verify through the official app is the best choice because it directly applies cyber safety to the situation and addresses the stated need with a practical, responsible action. | X28: Builds practical digital readiness for future study, work and responsible citizenship. | Y28: A clean Grade 8 educational table or chart illustrating: A message says, “Your game account will close in 10 minutes—send your password now.” What is the safest response? | Z28: Create a clear, age-appropriate educational visual for Grade 8. Show only the information needed for this MCQ: A message says, “Your game account will close in 10 minutes—send your password now.” What is the safest response? Use a light background, simple labels, high contrast, no answer clues, landscape 4:3. | AA28: ETDR_CS_08_002.png | AC28: 1.0
A29: ETDR-CTL-08-010 | B29: 8 | C29: ETDR | D29: Emerging Technologies & Digital Readiness | E29: CTL | F29: Computational Thinking & Coding Logic | G29: Flowcharts | H29: Apply computational thinking to design a simple solution | I29: IMAGINE | J29: Future Oriented | K29: Hard | M29: Ability to read and interpret flowcharts | N29: Visual | O29: Yes | P29: Look at the flowchart on the whiteboard. What decision does this flowchart help the student make? | Q29: Enjoy the rain and go out | R29: Whether to take an umbrella before going outside | S29: Which umbrealla is best to use | T29: What time to leave for school in the morning | U29: B | V29: Whether to take an umbrella before going outside | W29: The flowchart shows a clear decision: if it is raining, take an umbrella; if not, go outside without one—helping decide whether to carry an umbrella. | X29: Flowcharts are visual tools used in coding and planning to map out decisions and processes—helping you think clearly before taking action. | Y29: An illustration showing a young Indian student standing next to a whiteboard. On the whiteboard, there is a simple flowchart with boxes and arrows showing steps: "Start" at the top, then an arrow to a diamond-shaped box with text "Is it raining?" Inside the diamond, there are two arrows coming out. One arrow labelled "Yes" leads to a rectangular box saying "Take umbrella". The other arrow labelled "No" leads to a rectangular box saying "Go outside". Both paths then join and lead to a final box saying "End". The student is pointing at the flowchart with a marker in hand. The background shows a classroom setting with a window showing a cloudy sky. | Z29: A colorful cartoon-style illustration of a 14-year-old Indian student standing next to a whiteboard in a classroom. On the whiteboard, a simple flowchart is drawn with boxes and arrows showing: "Start" at the top, then an arrow to a diamond-shaped box with text "Is it raining?" Inside the diamond, two arrows come out—one labelled "Yes" leading to a rectangular box "Take umbrella" and one labelled "No" leading to a rectangular box "Go outside". Both paths then join and lead to a final box "End". The student is pointing at the flowchart with a marker. The background shows a classroom with desks and a window with a cloudy sky. Bright, engaging, educational style for 14-year-olds. | AC29: 1.0 | AD29: https://drive.google.com/file/d/1ZxahvHgliTJBzsVxXkvLz7DNB7Mqmwjo/view?usp=drive_link
A30: ETDR-DP-08-004 | B30: 8 | C30: ETDR | D30: Emerging Technologies & Digital Readiness | E30: DP | F30: Digital Privacy | G30: Digital Privacy | H30: Choose privacy-protecting settings | I30: Problem Solving Challenge | J30: Application-Based | K30: Easy | L30: Evaluate | M30: Digital Readiness | N30: MCQ - Single Correct | O30: No | P30: Pooja's social media profile shows her phone number, home address, school name and hobby visible publicly. Which change is most important? | Q30: Hide personal contact and location details | R30: Add more photographs and interests | S30: Use a brighter & recent profile picture | T30: Invite friends to share their contact numbers & photos | U30: A | V30: Hide personal contact and location details | W30: Hide personal contact and location details is the best choice because it directly applies digital privacy to the situation and addresses the stated need with a practical, responsible action. | X30: Builds practical digital readiness for future study, work and responsible citizenship. | AC30: 1.0
A31: ETDR-CT-08-005 | B31: 8 | C31: ETDR | D31: Emerging Technologies & Digital Readiness | E31: CT | F31: Computational Thinking | G31: Computational Thinking | H31: Break a task into logical steps | I31: Innovation Scenario | J31: Application-Based | K31: Easy | L31: Create | M31: Digital Readiness | N31: MCQ - Single Correct | O31: No | P31: A robot must collect paper, avoid chairs and reach a bin. What should the programmer do first? | Q31: Write one long command and run the robot | R31: Break the task into smaller steps (sense, avoid, move) | S31: Study and remove non useful sensors | T31: Ask the robot to guess and operate on own | U31: B | V31: Break the task into sense, move, avoid and drop steps | W31: Break the task into sense, move, avoid and drop steps is the best choice because it directly applies computational thinking to the situation and addresses the stated need with a practical, responsible action. | X31: Builds practical digital readiness for future study, work and responsible citizenship. | AC31: 1.0
A32: ETDR-TFI-08-006 | B32: 8 | C32: ETDR | D32: Emerging Technologies & Digital Readiness | E32: TFI | F32: Technology for Inclusion | G32: Technology for Inclusion | H32: Select technology that improves accessibility | I32: Situational MCQ | J32: Application-Based | K32: Easy | L32: Apply | M32: Digital Readiness | N32: MCQ - Single Correct | O32: No | P32: Which feature best helps a visually impaired student use a learning website? | Q32: Flashing advertisements | R32: Tiny decorative text | S32: Screen-reader labels and keyboard navigation | T32: Automatic video sound | U32: C | V32: Screen-reader labels and keyboard navigation | W32: Screen-reader labels and keyboard navigation is the best choice because it directly applies technology for inclusion to the situation and addresses the stated need with a practical, responsible action. | X32: Builds practical digital readiness for future study, work and responsible citizenship. | AC32: 1.0
A33: ETDR-MD-08-007 | B33: 8 | C33: ETDR | D33: Emerging Technologies & Digital Readiness | E33: MD | F33: Misinformation Detection | G33: Misinformation Detection | H33: Verify an online claim before sharing | I33: Case-Based Question | J33: Application-Based | K33: Easy | L33: Analyze | M33: Digital Readiness | N33: MCQ - Single Correct | O33: No | P33: A viral post claims school is closed, but gives no source. What should a student do? | Q33: Share it quickly | R33: Believe it because many people liked it | S33: Add an exciting caption | T33: Check the official school channel before sharing | U33: D | V33: Check the official school channel before sharing | W33: Check the official school channel before sharing is the best choice because it directly applies misinformation detection to the situation and addresses the stated need with a practical, responsible action. | X33: Builds practical digital readiness for future study, work and responsible citizenship. | AC33: 1.0
A34: ETDR-DF-08-008 | B34: 8 | C34: ETDR | D34: Emerging Technologies & Digital Readiness | E34: DF | F34: Digital Footprint | G34: Digital Footprint | H34: Recognise the long-term effect of online actions | I34: Data Interpretation | J34: Application-Based | K34: Easy | L34: Analyze | M34: Digital Readiness | N34: MCQ - Single Correct | O34: Yes | P34: A person does this- copied, screenshotted and forwards a social media post. What lesson does it communicate? | Q34: Online posts can remain and spread even after deletion | R34: Deleted posts always disappear everywhere | S34: Only famous people have digital footprints | T34: Screenshots cannot be shared | U34: A | V34: Online posts can remain and spread even after deletion | W34: Online posts can remain and spread even after deletion is the best choice because it directly applies digital footprint to the situation and addresses the stated need with a practical, responsible action. | X34: Builds practical digital readiness for future study, work and responsible citizenship. | Y34: A clean Grade 8 educational table or chart illustrating: A diagram shows a post being copied, screenshotted and forwarded. What lesson does it communicate? | Z34: Create a clear, age-appropriate educational visual for Grade 8. Show only the information needed for this MCQ: A diagram shows a post being copied, screenshotted and forwarded. What lesson does it communicate? Use a light background, simple labels, high contrast, no answer clues, landscape 4:3. | AA34: ETDR_DF_08_008.png | AC34: 1.0
A35: ETDR-ET-08-009 | B35: 8 | C35: ETDR | D35: Emerging Technologies & Digital Readiness | E35: ET | F35: Emerging Technology | G35: Emerging Technology | H35: Match a technology to a useful application | I35: Visual Question | J35: Application-Based | K35: Easy | L35: Analyze | M35: Digital Readiness | N35: MCQ - Single Correct | O35: Yes | P35: A farmer wants to check crop health across a large field quickly. Which method/tool is most suitable? | Q35: A good running track in the field | R35: A camera-equipped drone | S35: A big team to go around and check the crop | T35: A barcode on the gate | U35: B | V35: A camera-equipped drone | W35: A camera-equipped drone is the best choice because it directly applies emerging technology to the situation and addresses the stated need with a practical, responsible action. | X35: Builds practical digital readiness for future study, work and responsible citizenship. | Y35: A clean Grade 8 educational real-life scene illustrating: A farmer wants to check crop health across a large field quickly. Which tool is most suitable? | Z35: Create a clear, age-appropriate educational visual for Grade 8. Show only the information needed for this MCQ: A farmer wants to check crop health across a large field quickly. Which tool is most suitable? Use a light background, simple labels, high contrast, no answer clues, landscape 4:3. | AA35: ETDR_ET_08_009.png | AC35: 1.0
A36: ETDR-DW-08-010 | B36: 8 | C36: ETDR | D36: Emerging Technologies & Digital Readiness | E36: DW | F36: Digital Wellbeing | G36: Digital Wellbeing | H36: Design a balanced technology routine | I36: Problem Solving Challenge | J36: Application-Based | K36: Easy | L36: Evaluate | M36: Digital Readiness | N36: MCQ - Single Correct | O36: No | P36: Which plan best supports healthy digital habits during study? | Q36: Keep every notification on | R36: Study with five entertainment tabs open | S36: Use focus mode, take timed breaks and keep the phone away | T36: Use the phone throughout the night | U36: C | V36: Use focus mode, take timed breaks and keep the phone away | W36: Use focus mode, take timed breaks and keep the phone away is the best choice because it directly applies digital wellbeing to the situation and addresses the stated need with a practical, responsible action. | X36: Builds practical digital readiness for future study, work and responsible citizenship. | AC36: 1.0
A37: FRG-CR-08-001 | B37: 8 | C37: FRG | D37: Future Readiness & Global Awareness | E37: CR | F37: Climate Responsibility | G37: Climate Responsibility | H37: Choose a locally effective climate action | I37: Innovation Scenario | J37: Application-Based | K37: Easy | L37: Create | M37: Global Awareness | N37: MCQ - Single Correct | O37: No | P37: A neighbourhood wants to reduce summer heat. Which action offers the broadest long-term benefit? | Q37: Paint every wall black | R37: Run outdoor coolers all day | S37: Remove soil and add concrete | T37: Plant and care for native shade trees | U37: D | V37: Plant and care for native shade trees | W37: Plant and care for native shade trees is the best choice because it directly applies climate responsibility to the situation and addresses the stated need with a practical, responsible action. | X37: Builds practical global awareness for future study, work and responsible citizenship. | AC37: 1.0
A38: FRG-GI-08-002 | B38: 8 | C38: FRG | D38: Future Readiness & Global Awareness | E38: GI | F38: Global Interdependence | G38: Global Interdependence | H38: Understand how events in one place affect others | I38: Situational MCQ | J38: Application-Based | K38: Easy | L38: Apply | M38: Global Awareness | N38: MCQ - Single Correct | O38: No | P38: A port delay causes imported computer parts to arrive late. What does this best show? | Q38: Global supply chains connect producers and buyers | R38: Countries are completely independent and do not need imports | S38: Only ports & shipping industry are affected by trade | T38: Local shops & manufacturers never depend on imports | U38: A | V38: Global supply chains connect producers and buyers | W38: Global supply chains connect producers and buyers is the best choice because it directly applies global interdependence to the situation and addresses the stated need with a practical, responsible action. | X38: Builds practical global awareness for future study, work and responsible citizenship. | AC38: 1.0
A39: FRG-FS-08-003 | B39: 8 | C39: FRG | D39: Future Readiness & Global Awareness | E39: FS | F39: Future Skills | G39: Future Skills | H39: Interpret information about changing work | I39: Case-Based Question | J39: Application-Based | K39: Easy | L39: Analyze | M39: Global Awareness | N39: MCQ - Single Correct | O39: No | P39: A chart shows demand rising for data analysis, communication and green-energy skills. Which plan best prepares a student? | Q39: Learn all 20 skills to prepare for everything | R39: Learning digital, communication and sustainability skills | S39: Learn technology usage and Driving skills for gig jobs | T39: Ignore new technology & advancements as they keep changing | U39: B | V39: Develop a mix of digital, communication and sustainability skills | W39: Develop a mix of digital, communication and sustainability skills is the best choice because it directly applies future skills to the situation and addresses the stated need with a practical, responsible action. | X39: Builds practical global awareness for future study, work and responsible citizenship. | AC39: 1.0
A40: FRG-CA-08-004 | B40: 8 | C40: FRG | D40: Future Readiness & Global Awareness | E40: CA | F40: Cultural Awareness | G40: Cultural Awareness | H40: Respond respectfully to cultural differences | I40: Data Interpretation | J40: Application-Based | K40: Easy | L40: Analyze | M40: Global Awareness | N40: MCQ - Single Correct | O40: Yes | P40: A group of students is meeting. What is the most respectful response | Q40: Make fun of unfamiliar food that they don't like | R40: Insist everyone eat the same food in a sequence | S40: Ask questions and learn about each tradition/food | T40: Avoid speaking to students from other cultures | U40: C | V40: Ask respectful questions and learn about each tradition | W40: Ask respectful questions and learn about each tradition is the best choice because it directly applies cultural awareness to the situation and addresses the stated need with a practical, responsible action. | X40: Builds practical global awareness for future study, work and responsible citizenship. | Y40: A clean Grade 8 educational table or chart illustrating: An image shows students from several countries sharing different festival foods. What is the most respectful response? | Z40: Create a clear, age-appropriate educational visual for Grade 8. Show only the information needed for this MCQ: An image shows students from several countries sharing different festival foods. What is the most respectful response? Use a light background, simple labels, high contrast, no answer clues, landscape 4:3. | AA40: FRG_CA_08_004.png | AC40: 1.0
A41: FRG-FWC-08-002 | B41: 8 | C41: FRG | D41: Future Readiness & Global Awareness | E41: FWC | F41: Future of Work, Careers & Lifelong Learning | G41: Future Skills | H41: Identify the skills that will remain valuable in the future workplace. | I41: KNOW (Foundation Knowledge) | J41: Knowledge Based | K41: Easy | M41: Collaboration & Problem Solving | N41: Visual | O41: Yes | P41: Look at the picture. Which student is demonstrating one of the most important future-ready skills? | Q41: Student A | R41: Student B | S41: Student C | T41: Student D | U41: B | V41: Student B | W41: Collaboration and problem-solving are considered among the most important future skills. | X41: The jobs of tomorrow will reward people who can work together to solve new and complex problems. | Y41: Four students are shown performing different activities: Student A memorizing a textbook Student B solving a puzzle with teammates Student C copying notes from another student Student D decorating a notebook | Z41: Flat vector illustration, educational style, white background. Four Grade-8 students shown in four equal panels. Panel A: student memorizing from a textbook. Panel B: two students collaborating to solve a puzzle using sticky notes. Panel C: student copying homework. Panel D: student decorating a notebook. Bright colors, clean design, no text inside the illustration. | AC41: 1.0 | AD41: https://drive.google.com/file/d/1WKJ4LSuTHsn2Ban-Ihu5wmVt3cgAGxgs/view?usp=drive_link
A42: FRG-CR-08-006 | B42: 8 | C42: FRG | D42: Future Readiness & Global Awareness | E42: CR | F42: Community Resilience | G42: Community Resilience | H42: Plan for a disruption using available resources | I42: Problem Solving Challenge | J42: Application-Based | K42: Easy | L42: Evaluate | M42: Global Awareness | N42: MCQ - Single Correct | O42: No | P42: Heavy rain may cut electricity for a day. Which school plan is most useful? | Q42: Prepare emergency lights and other measures | R42: Wait until the power fails and do not act | S42: Cancel all planning & activities | T42: Ask students & teachers to bring oil lamps | U42: A | V42: Prepare emergency lights, contacts and safe assembly procedures | W42: Prepare emergency lights, contacts and safe assembly procedures is the best choice because it directly applies community resilience to the situation and addresses the stated need with a practical, responsible action. | X42: Builds practical global awareness for future study, work and responsible citizenship. | AC42: 1.0
A43: FRG-GC-08-007 | B43: 8 | C43: FRG | D43: Future Readiness & Global Awareness | E43: GC | F43: Global Citizenship | G43: Global Citizenship | H43: Choose responsible action on a shared global issue | I43: Innovation Scenario | J43: Application-Based | K43: Easy | L43: Create | M43: Global Awareness | N43: MCQ - Single Correct | O43: No | P43: Students learn that electronic waste is often dumped unsafely. What is the best response? | Q43: Throw devices into general waste | R43: Use authorised e-waste collection and extend device life | S43: Burn old wires | T43: Buy a new device every year | U43: B | V43: Use authorised e-waste collection and extend device life | W43: Use authorised e-waste collection and extend device life is the best choice because it directly applies global citizenship to the situation and addresses the stated need with a practical, responsible action. | X43: Builds practical global awareness for future study, work and responsible citizenship. | AC43: 1.0
A44: FRG-A-08-008 | B44: 8 | C44: FRG | D44: Future Readiness & Global Awareness | E44: A | F44: Adaptability | G44: Adaptability | H44: Learn and adjust when future conditions change | I44: Situational MCQ | J44: Application-Based | K44: Easy | L44: Apply | M44: Global Awareness | N44: MCQ - Single Correct | O44: No | P44: A timeline shows a student learning spreadsheet skills, receiving feedback, practising, and improving. Which future-ready quality is shown? | Q44: Avoiding change as feedback is not good | R44: Working on an Excel sheet is the most important skill | S44: Adaptability through continuous learning | T44: Waiting for perfect instructions from teacher | U44: C | V44: Adaptability through continuous learning | W44: Adaptability through continuous learning is the best choice because it directly applies adaptability to the situation and addresses the stated need with a practical, responsible action. | X44: Builds practical global awareness for future study, work and responsible citizenship. | AC44: 1.0
A45: FRD-B-08-001 | B45: 8 | C45: FRD | D45: Financial Readiness | E45: B | F45: Budgeting | G45: Budgeting | H45: Distinguish needs from wants in a limited budget | I45: Case-Based Question | J45: Application-Based | K45: Easy | L45: Analyze | M45: Financial Awareness | N45: MCQ - Single Correct | O45: No | P45: Meera has ₹500. She needs a notebook for ₹120 and bus fare of ₹200, and wants headphones for ₹350. What is the wisest choice? | Q45: Buy headphones first | R45: Borrow money for all three | S45: Spend everything on snacks | T45: Pay for the notebook and bus fare, then save the rest | U45: D | V45: Pay for the notebook and bus fare, then save the rest | W45: Pay for the notebook and bus fare, then save the rest is the best choice because it directly applies budgeting to the situation and addresses the stated need with a practical, responsible action. | X45: Builds practical financial awareness for future study, work and responsible citizenship. | AC45: 1.0
A46: FRD-SG-08-002 | B46: 8 | C46: FRD | D46: Financial Readiness | E46: SG | F46: Saving Goals | G46: Saving Goals | H46: Make a simple saving plan | I46: Data Interpretation | J46: Application-Based | K46: Easy | L46: Analyze | M46: Financial Awareness | N46: MCQ - Single Correct | O46: Yes | P46: Study the image. How much should be saved each month to achieve the goal? | Q46: ₹100 | R46: ₹50 | S46: ₹75 | T46: ₹150 | U46: A | V46: ₹100 | W46: ₹100 is the best choice because it directly applies saving goals to the situation and addresses the stated need with a practical, responsible action. | X46: Builds practical financial awareness for future study, work and responsible citizenship. | Y46: A clean Grade 8 educational table or chart illustrating: A student wants ₹600 for a course in six months. How much should be saved each month? | Z46: Create a clear, age-appropriate educational visual for Grade 8. Show only the information needed for this MCQ: A student wants ₹600 for a course in six months. How much should be saved each month? Use a light background, simple labels, high contrast, no answer clues, landscape 4:3. | AA46: FRD_SG_08_002.png | AC46: 1.0
A47: FRD-PC-08-003 | B47: 8 | C47: FRD | D47: Financial Readiness | E47: PC | F47: Price Comparison | G47: Price Comparison | H47: Compare value using unit prices | I47: Visual Question | J47: Application-Based | K47: Easy | L47: Analyze | M47: Financial Awareness | N47: MCQ - Single Correct | O47: Yes | P47: Study the chart. Which pack has the lower cost per pen? | Q47: The 5-pen pack | R47: The 8-pen pack | S47: Both cost the same per pen | T47: There is not enough information | U47: B | V47: The 8-pen pack | W47: The 8-pen pack is the best choice because it directly applies price comparison to the situation and addresses the stated need with a practical, responsible action. | X47: Builds practical financial awareness for future study, work and responsible citizenship. | Y47: A clean Grade 8 educational real-life scene illustrating: A chart shows 5 pens for ₹50 and 8 similar pens for ₹72. Which pack has the lower cost per pen? | Z47: Create a clear, age-appropriate educational visual for Grade 8. Show only the information needed for this MCQ: A chart shows 5 pens for ₹50 and 8 similar pens for ₹72. Which pack has the lower cost per pen? Use a light background, simple labels, high contrast, no answer clues, landscape 4:3. | AA47: FRD_PC_08_003.png | AC47: 1.0
A48: FRD-DPS-08-004 | B48: 8 | C48: FRD | D48: Financial Readiness | E48: DPS | F48: Digital Payment Safety | G48: Digital Payment Safety | H48: Protect financial information during payment | I48: Problem Solving Challenge | J48: Application-Based | K48: Easy | L48: Evaluate | M48: Financial Awareness | N48: MCQ - Single Correct | O48: No | P48: A caller asks Raja for an OTP to “confirm a refund.” What should the account holder do? | Q48: Share it if the caller sounds polite | R48: Share only the last two digits | S48: Never share the OTP | T48: Post the OTP in the help chat | U48: C | V48: Never share the OTP and contact the bank through an official channel | W48: Never share the OTP and contact the bank through an official channel is the best choice because it directly applies digital payment safety to the situation and addresses the stated need with a practical, responsible action. | X48: Builds practical financial awareness for future study, work and responsible citizenship. | AC48: 1.0
A49: FRD-IAE-08-005 | B49: 8 | C49: FRD | D49: Financial Readiness | E49: IAE | F49: Income and Expense | G49: Income and Expense | H49: Calculate remaining money after expenses | I49: Innovation Scenario | J49: Application-Based | K49: Easy | L49: Create | M49: Financial Awareness | N49: MCQ - Single Correct | O49: No | P49: Kabir earns ₹800 from a weekend project and spends ₹250 on materials and ₹150 on travel. How much remains? | Q49: ₹300 | R49: ₹500 | S49: ₹600 | T49: ₹400 | U49: D | V49: ₹400 | W49: ₹400 is the best choice because it directly applies income and expense to the situation and addresses the stated need with a practical, responsible action. | X49: Builds practical financial awareness for future study, work and responsible citizenship. | AC49: 1.0
A50: FRD-FR-08-006 | B50: 8 | C50: FRD | D50: Financial Readiness | E50: FR | F50: Financial Risk | G50: Financial Risk | H50: Choose a low-risk response to an unrealistic offer | I50: Situational MCQ | J50: Application-Based | K50: Easy | L50: Apply | M50: Financial Awareness | N50: MCQ - Single Correct | O50: No | P50: An online ad promises to double money in two days with “zero risk.” What should a student do? | Q50: Avoid it and discuss it with a trusted adult | R50: Invest immediately and wait for the results | S50: Borrow money from friends to invest more | T50: Share it with classmates & invite them to earn more money | U50: A | V50: Avoid it and discuss it with a trusted adult | W50: Avoid it and discuss it with a trusted adult is the best choice because it directly applies financial risk to the situation and addresses the stated need with a practical, responsible action. | X50: Builds practical financial awareness for future study, work and responsible citizenship. | AC50: 1.0
A51: FRD-RB-08-007 | B51: 8 | C51: FRD | D51: Financial Readiness | E51: RB | F51: Responsible Borrowing | G51: Responsible Borrowing | H51: Understand the obligation created by borrowing | I51: Case-Based Question | J51: Application-Based | K51: Easy | L51: Analyze | M51: Financial Awareness | N51: MCQ - Single Correct | O51: No | P51: A student borrows ₹300 from a friend for a necessary book. Which action is most responsible? | Q51: Avoid mentioning repayment | R51: Agree on when and how the money will be repaid | S51: Borrow from another friend to buy a game | T51: Promise an amount that cannot be paid | U51: B | V51: Agree on when and how the money will be repaid | W51: Agree on when and how the money will be repaid is the best choice because it directly applies responsible borrowing to the situation and addresses the stated need with a practical, responsible action. | X51: Builds practical financial awareness for future study, work and responsible citizenship. | AC51: 1.0
